Workbook

Sheet lista
A1: Codigo | B1: Descripcion | C1: P. nuevo
B2: BLANCO SEIN 40 X 50 | C2: 27511 | E2: 0 | F2: =ROUND(C2,0) -> 27511 | H2: =_xlfn.XLOOKUP(A2,Hoja1!A:A,Hoja1!G:G,0,0) -> #NAME?
A3: 0001BCO00003 | B3: BLANCO SEIN 64 X 90 | C3: 27511 | E3: 0 | F3: =ROUND(C3,0) -> 27511 | H3: =_xlfn.XLOOKUP(A3,Hoja1!A:A,Hoja1!G:G,0,0) -> #NAME?
A4: 0001BCO00004 | B4: BLANCO SEIN 64 X 45 | C4: 27511 | E4: 0 | F4: =ROUND(C4,0) -> 27511 | H4: =_xlfn.XLOOKUP(A4,Hoja1!A:A,Hoja1!G:G,0,0) -> #NAME?
A5: 0001BCO00005 | B5: BLANCO SEIN 32 X 45 | C5: 27511 | E5: 0 | F5: =ROUND(C5,0) -> 27511 | H5: =_xlfn.XLOOKUP(A5,Hoja1!A:A,Hoja1!G:G,0,0) -> #NAME?
A6: 0001BCO00006 | B6: BLANCO SEIN 52 X 72 | C6: 27511 | E6: 0 | F6: =ROUND(C6,0) -> 27511 | H6: =_xlfn.XLOOKUP(A6,Hoja1!A:A,Hoja1!G:G,0,0) -> #NAME?
A7: 0001BCO00007 | B7: BLANCO SEIN 52 X 36 | C7: 27511 | E7: 0 | F7: =ROUND(C7,0) -> 27511 | H7: =_xlfn.XLOOKUP(A7,Hoja1!A:A,Hoja1!G:G,0,0) -> #NAME?
A8: 0001BCO00008 | B8: BLANCO SEIN 26 X 36 | C8: 27511 | E8: 0 | F8: =ROUND(C8,0) -> 27511 | H8: =_xlfn.XLOOKUP(A8,Hoja1!A:A,Hoja1!G:G,0,0) -> #NAME?
A9: 0001BCO00009 | B9: BLANCO SEIN 26 X 18 | C9: 27511 | E9: 0 | F9: =ROUND(C9,0) -> 27511 | H9: =_xlfn.XLOOKUP(A9,Hoja1!A:A,Hoja1!G:G,0,0) -> #NAME?
A10: 0001BCO00010 | B10: BLANCO SEIN 58 X 81 | C10: 27511 | E10: 0 | F10: =ROUND(C10,0) -> 27511 | H10: =_xlfn.XLOOKUP(A10,Hoja1!A:A,Hoja1!G:G,0,0) -> #NAME?
A11: 0001BCO00011 | B11: BLANCO SEIN 58 X 40 | C11: 27511 | E11: 0 | F11: =ROUND(C11,0) -> 27511 | H11: =_xlfn.XLOOKUP(A11,Hoja1!A:A,Hoja1!G:G,0,0) -> #NAME?
A12: 0001BCO00014 | B12: BLANCO SEIN 9 X 13 PIZZERO | C12: 27511 | E12: 0 | F12: =ROUND(C12,0) -> 27511 | H12: =_xlfn.XLOOKUP(A12,Hoja1!A:A,Hoja1!G:G,0,0) -> #NAME?
A13: 0001BCO00015 | B13: BLANCO SEIN 30 X 40 | C13: 27511 | E13: 0 | F13: =ROUND(C13,0) -> 27511 | H13: =_xlfn.XLOOKUP(A13,Hoja1!A:A,Hoja1!G:G,0,0) -> #NAME?
A14: 0001BCP00002 | B14: SULFITO PRIMERA 40 X 50 | C14: 36341 | E14: 0 | F14: =ROUND(C14,0) -> 36341 | H14: =_xlfn.XLOOKUP(A14,Hoja1!A:A,Hoja1!G:G,0,0) -> #NAME?
... A81: 0012COM00006 | B81: BANDEJA DE CARTON Nº 6 21X29 | C81: 12216 | E81: 0.15 | F81: =ROUND(C81,0) -> 12216 | H81: =_xlfn.XLOOKUP(A81,Hoja1!A:A,Hoja1!G:G,0,0) -> #NAME?
A82: 0012COM00051 | B82: BANDEJA KRAFT PURO N°1 (6PX100U) | C82: 15561 | F82: =ROUND(C82,0) -> 15561 | H82: =_xlfn.XLOOKUP(A82,Hoja1!A:A,Hoja1!G:G,0,0) -> #NAME?
A83: 0012COM00052 | B83: BANDEJA KRAFT PURO N°2 (6PX100U) | C83: 37544 | E83: 0.07 | F83: =ROUND(C83,0) -> 37544 | H83: =_xlfn.XLOOKUP(A83,Hoja1!A:A,Hoja1!G:G,0,0) -> #NAME?
A84: 0012COM00053 | B84: BANDEJA KRAFT PURO N°3 (4PX100U) | C84: 32214 | F84: =ROUND(C84,0) -> 32214 | H84: =_xlfn.XLOOKUP(A84,Hoja1!A:A,Hoja1!G:G,0,0) -> #NAME?
A85: 0012COM00054 | B85: BANDEJA KRAFT PURO N°4 (2PX100U) | C85: 20915 | F85: =ROUND(C85,0) -> 20915 | H85: =_xlfn.XLOOKUP(A85,Hoja1!A:A,Hoja1!G:G,0,0) -> #NAME?
A86: 0012COM10002 | B86: BANDEJA MICRO CORRUGADO N° 2 (4PX100U) | C86: 22142 | E86: 0.07 | F86: =ROUND(C86,0) -> 22142 | H86: =_xlfn.XLOOKUP(A86,Hoja1!A:A,Hoja1!G:G,0,0) -> #NAME?
A87: 0012COM10003 | B87: BANDEJA MICRO CORRUGADO N° 3 (4PX100U) | C87: 25437 | E87: 0.07 | F87: =ROUND(C87,0) -> 25437 | H87: =_xlfn.XLOOKUP(A87,Hoja1!A:A,Hoja1!G:G,0,0) -> #NAME?
A88: 0012COM10004 | B88: BANDEJA MICRO CORRUGADO N° 4 (4PX100U) | C88: 33184 | E88: 0 | F88: =ROUND(C88,0) -> 33184 | H88: =_xlfn.XLOOKUP(A88,Hoja1!A:A,Hoja1!G:G,0,0) -> #NAME?
A89: 0012COM10005 | B89: BANDEJA MICRO CORRUGADO N° 5 (2PX100U) | C89: 21092 | E89: 0.03 | F89: =ROUND(C89,0) -> 21092 | H89: =_xlfn.XLOOKUP(A89,Hoja1!A:A,Hoja1!G:G,0,0) -> #NAME?
A90: 0012COM10006 | B90: BANDEJA MICRO CORRUGADO N° 6 (4P X 50U) | C90: 18340 | E90: 0.02 | F90: =ROUND(C90,0) -> 18340 | H90: =_xlfn.XLOOKUP(A90,Hoja1!A:A,Hoja1!G:G,0,0) -> #NAME?
A91: 0012COM10012 | B91: BANDEJA MICRO CORRUGADO N°2 IMPRESA | C91: 37414 | E91: 0.03 | F91: =ROUND(C91,0) -> 37414 | H91: =_xlfn.XLOOKUP(A91,Hoja1!A:A,Hoja1!G:G,0,0) -> #NAME?
A92: 0012COM10013 | B92: BANDEJA MICRO CORRUGADO N°3 IMPRESA | C92: 43394 | E92: 0.02 | F92: =ROUND(C92,0) -> 43394 | H92: =_xlfn.XLOOKUP(A92,Hoja1!A:A,Hoja1!G:G,0,0) -> #NAME?
A93: 0012COM10014 | B93: BANDEJA MICRO CORRUGADO N°4 IMPRESA | C93: 54601 | E93: 0.02 | F93: =ROUND(C93,0) -> 54601 | H93: =_xlfn.XLOOKUP(A93,Hoja1!A:A,Hoja1!G:G,0,0) -> #NAME?
A94: 0012COM10015 | B94: BANDEJA MICRO CORRUGADO N°5 IMPRESA | C94: 33720 | E94: 0.02 | F94: =ROUND(C94,0) -> 33720 | H94: =_xlfn.XLOOKUP(A94,Hoja1!A:A,Hoja1!G:G,0,0) -> #NAME?
A95: 0012COM10016 | B95: BANDEJA MICRO CORRUGADO N°6 IMPRESA | C95: 28301 | E95: 0.02 | F95: =ROUND(C95,0) -> 28301 | H95: =_xlfn.XLOOKUP(A95,Hoja1!A:A,Hoja1!G:G,0,0) -> #NAME?
A96: 0012COM10017 | B96: BANDEJA MICRO CORRUGADO N°7 IMPRESA | C96: 34372 | E96: 0.02 | F96: =ROUND(C96,0) -> 34372 | H96: =_xlfn.XLOOKUP(A96,Hoja1!A:A,Hoja1!G:G,0,0) -> #NAME?
A97: 0013COM00016 | B97: DISCO DE CARTON 16 CM (X 5KG) | C97: 24235 | E97: 0.02 | F97: =ROUND(C97,0) -> 24235 | H97: =_xlfn.XLOOKUP(A97,Hoja1!A:A,Hoja1!G:G,0,0) -> #NAME?
... A124: 0018DARBK0066 | B124: CAJA PARA ALIMENTOS DARNEL NATURAL 66 Oz MOCA PQX50 CJX200 | C124: 74222 | E124: 0 | F124: =ROUND(C124,0) -> 74222 | H124: =_xlfn.XLOOKUP(A124,Hoja1!A:A,Hoja1!G:G,0,0) -> #NAME?
A125: 0018DARBKF0001 | B125: CAJA PEQUEÑA PARA PAPAS FRITAS DARNEL NATURAL MOCA PQX100 CJX600 | C125: 29445 | F125: =ROUND(C125,0) -> 29445 | H125: =_xlfn.XLOOKUP(A125,Hoja1!A:A,Hoja1!G:G,0,0) -> #NAME?
A126: 0018DARBKS0049 | B126: CAJA PARA ALIMENTOS SAFETYPLUS DARNEL NATURAL 49 Oz MOCA PQX50CJX200 | C126: 72723 | E126: 0 | F126: =ROUND(C126,0) -> 72723 | H126: =_xlfn.XLOOKUP(A126,Hoja1!A:A,Hoja1!G:G,0,0) -> #NAME?
A127: 0018DARBKS0066 | B127: CAJA PARA ALIMENTOS SAFETYPLUS DARNEL NAT 66oz MOCA PQX50 CJX200 | C127: 79883 | E127: 0 | F127: =ROUND(C127,0) -> 79883 | H127: =_xlfn.XLOOKUP(A127,Hoja1!A:A,Hoja1!G:G,0,0) -> #NAME?
A128: 0018DARBKS026 | B128: CAJA PARA ALIMENTOS SAFETYPLUS DARNEL NATURAL 26 Oz MOCA PQX50 CAJX200 | C128: 45268 | E128: 0 | F128: =ROUND(C128,0) -> 45268 | H128: =_xlfn.XLOOKUP(A128,Hoja1!A:A,Hoja1!G:G,0,0) -> #NAME?
A129: 0018DARBKS045 | B129: CAJA ALIMENTOS SAFETYPLUS DARNEL NATURALS 45 Oz MOCA PQX50 CAJX200 | C129: 67623 | E129: 0 | F129: =ROUND(C129,0) -> 67623 | H129: =_xlfn.XLOOKUP(A129,Hoja1!A:A,Hoja1!G:G,0,0) -> #NAME?
A130: 0018DARKH0001 | B130: CAJA PEQUEÑA PARA HAMBURGUESA DARNEL NATURAL MOCA PAQX50 CAJ X300UNI | C130: 44059 | E130: 0 | F130: =ROUND(C130,0) -> 44059 | H130: =_xlfn.XLOOKUP(A130,Hoja1!A:A,Hoja1!G:G,0,0) -> #NAME?
A131: 0018DARKH0005 | B131: CAJA MEDIANA PARA HAMBURGUESA DARNEL NATURAL MOCA PAQX50 CAJ X300 UNI | C131: 45245 | E131: 0 | F131: =ROUND(C131,0) -> 45245 | H131: =_xlfn.XLOOKUP(A131,Hoja1!A:A,Hoja1!G:G,0,0) -> #NAME?
A132: 0018DARKH0010 | B132: CAJA GRANDE PARA HAMBURGUESA DARNEL NATURAL MOCA PAQX50 CAJX300 | C132: 55794 | E132: 0 | F132: =ROUND(C132,0) -> 55794 | H132: =_xlfn.XLOOKUP(A132,Hoja1!A:A,Hoja1!G:G,0,0) -> #NAME?
A133: 0018ESP00003 | B133: ESTUCHES PAPAS FRITAS GDE. | C133: 15059 | E133: 0 | F133: =ROUND(C133,0) -> 15059 | H133: =_xlfn.XLOOKUP(A133,Hoja1!A:A,Hoja1!G:G,0,0) -> #NAME?
A134: 0018ESP00004 | B134: ESTUCHES PAPAS FRITAS KRAFT X 1000 | C134: 97504 | E134: 0 | F134: =ROUND(C134,0) -> 97504 | H134: =_xlfn.XLOOKUP(A134,Hoja1!A:A,Hoja1!G:G,0,0) -> #NAME?
A135: 0018ESV00003 | B135: PORTAVASO DE CARTULINA | C135: 54611 | E135: 0 | F135: =ROUND(C135,0) -> 54611 | H135: =_xlfn.XLOOKUP(A135,Hoja1!A:A,Hoja1!G:G,0,0) -> #NAME?
A136: 0021ARR02026 | B136: ARRANQUE A.D. 20X25 (750 GR.) | C136: 3948 | E136: 0 | F136: =ROUND(C136,0) -> 3948 | H136: =_xlfn.XLOOKUP(A136,Hoja1!A:A,Hoja1!G:G,0,0) -> #NAME?
A137: 0021ARR02030 | B137: ARRANQUE A.D. 20X30 (1.5 KG.) | C137: 16733 | E137: 0 | F137: =ROUND(C137,0) -> 16733 | H137: =_xlfn.XLOOKUP(A137,Hoja1!A:A,Hoja1!G:G,0,0) -> #NAME?
... A151: 0027AUT00045 | B151: PVC AUTOMATICO 18" FV 50 | C151: 81973 | E151: 1.5 | F151: =ROUND(C151,0) -> 81973 | H151: =_xlfn.XLOOKUP(A151,Hoja1!A:A,Hoja1!G:G,0,0) -> #NAME?
A152: 0027BIO00300 | B152: PVC BIO TAMI 300 X 1400 MTS | C152: 35879 | F152: =ROUND(C152,0) -> 35879 | H152: =_xlfn.XLOOKUP(A152,Hoja1!A:A,Hoja1!G:G,0,0) -> #NAME?
A153: 0027BIO00380 | B153: PVC BIO TAMI 380 X 1400 MTS | C153: 45017 | F153: =ROUND(C153,0) -> 45017 | H153: =_xlfn.XLOOKUP(A153,Hoja1!A:A,Hoja1!G:G,0,0) -> #NAME?
A154: 0027BIO00450 | B154: PVB BIO TAMI 450 X 1400 MTS | C154: 52940 | F154: =ROUND(C154,0) -> 52940 | H154: =_xlfn.XLOOKUP(A154,Hoja1!A:A,Hoja1!G:G,0,0) -> #NAME?
A155: 0027BIO28100 | B155: PVC BIO DARNEL WRAP 31X28X100MTS | C155: 3157 | E155: 0.12 | F155: =ROUND(C155,0) -> 3157 | H155: =_xlfn.XLOOKUP(A155,Hoja1!A:A,Hoja1!G:G,0,0) -> #NAME?
A156: 0027BIO28300 | B156: PVC BIO DARNEL WRAP 31X28X300 MTS C/CORT | C156: 9905 | E156: 0.12 | F156: =ROUND(C156,0) -> 9905 | H156: =_xlfn.XLOOKUP(A156,Hoja1!A:A,Hoja1!G:G,0,0) -> #NAME?
A157: 0027BIO38100 | B157: PVC BIO DARNEL WRAP 35X38X1000 MTS | C157: 33577 | E157: 0.12 | F157: =ROUND(C157,0) -> 33577 | H157: =_xlfn.XLOOKUP(A157,Hoja1!A:A,Hoja1!G:G,0,0) -> #NAME?
A158: 0027EST00012 | B158: PVC 12 " (X 1400 MTS.) | C158: 34508 | E158: 0.12 | F158: =ROUND(C158,0) -> 34508 | H158: =_xlfn.XLOOKUP(A158,Hoja1!A:A,Hoja1!G:G,0,0) -> #NAME?
A159: 0027EST00015 | B159: PVC 15 " (X 1400 MTS.) | C159: 43780 | E159: 0.12 | F159: =ROUND(C159,0) -> 43780 | H159: =_xlfn.XLOOKUP(A159,Hoja1!A:A,Hoja1!G:G,0,0) -> #NAME?
A160: 0027EST00018 | B160: PVC 18 " (X 1400 MTS.) | C160: 51888 | E160: 0.12 | F160: =ROUND(C160,0) -> 51888 | H160: =_xlfn.XLOOKUP(A160,Hoja1!A:A,Hoja1!G:G,0,0) -> #NAME?
A161: 0027EST00022 | B161: PVC 400 MM (X 1400 MTS.) | C161: 49713 | E161: 0.12 | F161: =ROUND(C161,0) -> 49713 | H161: =_xlfn.XLOOKUP(A161,Hoja1!A:A,Hoja1!G:G,0,0) -> #NAME?
A162: 0027EST01015 | B162: PVC 15" (X1200 MTS) | C162: 41373 | E162: 0.12 | F162: =ROUND(C162,0) -> 41373 | H162: =_xlfn.XLOOKUP(A162,Hoja1!A:A,Hoja1!G:G,0,0) -> #NAME?
A163: 0027EST01018 | B163: PVC 18" (X1200 MTS) | C163: 49066 | E163: 0.12 | F163: =ROUND(C163,0) -> 49066 | H163: =_xlfn.XLOOKUP(A163,Hoja1!A:A,Hoja1!G:G,0,0) -> #NAME?
A164: 0027EST02018 | B164: PVC 18" (X1200 MTS) SUP | C164: 48980 | E164: 0.12 | F164: =ROUND(C164,0) -> 48980 | H164: =_xlfn.XLOOKUP(A164,Hoja1!A:A,Hoja1!G:G,0,0) -> #NAME?
A165: 0027LIG00030 | B165: PVC X 500 MTS. 12" | C165: 13086 | E165: 0.12 | F165: =ROUND(C165,0) -> 13086 | H165: =_xlfn.XLOOKUP(A165,Hoja1!A:A,Hoja1!G:G,0,0) -> #NAME?
A166: 0027LIG00038 | B166: PVC X 500 MTS. 15" | C166: 16171 | E166: 0.12 | F166: =ROUND(C166,0) -> 16171 | H166: =_xlfn.XLOOKUP(A166,Hoja1!A:A,Hoja1!G:G,0,0) -> #NAME?
... A268: 0034DARC0006 | B268: +CONTENEDOR ESPUMADO 6 Oz BLANCO PQX20 CJ X1000 | C268: 89744 | E268: 0 | F268: =ROUND(C268,0) -> 89744 | H268: =_xlfn.XLOOKUP(A268,Hoja1!A:A,Hoja1!G:G,0,0) -> #NAME?
A269: 0034DARC0008 | B269: +CONTENEDOR ESPUMADO 8 Oz BLANCO PQX20 CAJX1000 | C269: 110300 | D269: 0.89537111 | F269: =ROUND(C269,0) -> 110300 | H269: =_xlfn.XLOOKUP(A269,Hoja1!A:A,Hoja1!G:G,0,0) -> #NAME?
A270: 0034DARC0012 | B270: +CONTENEDOR ESPUMADO 12 Oz BLANCO PQX20 CAJX1000 | C270: 129941 | F270: =ROUND(C270,0) -> 129941 | H270: =_xlfn.XLOOKUP(A270,Hoja1!A:A,Hoja1!G:G,0,0) -> #NAME?
A271: 0034DARC0016 | B271: +CONTENEDOR ESPUMADO 16 Oz BLANCO PQX20 CAJX500 | C271: 107146 | E271: 0.1 | F271: =ROUND(C271,0) -> 107146 | H271: =_xlfn.XLOOKUP(A271,Hoja1!A:A,Hoja1!G:G,0,0) -> #NAME?
A272: 0034DARPB001 | B272: PORTACOMIDA WAVE BIODEGRADABLE JL-1 DARNEL BIO BLX200 | C272: 45748 | E272: 0.1 | F272: =ROUND(C272,0) -> 45748 | H272: =_xlfn.XLOOKUP(A272,Hoja1!A:A,Hoja1!G:G,0,0) -> #NAME?
A273: 0034DARPB002 | B273: PORTACOMIDAS WAVE BIODEGRADABLE J-1M DARNEL BIO BLX200 | C273: 49737 | E273: 0.11 | F273: =ROUND(C273,0) -> 49737 | H273: =_xlfn.XLOOKUP(A273,Hoja1!A:A,Hoja1!G:G,0,0) -> #NAME?
A274: 0034DARPB003 | B274: PORTACOMIDAS WAVE BIODEGRADABLE P-1 DARNEL BIO BLX200 | C274: 52087 | E274: 0.06 | F274: =ROUND(C274,0) -> 52087 | H274: =_xlfn.XLOOKUP(A274,Hoja1!A:A,Hoja1!G:G,0,0) -> #NAME?
A275: 0034DARPB004 | B275: PORTACOMIDAS WAVE BIODEGRADABLE P-3 CON 3 DIVISIONES DARNEL BIO BLX200 | C275: 50977 | E275: 0.12 | F275: =ROUND(C275,0) -> 50977 | H275: =_xlfn.XLOOKUP(A275,Hoja1!A:A,Hoja1!G:G,0,0) -> #NAME?
A276: 0034DARPBE006 | B276: BOWL ESPUMADO 6 Oz BLANCO PQX20 CAJ X1000 | C276: 90158 | E276: 0.13 | F276: =ROUND(C276,0) -> 90158 | H276: =_xlfn.XLOOKUP(A276,Hoja1!A:A,Hoja1!G:G,0,0) -> #NAME?
A277: 0034DARPBE012 | B277: BOWL ESPUMADO 12 Oz BLANCO PQX20 CAJX1000 | C277: 136153 | E277: 0.12 | F277: =ROUND(C277,0) -> 136153 | H277: =_xlfn.XLOOKUP(A277,Hoja1!A:A,Hoja1!G:G,0,0) -> #NAME?
A278: 0034DARPBE108 | B278: BOWL ESPUMADO BAJO 8 Oz PQX20 CAJX1000 | C278: 97269 | E278: 0.07 | F278: =ROUND(C278,0) -> 97269 | H278: =_xlfn.XLOOKUP(A278,Hoja1!A:A,Hoja1!G:G,0,0) -> #NAME?
A279: 0034DARPW0015 | B279: PLATO MWAVE 15.5 CM BLANCO PQX20 CAJ 480 | C279: 22123 | E279: 0.12 | F279: =ROUND(C279,0) -> 22123 | H279: =_xlfn.XLOOKUP(A279,Hoja1!A:A,Hoja1!G:G,0,0) -> #NAME?
A280: 0034DARPW0023 | B280: PLATO WAVE 23 CM BLANCO PQX20 CAJ 480 | C280: 43919 | E280: 0.11 | F280: =ROUND(C280,0) -> 43919 | H280: =_xlfn.XLOOKUP(A280,Hoja1!A:A,Hoja1!G:G,0,0) -> #NAME?
A281: 0034DARPWH05 | B281: PLATO WAVE 5 Oz HONDO BLANCO PQX20 CAJX480 | C281: 15646 | E281: 0.1 | F281: =ROUND(C281,0) -> 15646 | H281: =_xlfn.XLOOKUP(A281,Hoja1!A:A,Hoja1!G:G,0,0) -> #NAME?
A282: 0035DAR00004 | B282: VASO ESPUMADO 4 Oz BLANCO PQX40 CAJX2000 | C282: 125636 | F282: =ROUND(C282,0) -> 125636 | H282: =_xlfn.XLOOKUP(A282,Hoja1!A:A,Hoja1!G:G,0,0) -> #NAME?
A283: 0035DAR00006 | B283: #VASO ESPUMADO 6 OzBLANCO PQX40 CAJ X2000 | C283: 143738 | E283: 0 | F283: =ROUND(C283,0) -> 143738 | H283: =_xlfn.XLOOKUP(A283,Hoja1!A:A,Hoja1!G:G,0,0) -> #NAME?
A284: 0035DAR00008 | B284: VASO ESPUMADO 8 Oz BLANCO PQX20 CAJX1000 | C284: 79579 | E284: 0 | F284: =ROUND(C284,0) -> 79579 | H284: =_xlfn.XLOOKUP(A284,Hoja1!A:A,Hoja1!G:G,0,0) -> #NAME?
A285: 0035DARB0006 | B285: VASO ESPUMADO 6 Oz BIO PAQ X20 UNI CAJ X1000 | C285: 67392 | E285: 0 | F285: =ROUND(C285,0) -> 67392 | H285: =_xlfn.XLOOKUP(A285,Hoja1!A:A,Hoja1!G:G,0,0) -> #NAME?
A286: 0035DARB0008 | B286: VASO TERMICO BIODEGRADABLE 8 Oz DARNEL BIO PAQX20 CAJ X1000 | C286: 82298 | E286: 0 | F286: =ROUND(C286,0) -> 82298 | H286: =_xlfn.XLOOKUP(A286,Hoja1!A:A,Hoja1!G:G,0,0) -> #NAME?
A287: 0035DARBT0006 | B287: TAPA RIGIDA SIN PERFORACION PARA VASO 6 Oz Y CONTENEDOR 4 Oz OPAL PQX1 | C287: 30399 | E287: 0 | F287: =ROUND(C287,0) -> 30399 | H287: =_xlfn.XLOOKUP(A287,Hoja1!A:A,Hoja1!G:G,0,0) -> #NAME?
A288: 0035DART0008 | B288: +TAPA RIGIDA SIN PERFORACION PARA VASO 8 Oz OPAL PQX100 CAJ 1000UNID | C288: 35314 | E288: 0 | F288: =ROUND(C288,0) -> 35314 | H288: =_xlfn.XLOOKUP(A288,Hoja1!A:A,Hoja1!G:G,0,0) -> #NAME?
A289: 0035VAS00120 | B289: VASO TERMICO 120 CC. | C289: 47948 | E289: 0 | F289: =ROUND(C289,0) -> 47948 | H289: =_xlfn.XLOOKUP(A289,Hoja1!A:A,Hoja1!G:G,0,0) -> #NAME?
A290: 0035VAS00180 | B290: VASO TERMICO 180 CC. | C290: 57515 | E290: 0 | F290: =ROUND(C290,0) -> 57515 | H290: =_xlfn.XLOOKUP(A290,Hoja1!A:A,Hoja1!G:G,0,0) -> #NAME?
A291: 0035VAS00240 | B291: VASO TERMICO 240 CC. | C291: 70239 | E291: 0 | F291: =ROUND(C291,0) -> 70239 | H291: =_xlfn.XLOOKUP(A291,Hoja1!A:A,Hoja1!G:G,0,0) -> #NAME?
A292: 0035VAS00300 | B292: VASO TERMICO 300 CC. | C292: 80713 | E292: 0 | F292: =ROUND(C292,0) -> 80713 | H292: =_xlfn.XLOOKUP(A292,Hoja1!A:A,Hoja1!G:G,0,0) -> #NAME?
A293: 0035VTA00120 | B293: TAPA VASO TERMICO 120 CC. 4JL | C293: 20468 | E293: 0 | F293: =ROUND(C293,0) -> 20468 | H293: =_xlfn.XLOOKUP(A293,Hoja1!A:A,Hoja1!G:G,0,0) -> #NAME?
A294: 0035VTA00180 | B294: TAPA VASO TERMICO 180 CC. 6JL | C294: 23826 | E294: 0 | F294: =ROUND(C294,0) -> 23826 | H294: =_xlfn.XLOOKUP(A294,Hoja1!A:A,Hoja1!G:G,0,0) -> #NAME?
... A325: 0041DAR00024 | B325: DARNEL CUCHARA DEGUS PETITE NEG. 12PX24U | C325: 25456 | E325: 0.7 | F325: =ROUND(C325,0) -> 25456 | H325: =_xlfn.XLOOKUP(A325,Hoja1!A:A,Hoja1!G:G,0,0) -> #NAME?
A326: 0041DAR00110 | B326: TENEDOR DE MADERA 16CM DARNEL NAT 10PAQX100 | C326: 49425 | F326: =ROUND(C326,0) -> 49425 | H326: =_xlfn.XLOOKUP(A326,Hoja1!A:A,Hoja1!G:G,0,0) -> #NAME?
A327: 0041DAR00111 | B327: CUCHILLO DE MADERA 16CM DARNEL NAT 10PQX100 | C327: 37691 | F327: =ROUND(C327,0) -> 37691 | H327: =_xlfn.XLOOKUP(A327,Hoja1!A:A,Hoja1!G:G,0,0) -> #NAME?
A328: 0041DAR00140 | B328: CUCHARA DE MADERA 14CM DARNEL NAT10PQX100 | C328: 37821 | F328: =ROUND(C328,0) -> 37821 | H328: =_xlfn.XLOOKUP(A328,Hoja1!A:A,Hoja1!G:G,0,0) -> #NAME?
A329: 0041TAM00010 | B329: TAMI TENEDOR BLANCO 50PX20U | C329: 27573 | E329: 0 | F329: =ROUND(C329,0) -> 27573 | H329: =_xlfn.XLOOKUP(A329,Hoja1!A:A,Hoja1!G:G,0,0) -> #NAME?
A330: 0041TAM00011 | B330: TAMI TENEDOR BLANCO 10PX100U | C330: 24927 | E330: 0 | F330: =ROUND(C330,0) -> 24927 | H330: =_xlfn.XLOOKUP(A330,Hoja1!A:A,Hoja1!G:G,0,0) -> #NAME?
A331: 0041TAM00012 | B331: TAMI CUCHILLO BLANCO 50PX20U | C331: 24804 | E331: 0 | F331: =ROUND(C331,0) -> 24804 | H331: =_xlfn.XLOOKUP(A331,Hoja1!A:A,Hoja1!G:G,0,0) -> #NAME?
A332: 0041TAM00013 | B332: TAMI CUCHILLO BLANCO 10PX100U | C332: 22723 | E332: 0 | F332: =ROUND(C332,0) -> 22723 | H332: =_xlfn.XLOOKUP(A332,Hoja1!A:A,Hoja1!G:G,0,0) -> #NAME?
A333: 0041TAM00014 | B333: TAMI CUCHARA DULCERA BCA 50PX20U | C333: 24377 | E333: 0 | F333: =ROUND(C333,0) -> 24377 | H333: =_xlfn.XLOOKUP(A333,Hoja1!A:A,Hoja1!G:G,0,0) -> #NAME?
A334: 0041TAM00015 | B334: TAMI CUCHARA DULCERA BCA 10PX100U | C334: 21995 | E334: 0 | F334: =ROUND(C334,0) -> 21995 | H334: =_xlfn.XLOOKUP(A334,Hoja1!A:A,Hoja1!G:G,0,0) -> #NAME?
A335: 0041TAM00016 | B335: TAMI CUCHARA SOPERA BCA 50PX20U | C335: 36702 | E335: 0 | F335: =ROUND(C335,0) -> 36702 | H335: =_xlfn.XLOOKUP(A335,Hoja1!A:A,Hoja1!G:G,0,0) -> #NAME?
A336: 0041TAM00017 | B336: TAMI CUCHARA SOPERA BCA 10PX100U | C336: 33464 | E336: 0 | F336: =ROUND(C336,0) -> 33464 | H336: =_xlfn.XLOOKUP(A336,Hoja1!A:A,Hoja1!G:G,0,0) -> #NAME?
...

Sheet Hoja1
A3: {=_xlfn.VSTACK('Papeles-Cartulina'!B6:H69,PVC!B7:H31,'Porta Comida XPS'!B6:H28,'Band. Expandido'!B7:H47,'Linea Aluminio'!B6:H54)} -> 0001BIO00002 | B3: 0 | C3: kg | D3: 1 | E3: BIOXIDO 75 X 50 | F3: Resma 10 KG. | G3: 72428
A4: 0001BIO00004 | B4: 0 | C4: kg | D4: 1 | E4: BIOXIDO 37 X 50 | F4: Resma 10 KG. | G4: 72428
A5: 0001BIO00008 | B5: 0 | C5: kg | D5: 1 | E5: BIOXIDO 37 X 25 | F5: Resma 10 KG. | G5: 72428
A6: 0001BIO00016 | B6: 0 | C6: kg | D6: 1 | E6: BIOXIDO 18 X 25 | F6: Resma 10 KG. | G6: 72428
A7: 0002DES03246 | B7: 0 | C7: res | D7: 1 | E7: DESMOLDANTE 32 X 46 | F7: Resma 5 KG. | G7: 64589
A8: 0002DES04060 | B8: 0 | C8: res | D8: 1 | E8: DESMOLDANTE 40 X 60 | F8: Resma 5 KG. | G8: 64589
A9: 0002DES04565 | B9: 0 | C9: res | D9: 1 | E9: DESMOLDANTE 45 X 64 | F9: Resma 5 KG. | G9: 64589
A10: 0002DES06080 | B10: 0 | C10: res | D10: 1 | E10: DESMOLDANTE 60 X 80 | F10: Resma 5 KG. | G10: 64589
A11: 0002DES07090 | B11: 0 | C11: res | D11: 1 | E11: DESMOLDANTE 70 X 90 | F11: Resma 5 KG. | G11: 64589
A12: PAPEL PARAFINADO | B12: 0 | C12: 0 | D12: 0 | E12: 0 | F12: 0 | G12: 0
A13: 0082ALL00009 | B13: 0 | C13: res | D13: 1 | E13: PAPEL PARAFINADO LISO 40 x 40 cm | F13: Resma 1 KG. | G13: 12994
A14: 0082ALL00020 | B14: 0 | C14: res | D14: 1 | E14: PAPEL PARAFINADO LISO 35 x 40 cm | F14: Resma 5 KG. | G14: 64439
A15: 0082ALL00021 | B15: 0 | C15: res | D15: 1 | E15: PAPEL PARAFINADO GENERICO 35 x 40 cm | F15: Resma 5 KG. | G15: 64566
A16: 0082ALL00022 | B16: 0 | C16: res | D16: 1 | E16: PAPEL PARAFINADO PERSONALIZADO | F16: Resma 5 KG. | G16: 64276
A17: PAPEL ALUMINIZADO | B17: 0 | C17: 0 | D17: 0 | E17: 0 | F17: 0 | G17: 0
A18: 0082ALL00002 | B18: 0 | C18: res | D18: 1 | E18: PAPEL ALUMINIO IMPRESO GENERICO 25 x 35 cm | F18: Resma 5 KG. | G18: 125496
A19: 0082ALL00003 | B19: 0 | C19: res | D19: 1 | E19: PAPEL ALUMINIO PERSONALIZADO | F19: Resma 5 KG. | G19: 125185
A20: 0082ALL00004 | B20: 0 | C20: res | D20: 1 | E20: PAPEL ALUMINIO LISO 25 x 35 cm | F20: Resma 5 KG. | G20: 126192
A21: 0082ALL00005 | B21: 0 | C21: res | D21: 1 | E21: PAPEL ALUMINIO LISO 34 x 50 cm | F21: Resma 5 KG. | G21: 126192
A22: 0082ALL00006 | B22: 0 | C22: res | D22: 1 | E22: PAPEL ALUMINIO IMPRESO GENERICO 34 x 50 cm | F22: Resma 5 KG. | G22: 125844
A23: CARTON - CARTULINA ANTIGRASA | B23: 0 | C23: 0 | D23: 0 | E23: 0 | F23: 0 | G23: 0
A24: 0018DARBB0026 | B24: RPN02026101XC | C24: caja | D24: 200 | E24: CAJA PARA ALIMENTOS DARNEL NATURAL 26 Oz BLANCA PAQX50 Un. | F24: Nuevo | G24: 47151
A25: 0018DARBK0026 | B25: RPN02026102XC | C25: PAQ | D25: 200 | E25: CAJA PARA ALIMENTOS DARNEL NATURAL 26 Oz MOCA PAQX50 CAJ X200UNID | F25: Nuevo | G25: 43116
A26: 0018DARBB0045 | B26: RPN02045101XC | C26: PAQ | D26: 200 | E26: CAJA PARA ALIMENTOS DARNEL NATURAL 45 Oz BLANCO PQX50 CJX200 | F26: Nuevo | G26: 68591
A27: 0018DARBKS045 | B27: RPN02045102XTE | C27: PAQ | D27: 200 | E27: CAJA ALIMENTOS SAFETYPLUS DARNEL NATURALS 45 Oz MOCA PQX50 CAJX200 | F27: Nuevo | G27: 67623
A28: 0018DARBB0049 | B28: RPN02049101XC | C28: PAQ | D28: 200 | E28: CAJA PARA ALIMENTOS DARNEL NATURALS 49 Oz BLANCO PQX50 CAJX200 | F28: Nuevo | G28: 73442
A29: 0018DARBK0049 | B29: RPN02049102XC | C29: PAQ | D29: 200 | E29: CAJA PARA ALIMENTOS DARNEL NATURAL 49 Oz MOCA PQX50 CJX200 | F29: Nuevo | G29: 67949
A30: 0018DARBB0066 | B30: RPN02066101XC | C30: PAQ | D30: 200 | E30: CAJA PARA ALIMENTOS DARNEL NATURAL 66 Oz BLANCO PQX50 CJX200 | F30: Nuevo | G30: 80488
A31: 0018DARBK0066 | B31: RPN02066102XC | C31: PAQ | D31: 200 | E31: CAJA PARA ALIMENTOS DARNEL NATURAL 66 Oz MOCA PQX50 CJX200 | F31: Nuevo | G31: 74222
A32: 0018DARBB0072 | B32: RPN0207201X | C32: PAQ | D32: 100 | E32: CAJA PARA ALIMENTOS DARNEL NATURALS 72 Oz BLANCO BLX100 | F32: Nuevo | G32: 50051
A33: 0018DARBBK072 | B33: RPN0207202X | C33: PAQ | D33: 100 | E33: CAJA PARA ALIMENTOS DARNEL NATURALS 72 Oz MOCA BLX100 | F33: Nuevo | G33: 50375
A34: 0018DARBB0115 | B34: RPN02011501X | C34: PAQ | D34: 100 | E34: CAJA PARA ALIMENTOS DARNEL NATURALS 115 Oz BLANCO BLX100 UNID | F34: Nuevo | G34: 43095
A35: 0018DARBBK115 | B35: RPN02011502X | C35: caja | D35: 100 | E35: CAJA PARA ALIMENTOS DARNEL NATURAL 115oz MOCA | F35: Nuevo | G35: 43428
A36: CAJAS y ESTUCHES PARA PAPAS FRITAS | B36: 0 | C36: 0 | D36: 0 | E36: 0 | F36: 0 | G36: 0
A37: 0018DARBBF0001 | B37: RPN02P08201X | C37: PAQ | D37: 600 | E37: CAJA PEQUEÑA PARA PAPAS FRITAS DARNEL NATURAL BLANCA PQX100 CJX600 | F37: Nuevo | G37: 33056
A38: 0018DARBBF0005 | B38: RPN02P08701X | C38: PAQ | D38: 600 | E38: CAJA MEDIANA PARA PAPAS FRITAS DARNEL NATURAL BLANCO PQX100 CJX600 | F38: Nuevo | G38: 60322
A39: 0018DARBBF0010 | B39: RPN02P12801X | C39: PAQ | D39: 600 | E39: CAJA GRANDE PARA PAPAS FRITAS DARNEL NATURAL BLANCO PQX100 CJX600 | F39: Nuevo | G39: 81948
A40: 0018DARBKF0001 | B40: RPN02P08202X | C40: PAQ | D40: 600 | E40: CAJA PEQUEÑA PARA PAPAS FRITAS DARNEL NATURAL MOCA PQX100 CJX600 | F40: Nuevo | G40: 29445
A41: 0018ESP00004 | B41: 0018ESP00004 | C41: PAQ | D41: 1000 | E41: ESTUCHES PAPAS FRITAS KRAFT X 1000 | F41: 210 Grs (Aprox) | G41: 97504
A42: CAJAS PARA ALIMENTOS SAFETYPLUS | B42: 0 | C42: 0 | D42: 0 | E42: 0 | F42: 0 | G42: 0
A43: 0018DARBKS026 | B43: RPN02026102XTE | C43: caja | D43: 200 | E43: CAJA P/ALIMENTOS SAFETYPLUS DARNEL NAT. 26oz MOCA PQX50 Un. | F43: Nuevo | G43: 45268
A44: 0018DARBK0045 | B44: RPN02045102XC | C44: caja | D44: 200 | E44: CAJA PARA ALIMENTOS DARNEL NATURAL 45 Oz MOCA PQX50 Un. | F44: Nuevo | G44: 62476
A45: 0018DARBKS0049 | B45: RPN02049102XTE | C45: caja | D45: 200 | E45: CAJA P/ALIMENTOS SAFETYPLUS DARNEL NAT. 49oz MOCA PQX50 Un. | F45: Nuevo | G45: 72723
A46: 0018DARBKS0066 | B46: RPN02066102XTE | C46: caja | D46: 200 | E46: CAJA P/ALIMENTOS SAFETYPLUS DARNEL NAT 66oz MOCA PQX50 Un. | F46: Nuevo | G46: 79883
A47: CAJAS PARA HAMBURGUESAS | B47: 0 | C47: 0 | D47: 0 | E47: 0 | F47: 0 | G47: 0
A48: 0018DARKH0001 | B48: RPN0209302X | C48: caja | D48: 300 | E48: CAJA PEQUEÑA P/HAMBURGUESA DARNEL NATURAL MOCA PAQX50 Un. | F48: Nuevo | G48: 44059
A49: 0018DARKH0005 | B49: RPN0209502X | C49: caja | D49: 300 | E49: CAJA MEDIANA P/HAMBURGUESA DARNEL NATURAL MOCA PAQX50 Un. | F49: Nuevo | G49: 45245
A50: 0018DARKH0010 | B50: RPN02011402X | C50: caja | D50: 400 | E50: CAJA GRANDE P/HAMBURGUESA DARNEL NATURAL MOCA PAQX50 Un. | F50: Nuevo | G50: 55794
A51: PORTA VASO CARTULINA | B51: 0 | C51: 0 | D51: 0 | E51: 0 | F51: 0 | G51: 0
A52: 0018ESV00003 | B52: 0 | C52: caja | D52: 400 | E52: PORTA VASOS DE CARTULINA | F52: 0 | G52: 54611
A53: PAPEL SEDA | B53: 0 | C53: 0 | D53: 0 | E53: 0 | F53: 0 | G53: 0
A54: 0002SED75100 | B54: 0 | C54: res | D54: 1 | E54: PAPEL SEDA 75 x 100 cm. | F54: Resma 5 KG. | G54: 26092
A55: BANDEJAS KRAFT MICROCORRUGADAS | B55: 0 | C55: 0 | D55: 0 | E55: 0 | F55: 0 | G55: 0
A56: 0012COM00052 | B56: 0 | C56: caja | D56: 600 | E56: BAND. Kraft puro CARTULINA Nro 2 (10 x 6,5 x 3 cm) | F56: 3 paq x 200 Un. | G56: 37544
A57: 0012COM10012 | B57: 0 | C57: caja | D57: 400 | E57: BAND Kraft microcorr IMPRESA nro 2 (17x13,8x1,5 cm) | F57: 4 paq x 100 Un. | G57: 33673
A58: 0012COM10013 | B58: 0 | C58: caja | D58: 400 | E58: BAND Kraft microcorr IMPRESA nro 3 (20,5x18x2 cm) | F58: 4 paq x 100 Un. | G58: 39055
A59: 0012COM10014 | B59: 0 | C59: caja | D59: 400 | E59: BAND Kraft microcorr. IMPRESA nro 4 (23,3x18x2 cm) | F59: 4 paq x 100 Un. | G59: 49140
A60: 0012COM10015 | B60: 0 | C60: caja | D60: 200 | E60: BAND Kraft microcorr IMPRESA nro 5 (27x20,5x2,3 cm) | F60: 2 paq x 100 Un. | G60: 30348
A61: 0012COM10016 | B61: 0 | C61: caja | D61: 200 | E61: BAND Kraft microcorr IMPRESA nro 6 (19x14x4 cm) | F61: 2 paq x 100 Un. | G61: 28301
A62: 0012COM10017 | B62: 0 | C62: caja | D62: 200 | E62: BAND Kraft microcorr IMPRESA nro 7 (23x17x3,5 cm) | F62: 2 paq x 100 Un. | G62: 34372
A63: BOLSAS DE PAPEL Y SERVILLETAS ENSOBRADAS | B63: 0 | C63: 0 | D63: 0 | E63: 0 | F63: 0 | G63: 0
A64: 0004KRA00090 | B64: 0 | C64: paq | D64: 250 | E64: BOLSA CHICA PAPEL KRAFT Impresa "Delivery" | F64: 370x200x120mm | G64: 21515
A65: 0004KRA00091 | B65: 0 | C65: paq | D65: 250 | E65: BOLSA GRANDE PAPEL KRAFT Impresa "Delivery" | F65: 470x200x120mm | G65: 26260
A66: 0005SERZ0001 | B66: 0 | C66: paq | D66: 500 | E66: SERVILLETAS PAPEL KRAFT Ensobradas (2 Un x sobre) | F66: 400x145 mm | G66: 21216
A67: 0027LIG00030 | B67: SA135-300-500L | C67: Rollo | D67: 1 | E67: PVC 300mm (12") 300MM x 500 MTS. | F67: 0 | G67: 13343
A68: 0027LIG00038 | B68: SA135-380-500L | C68: Rollo | D68: 1 | E68: PVC 380mm (15") 380MM x 500 MTS. | F68: 0 | G68: 16489
A69: 0027LIG00045 | B69: SA135-450-500L | C69: Rollo | D69: 1 | E69: PVC 450mm (18") 450MM x 500 MTS. | F69: 0 | G69: 19249
A70: PVC DARNEL 1000 Mts. | B70: 0 | C70: 0 | D70: 0 | E70: 0 | F70: 0 | G70: 0
A71: 0027LIG01012 | B71: SA1D353001000 | C71: Rollo | D71: 1 | E71: PVC ECONO FILM 12" (300MM x 1000 MTS.) | F71: 0 | G71: 23283
A72: 0027LIG01015 | B72: SA1D353801000 | C72: Rollo | D72: 1 | E72: PVC ECONO FILM 15" (380MM x 1000 MTS.) | F72: 0 | G72: 29490
A73: 0027LIG01018 | B73: SA1D354501000 | C73: Rollo | D73: 1 | E73: PVC ECONO FILM 18" (450MM x 1000 MTS.) | F73: 0 | G73: 34282
A74: PVC DARNEL 1400 Mts. | B74: 0 | C74: 0 | D74: 0 | E74: 0 | F74: 0 | G74: 0
A75: 0027EST00012 | B75: SA1D35-300-1400 | C75: Rollo | D75: 1 | E75: PVC 12 " (300 MM X 1400 MTS.) | F75: 0 | G75: 34508
A76: 0027EST00015 | B76: SA1D35-380-1400 | C76: Rollo | D76: 1 | E76: PVC 15 " (380MM X 1400 MTS.) | F76: 0 | G76: 43780
A77: 0027EST00018 | B77: SA1D35-450-1400 | C77: Rollo | D77: 1 | E77: PVC 18 " (450MM X 1400 MTS.) | F77: 0 | G77: 51888
A78: PVC LINEA TAMI | B78: 0 | C78: 0 | D78: 0 | E78: 0 | F78: 0 | G78: 0
A79: 0027TAM28050 | B79: ST2-280-50R | C79: Rollo | D79: 1 | E79: PVC TAMI WRAP 280 MM X 50 MTS | F79: 35 unid./caja | G79: 1375
A80: 0027TAM28100 | B80: ST2-280-100R | C80: Rollo | D80: 1 | E80: PVC TAMI WRAP 280 MM X 100 MTS | F80: 24 unid./caja | G80: 2287
A81: PVC LINEA DOMESTICA | B81: 0 | C81: 0 | D81: 0 | E81: 0 | F81: 0 | G81: 0
A82: 0027REP00282 | B82: ST3-280-200 | C82: Rollo | D82: 1 | E82: PVC REPUESTO 12" (300MM X 200 MTS) | F82: 15 unid./caja | G82: 4416
A83: 0027REP00382 | B83: ST3-380-200 | C83: Rollo | D83: 1 | E83: PVC REPUESTO 15" (380MM X 200 MTS) | F83: 15 Unid./caja | G83: 5733
A84: 0027REP00015 | B84: SD135-380-300R | C84: Rollo | D84: 1 | E84: PVC REPUESTO 15" (380MM X 300 MTS.) | F84: 12 unid./caja | G84: 9255
A85: 0027REP00030 | B85: SD135-380-300D | C85: Rollo | D85: 1 | E85: REPUESTO 15" (380MM X 300 MTS.) C/Dispenser | F85: 6 unid./caja | G85: 13184
A86: 0027REP00018 | B86: SD135-450-300DRB | C86: Rollo | D86: 1 | E86: PVC REPUESTO 18" (450MM X 300 MTS) | F86: 12 unid./caja | G86: 11297
A87: 0027REP00036 | B87: SD135-450-300D | C87: Rollo | D87: 1 | E87: PVC REPUESTO 18" (450mm X 300mts) C/Dispenser | F87: 6 unid./caja | G87: 14713
A88: PVC LINEA BIODEGRADABLE | B88: 0 | C88: 0 | D88: 0 | E88: 0 | F88: 0 | G88: 0
A89: 0027BIO38100 | B89: SA4B35-380-1000 | C89: Rollo | D89: 1 | E89: PVC BIODEG. DARNEL 380MM X 1000 MTS | F89: 0 | G89: 33577
A90: 0027BIO28100 | B90: SA4B31-280-100DR | C90: Rollo | D90: 1 | E90: PVC BIODEG. DARNEL 280MM X 100 MTS | F90: 24 unid./caja | G90: 2683
A91: 0027BIO28300 | B91: SA4B31-280-300D | C91: Rollo | D91: 1 | E91: PVC BIODEG DARNEL 280mm x 300 Mts C/Dispenser | F91: 6 unid./caja | G91: 9310
A92: 0034CON00020 | B92: D742801RLFY | C92: paq | D92: 100 | E92: PLATO TERMICO C/TAPA R102 850ml (base/tapa) | F92: diam 190x50mm | G92: 24084
A93: 0034CON00021 | B93: D741701RY | C93: paq | D93: 100 | E93: PLATO TERMICO C/TAPA R100 500ml (base/tapa) | F93: diam 190x35mm | G93: 24509
A94: 0034CON00022 | B94: D744001RY | C94: paq | D94: 100 | E94: PLATO TERMICO C/TAPA R104 1200ml (base/tapa) | F94: diam 190x68mm | G94: 28822
A95: PLATOS ESPUMADOS | B95: 0 | C95: 0 | D95: 0 | E95: 0 | F95: 0 | G95: 0
A96: 0034DARPWH05 | B96: D5105101NW | C96: caja | D96: 480 | E96: DARNEL PLATO HONDO BLANCO 5oz x 20u. | F96: Nuevo | G96: 15646
A97: 0034DARPW0015 | B97: D510601NW | C97: caja | D97: 480 | E97: DARNEL PLATO BLANCO 15,5 cm x 20u. | F97: Nuevo | G97: 22123
A98: 0034DARPW0023 | B98: D510901NW | C98: caja | D98: 480 | E98: DARNEL PLATO BLANCO 23 cm x 20u. | F98: Nuevo | G98: 43919
A99: ESTUCHES RECTANGULAR DE EXPANDIDO | B99: 0 | C99: 0 | D99: 0 | E99: 0 | F99: 0 | G99: 0
A100: 0034DARP0001 | B100: NUEVO | C100: Bolson | D100: 200 | E100: PORTACOMIDA UY EXPANDIDO NR-J1 S/DIV x 200 un | F100: 230x160x60mm | G100: 28791
A101: 0034DARP0002 | B101: NUEVO | C101: Bolson | D101: 200 | E101: PORTACOMIDA UY EXPANDIDO NR-J2 C/DIV x 200 un | F101: 230x160x60mm | G101: 30819
A102: 0034DARP0011 | B102: NUEVO | C102: Bolson | D102: 200 | E102: PORTACOMIDA Uy EXPAND. NR-J1 BIO S/DIV x 200un | F102: 230x160x60mm | G102: 34510
...

Sheet amb
A1: SIS8120-Consulta dinamica
A3: Nombre Articulo | B3: Articulo | C3: Articulo Interno | D3: Articulo Formularios | E3: Cantidad Bulto | F3: Peso embalado | G3: Cantidad Bulto (Vent) | H3: Unidad Medida homogenea (Vent) | I3: Nombre Unidad de Medida | J3: Unidad de Medida_1 | K3: Unidad de medidad Utilizable | L3: Unidad de Medida_2 | M3: Clasificacion 1 | N3: Clasificacion 1 Utilizable | O3: Nombre Clasificacion 1 | P3: Clasificacion 2 | Q3: Nombre Clasificacion 2 | R3: Clasificacion 2 Utilizable | S3: Clasificacion 3 | T3: Nombre Clasificacion 3 | U3: Clasificacion 3 Utilizable | V3: Clasificacion 4 | W3: Nombre Clasificacion 4 | X3: Clasificacion 4 Utilizable | Y3: Formato | Z3: Simbolo | AA3: Clasificacion 5 | AB3: Nombre Clasificacion 5 | AC3: Clasificacion 5 Utilizable | AD3: Fecha de baja (Comp) | AE3: Fecha Baja
A4: BLANCO SEIN 40 X 50 | B4: 0001BCO00002 | C4: 1 | D4: 0001BCO00002 | E4: .0000 | F4: 10.0000 | G4: .0000 | I4: Resmas | K4: 1 | L4: RES | M4: 007 | N4: 1 | O4: Papeles | P4: 001 | Q4: Papel | R4: 1 | S4: 001 | T4: Manufactured Group Locally | U4: 1 | V4: 001 | W4: Bolsas de Papel | X4: 1 | Z4: RES | AA4: 1 | AB4: 1 | AC4: 1
A5: BLANCO SEIN 64 X 90 | B5: 0001BCO00003 | C5: 2 | D5: 0001BCO00003 | E5: .0000 | F5: 10.0000 | G5: .0000 | I5: Resmas | K5: 1 | L5: RES | M5: 007 | N5: 1 | O5: Papeles | P5: 001 | Q5: Papel | R5: 1 | S5: 001 | T5: Manufactured Group Locally | U5: 1 | V5: 001 | W5: Bolsas de Papel | X5: 1 | Z5: RES | AA5: 1 | AB5: 1 | AC5: 1
A6: BLANCO SEIN 64 X 45 | B6: 0001BCO00004 | C6: 3 | D6: 0001BCO00004 | E6: .0000 | F6: 10.0000 | G6: .0000 | I6: Resmas | K6: 1 | L6: RES | M6: 007 | N6: 1 | O6: Papeles | P6: 001 | Q6: Papel | R6: 1 | S6: 001 | T6: Manufactured Group Locally | U6: 1 | V6: 001 | W6: Bolsas de Papel | X6: 1 | Z6: RES | AA6: 1 | AB6: 1 | AC6: 1
A7: BLANCO SEIN 32 X 45 | B7: 0001BCO00005 | C7: 4 | D7: 0001BCO00005 | E7: .0000 | F7: 10.0000 | G7: .0000 | I7: Resmas | K7: 1 | L7: RES | M7: 007 | N7: 1 | O7: Papeles | P7: 001 | Q7: Papel | R7: 1 | S7: 001 | T7: Manufactured Group Locally | U7: 1 | V7: 001 | W7: Bolsas de Papel | X7: 1 | Z7: RES | AA7: 1 | AB7: 1 | AC7: 1
A8: BLANCO SEIN 52 X 72 | B8: 0001BCO00006 | C8: 5 | D8: 0001BCO00006 | E8: .0000 | F8: 10.0000 | G8: .0000 | I8: Resmas | K8: 1 | L8: RES | M8: 007 | N8: 1 | O8: Papeles | P8: 001 | Q8: Papel | R8: 1 | S8: 001 | T8: Manufactured Group Locally | U8: 1 | V8: 001 | W8: Bolsas de Papel | X8: 1 | Z8: RES | AA8: 1 | AB8: 1 | AC8: 1
A9: BLANCO SEIN 52 X 36 | B9: 0001BCO00007 | C9: 6 | D9: 0001BCO00007 | E9: .0000 | F9: 10.0000 | G9: .0000 | I9: Resmas | K9: 1 | L9: RES | M9: 007 | N9: 1 | O9: Papeles | P9: 001 | Q9: Papel | R9: 1 | S9: 001 | T9: Manufactured Group Locally | U9: 1 | V9: 001 | W9: Bolsas de Papel | X9: 1 | Z9: RES | AA9: 1 | AB9: 1 | AC9: 1
A10: BLANCO SEIN 26 X 36 | B10: 0001BCO00008 | C10: 7 | D10: 0001BCO00008 | E10: .0000 | F10: 10.0000 | G10: .0000 | I10: Resmas | K10: 1 | L10: RES | M10: 007 | N10: 1 | O10: Papeles | P10: 001 | Q10: Papel | R10: 1 | S10: 001 | T10: Manufactured Group Locally | U10: 1 | V10: 001 | W10: Bolsas de Papel | X10: 1 | Z10: RES | AA10: 1 | AB10: 1 | AC10: 1
A11: BLANCO SEIN 26 X 18 | B11: 0001BCO00009 | C11: 8 | D11: 0001BCO00009 | E11: .0000 | F11: 10.0000 | G11: .0000 | I11: Resmas | K11: 1 | L11: RES | M11: 007 | N11: 1 | O11: Papeles | P11: 001 | Q11: Papel | R11: 1 | S11: 001 | T11: Manufactured Group Locally | U11: 1 | V11: 001 | W11: Bolsas de Papel | X11: 1 | Z11: RES | AA11: 1 | AB11: 1 | AC11: 1
A12: BLANCO SEIN 58 X 81 | B12: 0001BCO00010 | C12: 9 | D12: 0001BCO00010 | E12: .0000 | F12: 10.0000 | G12: .0000 | I12: Resmas | K12: 1 | L12: RES | M12: 007 | N12: 1 | O12: Papeles | P12: 001 | Q12: Papel | R12: 1 | S12: 001 | T12: Manufactured Group Locally | U12: 1 | V12: 001 | W12: Bolsas de Papel | X12: 1 | Z12: RES | AA12: 1 | AB12: 1 | AC12: 1
A13: BLANCO SEIN 58 X 40 | B13: 0001BCO00011 | C13: 10 | D13: 0001BCO00011 | E13: .0000 | F13: 10.0000 | G13: .0000 | I13: Resmas | K13: 1 | L13: RES | M13: 007 | N13: 1 | O13: Papeles | P13: 001 | Q13: Papel | R13: 1 | S13: 001 | T13: Manufactured Group Locally | U13: 1 | V13: 001 | W13: Bolsas de Papel | X13: 1 | Z13: RES | AA13: 1 | AB13: 1 | AC13: 1
A14: BLANCO SEIN 9 X 13 PIZZERO | B14: 0001BCO00014 | C14: 11 | D14: 0001BCO00014 | E14: .0000 | F14: 10.0000 | G14: .0000 | I14: Resmas | K14: 1 | L14: RES | M14: 007 | N14: 1 | O14: Papeles | P14: 001 | Q14: Papel | R14: 1 | S14: 001 | T14: Manufactured Group Locally | U14: 1 | V14: 001 | W14: Bolsas de Papel | X14: 1 | Z14: RES | AA14: 1 | AB14: 1 | AC14: 1
A15: BLANCO SEIN 30 X 40 | B15: 0001BCO00015 | C15: 12 | D15: 0001BCO00015 | E15: .0000 | F15: 10.0000 | G15: .0000 | I15: Resmas | K15: 1 | L15: RES | M15: 007 | N15: 1 | O15: Papeles | P15: 001 | Q15: Papel | R15: 1 | S15: 001 | T15: Manufactured Group Locally | U15: 1 | V15: 001 | W15: Bolsas de Papel | X15: 1 | Z15: RES | AA15: 1 | AB15: 1 | AC15: 1
... A30: KRAFT PURO 80 GRS. | B30: 0001KPU00080 | C30: 27 | D30: 0001KPU00080 | E30: .0000 | F30: 1.0000 | G30: .0000 | I30: Kilogramos | K30: 1 | L30: KG | M30: 007 | N30: 1 | O30: Papeles | P30: 001 | Q30: Papel | R30: 1 | S30: 001 | T30: Manufactured Group Locally | U30: 1 | V30: 001 | W30: Bolsas de Papel | X30: 1 | Z30: KG | AA30: 1 | AB30: 1 | AC30: 1
A31: KRAFT PURO 125 GRS. | B31: 0001KPU00125 | C31: 28 | D31: 0001KPU00125 | E31: .0000 | F31: 1.0000 | G31: .0000 | I31: Kilogramos | K31: 1 | L31: KG | M31: 007 | N31: 1 | O31: Papeles | P31: 001 | Q31: Papel | R31: 1 | S31: 001 | T31: Manufactured Group Locally | U31: 1 | V31: 001 | W31: Bolsas de Papel | X31: 1 | Z31: KG | AA31: 1 | AB31: 1 | AC31: 1 | AE31: 2025-05-21-00.00.00.000000
A32: KRAFT SEIN EN HOJAS 50 GRS. | B32: 0001KSE00001 | C32: 29 | D32: 0001KSE00001 | E32: .0000 | F32: 1.0000 | G32: .0000 | I32: Kilogramos | K32: 1 | L32: KG | M32: 007 | N32: 1 | O32: Papeles | P32: 001 | Q32: Papel | R32: 1 | S32: 001 | T32: Manufactured Group Locally | U32: 1 | V32: 001 | W32: Bolsas de Papel | X32: 1 | Z32: KG | AA32: 1 | AB32: 1 | AC32: 1
A33: KRAFT SEIN EN HOJAS 80 GRS. | B33: 0001KSE00002 | C33: 30 | D33: 0001KSE00002 | E33: .0000 | F33: 1.0000 | G33: .0000 | I33: Kilogramos | K33: 1 | L33: KG | M33: 007 | N33: 1 | O33: Papeles | P33: 001 | Q33: Papel | R33: 1 | S33: 001 | T33: Manufactured Group Locally | U33: 1 | V33: 001 | W33: Bolsas de Papel | X33: 1 | Z33: KG | AA33: 1 | AB33: 1 | AC33: 1
A34: DESMOLDANTE 30 X 40 | B34: 0002DES03040 | C34: 31 | D34: 0002DES03040 | E34: .0000 | F34: 5.0000 | G34: .0000 | I34: Resmas | K34: 1 | L34: RES | M34: 007 | N34: 1 | O34: Papeles | P34: 001 | Q34: Papel | R34: 1 | S34: 001 | T34: Manufactured Group Locally | U34: 1 | V34: 059 | W34: Papel en Hojas | X34: 1 | Z34: RES | AA34: 1 | AB34: 1 | AC34: 1 | AE34: 2025-05-21-00.00.00.000000
A35: DESMOLDANTE 32 X 30 | B35: 0002DES03230 | C35: 32 | D35: 0002DES03230 | E35: .0000 | F35: 5.0000 | G35: .0000 | I35: Resmas | K35: 1 | L35: RES | M35: 007 | N35: 1 | O35: Papeles | P35: 001 | Q35: Papel | R35: 1 | S35: 001 | T35: Manufactured Group Locally | U35: 1 | V35: 059 | W35: Papel en Hojas | X35: 1 | Z35: RES | AA35: 1 | AB35: 1 | AC35: 1 | AE35: 2024-04-11-00.00.00.000000
A36: DESMOLDANTE 32 X 46 | B36: 0002DES03246 | C36: 33 | D36: 0002DES03246 | E36: .0000 | F36: 5.0000 | G36: .0000 | I36: Resmas | K36: 1 | L36: RES | M36: 007 | N36: 1 | O36: Papeles | P36: 001 | Q36: Papel | R36: 1 | S36: 001 | T36: Manufactured Group Locally | U36: 1 | V36: 059 | W36: Papel en Hojas | X36: 1 | Z36: RES | AA36: 1 | AB36: 1 | AC36: 1
A37: DESMOLDANTE 40 X 60 | B37: 0002DES04060 | C37: 34 | D37: 0002DES04060 | E37: .0000 | F37: 5.0000 | G37: .0000 | I37: Resmas | K37: 1 | L37: RES | M37: 007 | N37: 1 | O37: Papeles | P37: 001 | Q37: Papel | R37: 1 | S37: 001 | T37: Manufactured Group Locally | U37: 1 | V37: 059 | W37: Papel en Hojas | X37: 1 | Z37: RES | AA37: 1 | AB37: 1 | AC37: 1
A38: DESMOLDANTE 45 X 70 | B38: 0002DES04565 | C38: 35 | D38: 0002DES04565 | E38: .0000 | F38: 5.0000 | G38: .0000 | I38: Resmas | K38: 1 | L38: RES | M38: 007 | N38: 1 | O38: Papeles | P38: 001 | Q38: Papel | R38: 1 | S38: 001 | T38: Manufactured Group Locally | U38: 1 | V38: 001 | W38: Bolsas de Papel | X38: 1 | Z38: RES | AA38: 1 | AB38: 1 | AC38: 1
A39: DESMOLDANTE 60 X 80 | B39: 0002DES06080 | C39: 36 | D39: 0002DES06080 | E39: .0000 | F39: 5.0000 | G39: .0000 | I39: Unidades | K39: 1 | L39: UN | M39: 007 | N39: 1 | O39: Papeles | P39: 001 | Q39: Papel | R39: 1 | S39: 001 | T39: Manufactured Group Locally | U39: 1 | V39: 059 | W39: Papel en Hojas | X39: 1 | Z39: UN | AA39: 1 | AB39: 1 | AC39: 1
A40: DESMOLDANTE 70 X 90 | B40: 0002DES07090 | C40: 37 | D40: 0002DES07090 | E40: .0000 | F40: 5.0000 | G40: .0000 | I40: Resmas | K40: 1 | L40: RES | M40: 007 | N40: 1 | O40: Papeles | P40: 001 | Q40: Papel | R40: 1 | S40: 001 | T40: Manufactured Group Locally | U40: 1 | V40: 001 | W40: Bolsas de Papel | X40: 1 | Z40: RES | AA40: 1 | AB40: 1 | AC40: 1
A41: SEDA BLANCO 75 X 100 (400 H) | B41: 0002SED75100 | C41: 38 | D41: 0002SED75100 | E41: .0000 | F41: 10.0000 | G41: .0000 | I41: Resmas | K41: 1 | L41: RES | M41: 007 | N41: 1 | O41: Papeles | P41: 001 | Q41: Papel | R41: 1 | S41: 001 | T41: Manufactured Group Locally | U41: 1 | V41: 001 | W41: Bolsas de Papel | X41: 1 | Z41: RES | AA41: 1 | AB41: 1 | AC41: 1 | AE41: 2025-05-22-00.00.00.000000
A42: BOBINA BLANCO SEIN 40 CM. | B42: 0003BCO00040 | C42: 39 | D42: 0003BCO00040 | E42: .0000 | F42: 1.0000 | G42: .0000 | I42: Kilogramos | K42: 1 | L42: KG | M42: 007 | N42: 1 | O42: Papeles | P42: 001 | Q42: Papel | R42: 1 | S42: 001 | T42: Manufactured Group Locally | U42: 1 | V42: 001 | W42: Bolsas de Papel | X42: 1 | Z42: KG | AA42: 1 | AB42: 1 | AC42: 1
A43: BOBINA BLANCO SEIN 60 CM. | B43: 0003BCO00060 | C43: 40 | D43: 0003BCO00060 | E43: .0000 | F43: 1.0000 | G43: .0000 | I43: Kilogramos | K43: 1 | L43: KG | M43: 007 | N43: 1 | O43: Papeles | P43: 001 | Q43: Papel | R43: 1 | S43: 001 | T43: Manufactured Group Locally | U43: 1 | V43: 001 | W43: Bolsas de Papel | X43: 1 | Z43: KG | AA43: 1 | AB43: 1 | AC43: 1
A44: BOBINA SULFITO PRIMERA 40 CM. | B44: 0003BCP00040 | C44: 41 | D44: 0003BCP00040 | E44: .0000 | F44: 1.0000 | G44: .0000 | I44: Kilogramos | K44: 1 | L44: KG | M44: 007 | N44: 1 | O44: Papeles | P44: 001 | Q44: Papel | R44: 1 | S44: 001 | T44: Manufactured Group Locally | U44: 1 | V44: 001 | W44: Bolsas de Papel | X44: 1 | Z44: KG | AA44: 1 | AB44: 1 | AC44: 1 | AE44: 2025-05-22-00.00.00.000000
A45: BOBINA SULFITO PRIMERA 60 CM. | B45: 0003BCP00060 | C45: 42 | D45: 0003BCP00060 | E45: .0000 | F45: 1.0000 | G45: .0000 | I45: Kilogramos | K45: 1 | L45: KG | M45: 007 | N45: 1 | O45: Papeles | P45: 001 | Q45: Papel | R45: 1 | S45: 001 | T45: Manufactured Group Locally | U45: 1 | V45: 001 | W45: Bolsas de Papel | X45: 1 | Z45: KG | AA45: 1 | AB45: 1 | AC45: 1 | AE45: 2025-05-22-00.00.00.000000
A46: BOBINA KRAFT 50 SEIN 40 CM. | B46: 0003KRA00040 | C46: 43 | D46: 0003KRA00040 | E46: .0000 | F46: 1.0000 | G46: .0000 | I46: Kilogramos | K46: 1 | L46: KG | M46: 007 | N46: 1 | O46: Papeles | P46: 001 | Q46: Papel | R46: 1 | S46: 001 | T46: Manufactured Group Locally | U46: 1 | V46: 001 | W46: Bolsas de Papel | X46: 1 | Z46: KG | AA46: 1 | AB46: 1 | AC46: 1 | AE46: 2025-05-22-00.00.00.000000
A47: BOBINA KRAFT 80 SEIN 40 CM. | B47: 0003KRA00041 | C47: 44 | D47: 0003KRA00041 | E47: .0000 | F47: 1.0000 | G47: .0000 | I47: Kilogramos | K47: 1 | L47: KG | M47: 007 | N47: 1 | O47: Papeles | P47: 001 | Q47: Papel | R47: 1 | S47: 001 | T47: Manufactured Group Locally | U47: 1 | V47: 001 | W47: Bolsas de Papel | X47: 1 | Z47: KG | AA47: 1 | AB47: 1 | AC47: 1 | AE47: 2025-05-22-00.00.00.000000
A48: BOBINA KRAFT 50 SEIN 60 CM. | B48: 0003KRA00060 | C48: 45 | D48: 0003KRA00060 | E48: .0000 | F48: 1.0000 | G48: .0000 | I48: Kilogramos | K48: 1 | L48: KG | M48: 007 | N48: 1 | O48: Papeles | P48: 001 | Q48: Papel | R48: 1 | S48: 001 | T48: Manufactured Group Locally | U48: 1 | V48: 001 | W48: Bolsas de Papel | X48: 1 | Z48: KG | AA48: 1 | AB48: 1 | AC48: 1 | AE48: 2025-05-22-00.00.00.000000
A49: BOBINA KRAFT 80 SEIN 60 CM. | B49: 0003KRA00061 | C49: 46 | D49: 0003KRA00061 | E49: .0000 | F49: 1.0000 | G49: .0000 | I49: Kilogramos | K49: 1 | L49: KG | M49: 007 | N49: 1 | O49: Papeles | P49: 001 | Q49: Papel | R49: 1 | S49: 001 | T49: Manufactured Group Locally | U49: 1 | V49: 001 | W49: Bolsas de Papel | X49: 1 | Z49: KG | AA49: 1 | AB49: 1 | AC49: 1 | AE49: 2025-05-22-00.00.00.000000
A50: BOBINA KRAFT 80 SEIN 80 CM. | B50: 0003KRA00081 | C50: 47 | D50: 0003KRA00081 | E50: .0000 | F50: 1.0000 | G50: .0000 | I50: Kilogramos | K50: 1 | L50: KG | M50: 007 | N50: 1 | O50: Papeles | P50: 001 | Q50: Papel | R50: 1 | S50: 001 | T50: Manufactured Group Locally | U50: 1 | V50: 001 | W50: Bolsas de Papel | X50: 1 | Z50: KG | AA50: 1 | AB50: 1 | AC50: 1 | AE50: 2025-05-22-00.00.00.000000
A51: PAPEL SEPARADOR PARA PICADA 11CM | B51: 0003PER00011 | C51: 904 | D51: 0003PER00011 | E51: .0000 | F51: 5.0000 | G51: .0000 | I51: Unidades | K51: 1 | L51: UN | M51: 007 | N51: 1 | O51: Papeles | P51: 001 | Q51: Papel | R51: 1 | S51: 001 | T51: Manufactured Group Locally | U51: 1 | V51: 001 | W51: Bolsas de Papel | X51: 1 | Z51: UN | AA51: 1 | AB51: 1 | AC51: 1
A52: BSAS KRAFT Nº 2L | B52: 0004KRA0002L | C52: 48 | D52: 0004KRA0002L | E52: .0000 | F52: 4.3000 | G52: .0000 | I52: Paquetes | K52: 1 | L52: PAQ | M52: 007 | N52: 1 | O52: Papeles | P52: 001 | Q52: Papel | R52: 1 | S52: 001 | T52: Manufactured Group Locally | U52: 1 | V52: 001 | W52: Bolsas de Papel | X52: 1 | Z52: PAQ | AA52: 1000 | AB52: 1000 | AC52: 1
A53: BSAS KRAFT Nº 3 | B53: 0004KRA0003C | C53: 49 | D53: 0004KRA0003C | E53: .0000 | F53: 4.8500 | G53: .0000 | I53: Paquetes | K53: 1 | L53: PAQ | M53: 007 | N53: 1 | O53: Papeles | P53: 001 | Q53: Papel | R53: 1 | S53: 001 | T53: Manufactured Group Locally | U53: 1 | V53: 001 | W53: Bolsas de Papel | X53: 1 | Z53: PAQ | AA53: 1000 | AB53: 1000 | AC53: 1
A54: BSAS KRAFT Nº 3L | B54: 0004KRA0003L | C54: 50 | D54: 0004KRA0003L | E54: .0000 | F54: 5.6500 | G54: .0000 | I54: Paquetes | K54: 1 | L54: PAQ | M54: 007 | N54: 1 | O54: Papeles | P54: 001 | Q54: Papel | R54: 1 | S54: 001 | T54: Manufactured Group Locally | U54: 1 | V54: 001 | W54: Bolsas de Papel | X54: 1 | Z54: PAQ | AA54: 1000 | AB54: 1000 | AC54: 1
A55: BSAS KRAFT Nº 4A | B55: 0004KRA0004A | C55: 51 | D55: 0004KRA0004A | E55: .0000 | F55: 6.5000 | G55: .0000 | I55: Paquetes | K55: 1 | L55: PAQ | M55: 007 | N55: 1 | O55: Papeles | P55: 001 | Q55: Papel | R55: 1 | S55: 001 | T55: Manufactured Group Locally | U55: 1 | V55: 001 | W55: Bolsas de Papel | X55: 1 | Z55: PAQ | AA55: 1000 | AB55: 1000 | AC55: 1
A56: BSAS KRAFT Nº 4 | B56: 0004KRA0004C | C56: 52 | D56: 0004KRA0004C | E56: .0000 | F56: 6.8500 | G56: .0000 | I56: Paquetes | K56: 1 | L56: PAQ | M56: 007 | N56: 1 | O56: Papeles | P56: 001 | Q56: Papel | R56: 1 | S56: 001 | T56: Manufactured Group Locally | U56: 1 | V56: 001 | W56: Bolsas de Papel | X56: 1 | Z56: PAQ | AA56: 1000 | AB56: 1000 | AC56: 1
A57: BSAS KRAFT Nº 5 | B57: 0004KRA0005C | C57: 53 | D57: 0004KRA0005C | E57: .0000 | F57: 7.4000 | G57: .0000 | I57: Paquetes | K57: 1 | L57: PAQ | M57: 007 | N57: 1 | O57: Papeles | P57: 001 | Q57: Papel | R57: 1 | S57: 001 | T57: Manufactured Group Locally | U57: 1 | V57: 001 | W57: Bolsas de Papel | X57: 1 | Z57: PAQ | AA57: 1000 | AB57: 1000 | AC57: 1
A58: BSAS KRAFT Nº 6 | B58: 0004KRA0006C | C58: 54 | D58: 0004KRA0006C | E58: .0000 | F58: 8.5500 | G58: .0000 | I58: Paquetes | K58: 1 | L58: PAQ | M58: 007 | N58: 1 | O58: Papeles | P58: 001 | Q58: Papel | R58: 1 | S58: 001 | T58: Manufactured Group Locally | U58: 1 | V58: 001 | W58: Bolsas de Papel | X58: 1 | Z58: PAQ | AA58: 1000 | AB58: 1000 | AC58: 1
A59: BSAS KRAFT Nº 6L | B59: 0004KRA0006L | C59: 55 | D59: 0004KRA0006L | E59: .0000 | F59: 9.2000 | G59: .0000 | I59: Paquetes | K59: 1 | L59: PAQ | M59: 007 | N59: 1 | O59: Papeles | P59: 001 | Q59: Papel | R59: 1 | S59: 001 | T59: Manufactured Group Locally | U59: 1 | V59: 001 | W59: Bolsas de Papel | X59: 1 | Z59: PAQ | AA59: 1000 | AB59: 1000 | AC59: 1
A60: BSAS KRAFT Nº 7 | B60: 0004KRA0007C | C60: 56 | D60: 0004KRA0007C | E60: .0000 | F60: 11.0000 | G60: .0000 | I60: Paquetes | K60: 1 | L60: PAQ | M60: 007 | N60: 1 | O60: Papeles | P60: 001 | Q60: Papel | R60: 1 | S60: 001 | T60: Manufactured Group Locally | U60: 1 | V60: 001 | W60: Bolsas de Papel | X60: 1 | Z60: PAQ | AA60: 1000 | AB60: 1000 | AC60: 1
A61: BSAS KRAFT Nº 8 | B61: 0004KRA0008C | C61: 57 | D61: 0004KRA0008C | E61: .0000 | F61: 13.2500 | G61: .0000 | I61: Paquetes | K61: 1 | L61: PAQ | M61: 007 | N61: 1 | O61: Papeles | P61: 001 | Q61: Papel | R61: 1 | S61: 001 | T61: Manufactured Group Locally | U61: 1 | V61: 001 | W61: Bolsas de Papel | X61: 1 | Z61: PAQ | AA61: 1000 | AB61: 1000 | AC61: 1
A62: BOLSA DELIVERY CHICA 37 x 20 x 12 cm ( X 250) | B62: 0004KRA00090 | C62: 58 | D62: 0004KRA00090 | E62: .0000 | F62: 2.8000 | G62: .0000 | I62: Paquetes | K62: 1 | L62: PAQ | M62: 007 | N62: 1 | O62: Papeles | P62: 001 | Q62: Papel | R62: 1 | S62: 001 | T62: Manufactured Group Locally | U62: 1 | V62: 001 | W62: Bolsas de Papel | X62: 1 | Z62: PAQ | AA62: 250 | AB62: 250 | AC62: 1
... A75: SERVILLETA 33 X 33 | B75: 0005SER03333 | C75: 71 | D75: 0005SER03333 | E75: .0000 | F75: 2.7500 | G75: .0000 | I75: Cajas | K75: 1 | L75: CAJ | M75: 007 | N75: 1 | O75: Papeles | P75: 001 | Q75: Papel | R75: 1 | S75: 003 | T75: Purchased from 3rd Party | U75: 1 | V75: 002 | W75: Servilletas/Papel Cocina | X75: 1 | Z75: CAJ | AA75: 1000 | AB75: 1000 | AC75: 1
A76: SERVILLETA (X 10.000) | B76: 0005SER10000 | C76: 72 | D76: 0005SER10000 | E76: .0000 | F76: 3.0000 | G76: .0000 | I76: Cajas | K76: 1 | L76: CAJ | M76: 007 | N76: 1 | O76: Papeles | P76: 001 | Q76: Papel | R76: 1 | S76: 003 | T76: Purchased from 3rd Party | U76: 1 | V76: 002 | W76: Servilletas/Papel Cocina | X76: 1 | Z76: CAJ | AA76: 10000 | AB76: 10000 | AC76: 1 | AE76: 2024-04-11-00.00.00.000000
A77: SERVILLETAS DELIVERY ENSOBRADO x 2 (X 500) | B77: 0005SERZ0001 | C77: 73 | D77: 0005SERZ0001 | E77: .0000 | F77: 2.2500 | G77: .0000 | I77: Cajas | K77: 1 | L77: CAJ | M77: 007 | N77: 1 | O77: Papeles | P77: 001 | Q77: Papel | R77: 1 | S77: 003 | T77: Purchased from 3rd Party | U77: 1 | V77: 002 | W77: Servilletas/Papel Cocina | X77: 1 | Z77: CAJ | AA77: 500 | AB77: 500 | AC77: 1
A78: CARPETA BORDADA 34X41 | B78: 0006BOR03441 | C78: 74 | D78: 0006BOR03441 | E78: .0000 | F78: .6000 | G78: .0000 | I78: Paquetes | K78: 1 | L78: PAQ | M78: 007 | N78: 1 | O78: Papeles | P78: 001 | Q78: Papel | R78: 1 | S78: 003 | T78: Purchased from 3rd Party | U78: 1 | V78: 003 | W78: Moldes de Papel | X78: 1 | Z78: PAQ | AA78: 100 | AB78: 100 | AC78: 1
A79: MOLDE BIZCOCHUELO Nº 16 | B79: 0008MBI00016 | C79: 75 | D79: 0008MBI00016 | E79: .0000 | F79: 1.0000 | G79: .0000 | I79: Paquetes | K79: 1 | L79: PAQ | M79: 007 | N79: 1 | O79: Papeles | P79: 001 | Q79: Papel | R79: 1 | S79: 003 | T79: Purchased from 3rd Party | U79: 1 | V79: 003 | W79: Moldes de Papel | X79: 1 | Z79: PAQ | AA79: 200 | AB79: 200 | AC79: 1
A80: MOLDE BIZCOCHUELO Nº 20 | B80: 0008MBI00020 | C80: 76 | D80: 0008MBI00020 | E80: .0000 | F80: 1.3000 | G80: .0000 | I80: Paquetes | K80: 1 | L80: PAQ | M80: 007 | N80: 1 | O80: Papeles | P80: 001 | Q80: Papel | R80: 1 | S80: 003 | T80: Purchased from 3rd Party | U80: 1 | V80: 003 | W80: Moldes de Papel | X80: 1 | Z80: PAQ | AA80: 200 | AB80: 200 | AC80: 1
A81: MOLDE BIZCOCHUELO Nº 22 | B81: 0008MBI00022 | C81: 77 | D81: 0008MBI00022 | E81: .0000 | F81: 1.4000 | G81: .0000 | I81: Paquetes | K81: 1 | L81: PAQ | M81: 007 | N81: 1 | O81: Papeles | P81: 001 | Q81: Papel | R81: 1 | S81: 003 | T81: Purchased from 3rd Party | U81: 1 | V81: 003 | W81: Moldes de Papel | X81: 1 | Z81: PAQ | AA81: 200 | AB81: 200 | AC81: 1 | AE81: 2025-05-22-00.00.00.000000
A82: MOLDE BUDIN P/C CHICO x1000 (220) | B82: 0008MBU00220 | C82: 958 | D82: 0008MBU00220 | E82: .0000 | F82: 7.5000 | G82: .0000 | I82: Cajas | K82: 1 | L82: CAJ | M82: 007 | N82: 1 | O82: Papeles | P82: 001 | Q82: Papel | R82: 1 | S82: 003 | T82: Purchased from 3rd Party | U82: 1 | V82: 003 | W82: Moldes de Papel | X82: 1 | Z82: CAJ | AA82: 1000 | AB82: 1000 | AC82: 1
A83: MOLDE BUDIN P/C GRANDE x1000 (500) | B83: 0008MBU00500 | C83: 959 | D83: 0008MBU00500 | E83: .0000 | F83: 14.0000 | G83: .0000 | I83: Cajas | K83: 1 | L83: CAJ | M83: 007 | N83: 1 | O83: Papeles | P83: 001 | Q83: Papel | R83: 1 | S83: 003 | T83: Purchased from 3rd Party | U83: 1 | V83: 003 | W83: Moldes de Papel | X83: 1 | Z83: CAJ | AA83: 1000 | AB83: 1000 | AC83: 1
A84: MOLDE PAN DULCE LI.1/4 KG. | B84: 0008MPDL0250 | C84: 78 | D84: 0008MPDL0250 | E84: .0000 | F84: .0000 | G84: .0000 | I84: Cajas | K84: 1 | L84: CAJ | M84: 007 | N84: 1 | O84: Papeles | P84: 001 | Q84: Papel | R84: 1 | S84: 003 | T84: Purchased from 3rd Party | U84: 1 | V84: 003 | W84: Moldes de Papel | X84: 1 | Z84: CAJ | AA84: 1000 | AB84: 1000 | AC84: 1 | AE84: 2024-04-11-00.00.00.000000
A85: MOLDE PAN DULCE LI.1/2 KG. | B85: 0008MPDL0500 | C85: 79 | D85: 0008MPDL0500 | E85: 1.0000 | F85: 5.0000 | G85: .0000 | I85: Cajas | K85: 1 | L85: CAJ | M85: 007 | N85: 1 | O85: Papeles | P85: 001 | Q85: Papel | R85: 1 | S85: 003 | T85: Purchased from 3rd Party | U85: 1 | V85: 003 | W85: Moldes de Papel | X85: 1 | Z85: CAJ | AA85: 1000 | AB85: 1000 | AC85: 1 | AE85: 2024-04-11-00.00.00.000000
A86: MOLDE PAN DULCE 1KG | B86: 0008MPDL1000 | C86: 929 | D86: 0008MPDL1000 | E86: 1.0000 | F86: 6.0000 | G86: .0000 | I86: Cajas | K86: 1 | L86: CAJ | M86: 007 | N86: 1 | O86: Papeles | P86: 001 | Q86: Papel | R86: 1 | S86: 003 | T86: Purchased from 3rd Party | U86: 1 | V86: 003 | W86: Moldes de Papel | X86: 1 | Z86: CAJ | AA86: 1000 | AB86: 1000 | AC86: 1
A87: MOLDE ROSCA Nº 20 | B87: 0008MRO00020 | C87: 80 | D87: 0008MRO00020 | E87: .0000 | F87: .7500 | G87: .0000 | I87: Paquetes | K87: 1 | L87: PAQ | M87: 007 | N87: 1 | O87: Papeles | P87: 001 | Q87: Papel | R87: 1 | S87: 003 | T87: Purchased from 3rd Party | U87: 1 | V87: 003 | W87: Moldes de Papel | X87: 1 | Z87: PAQ | AA87: 100 | AB87: 100 | AC87: 1
A88: MOLDE ROSCA Nº 22 | B88: 0008MRO00022 | C88: 81 | D88: 0008MRO00022 | E88: .0000 | F88: 1.0000 | G88: .0000 | I88: Paquetes | K88: 1 | L88: PAQ | M88: 007 | N88: 1 | O88: Papeles | P88: 001 | Q88: Papel | R88: 1 | S88: 003 | T88: Purchased from 3rd Party | U88: 1 | V88: 003 | W88: Moldes de Papel | X88: 1 | Z88: PAQ | AA88: 100 | AB88: 100 | AC88: 1 | AE88: 2025-05-22-00.00.00.000000
A89: PIROTINES Nº 5 | B89: 0008PIR00005 | C89: 82 | D89: 0008PIR00005 | E89: .0000 | F89: .6000 | G89: .0000 | I89: Cajas | K89: 1 | L89: CAJ | M89: 007 | N89: 1 | O89: Papeles | P89: 001 | Q89: Papel | R89: 1 | S89: 003 | T89: Purchased from 3rd Party | U89: 1 | V89: 003 | W89: Moldes de Papel | X89: 1 | Z89: CAJ | AA89: 1000 | AB89: 1000 | AC89: 1
A90: PIROTINES Nº 10 | B90: 0008PIR00010 | C90: 83 | D90: 0008PIR00010 | E90: .0000 | F90: .8000 | G90: .0000 | I90: Cajas | K90: 1 | L90: CAJ | M90: 007 | N90: 1 | O90: Papeles | P90: 001 | Q90: Papel | R90: 1 | S90: 003 | T90: Purchased from 3rd Party | U90: 1 | V90: 003 | W90: Moldes de Papel | X90: 1 | Z90: CAJ | AA90: 1000 | AB90: 1000 | AC90: 1
A91: CARTON BLANCO CIFIVE | B91: 0011PRI00003 | C91: 84 | D91: 0011PRI00003 | E91: .0000 | F91: 1.0000 | G91: .0000 | I91: Kilogramos | K91: 1 | L91: KG | M91: 008 | N91: 1 | O91: Cartón | P91: 001 | Q91: Papel | R91: 1 | S91: 003 | T91: Purchased from 3rd Party | U91: 1 | V91: 004 | W91: Carton en Hojas | X91: 1 | Z91: KG | AA91: 1 | AB91: 1 | AC91: 1
A92: CARTON GRIS Nº 30 | B92: 0011SEG00030 | C92: 85 | D92: 0011SEG00030 | E92: .0000 | F92: 1.0000 | G92: .0000 | I92: Kilogramos | K92: 1 | L92: KG | M92: 008 | N92: 1 | O92: Cartón | P92: 001 | Q92: Papel | R92: 1 | S92: 003 | T92: Purchased from 3rd Party | U92: 1 | V92: 004 | W92: Carton en Hojas | X92: 1 | Z92: KG | AA92: 1 | AB92: 1 | AC92: 1
A93: CARTON GRIS Nº 40 | B93: 0011SEG00040 | C93: 86 | D93: 0011SEG00040 | E93: .0000 | F93: 1.0000 | G93: .0000 | I93: Kilogramos | K93: 1 | L93: KG | M93: 008 | N93: 1 | O93: Cartón | P93: 001 | Q93: Papel | R93: 1 | S93: 003 | T93: Purchased from 3rd Party | U93: 1 | V93: 004 | W93: Carton en Hojas | X93: 1 | Z93: KG | AA93: 1 | AB93: 1 | AC93: 1
A94: BANDEJA DE CARTON Nº 1 12X15 | B94: 0012COM00001 | C94: 87 | D94: 0012COM00001 | E94: .0000 | F94: .6000 | G94: .0000 | I94: Paquetes | K94: 1 | L94: PAQ | M94: 008 | N94: 1 | O94: Cartón | P94: 001 | Q94: Papel | R94: 1 | S94: 003 | T94: Purchased from 3rd Party | U94: 1 | V94: 005 | W94: Bandejas de Papel / Carton | X94: 1 | Z94: PAQ | AA94: 100 | AB94: 100 | AC94: 1
A95: BANDEJA DE CARTON Nº 2 15X17 | B95: 0012COM00002 | C95: 88 | D95: 0012COM00002 | E95: .0000 | F95: 1.0000 | G95: .0000 | I95: Paquetes | K95: 1 | L95: PAQ | M95: 008 | N95: 1 | O95: Cartón | P95: 001 | Q95: Papel | R95: 1 | S95: 003 | T95: Purchased from 3rd Party | U95: 1 | V95: 005 | W95: Bandejas de Papel / Carton | X95: 1 | Z95: PAQ | AA95: 100 | AB95: 100 | AC95: 1
A96: BANDEJA DE CARTON Nº 3 17X21 | B96: 0012COM00003 | C96: 89 | D96: 0012COM00003 | E96: .0000 | F96: 1.2000 | G96: .0000 | I96: Paquetes | K96: 1 | L96: PAQ | M96: 008 | N96: 1 | O96: Cartón | P96: 001 | Q96: Papel | R96: 1 | S96: 003 | T96: Purchased from 3rd Party | U96: 1 | V96: 005 | W96: Bandejas de Papel / Carton | X96: 1 | Z96: PAQ | AA96: 100 | AB96: 100 | AC96: 1
A97: BANDEJA DE CARTON Nº 4 18X23 | B97: 0012COM00004 | C97: 90 | D97: 0012COM00004 | E97: .0000 | F97: 1.4000 | G97: .0000 | I97: Paquetes | K97: 1 | L97: PAQ | M97: 008 | N97: 1 | O97: Cartón | P97: 001 | Q97: Papel | R97: 1 | S97: 003 | T97: Purchased from 3rd Party | U97: 1 | V97: 005 | W97: Bandejas de Papel / Carton | X97: 1 | Z97: PAQ | AA97: 100 | AB97: 100 | AC97: 1
A98: BANDEJA DE CARTON Nº 5 20X26 | B98: 0012COM00005 | C98: 91 | D98: 0012COM00005 | E98: .0000 | F98: 2.0000 | G98: .0000 | I98: Paquetes | K98: 1 | L98: PAQ | M98: 008 | N98: 1 | O98: Cartón | P98: 001 | Q98: Papel | R98: 1 | S98: 003 | T98: Purchased from 3rd Party | U98: 1 | V98: 005 | W98: Bandejas de Papel / Carton | X98: 1 | Z98: PAQ | AA98: 100 | AB98: 100 | AC98: 1
A99: BANDEJA DE CARTON Nº 6 21X29 | B99: 0012COM00006 | C99: 92 | D99: 0012COM00006 | E99: .0000 | F99: 2.4000 | G99: .0000 | I99: Paquetes | K99: 1 | L99: PAQ | M99: 008 | N99: 1 | O99: Cartón | P99: 001 | Q99: Papel | R99: 1 | S99: 003 | T99: Purchased from 3rd Party | U99: 1 | V99: 005 | W99: Bandejas de Papel / Carton | X99: 1 | Z99: PAQ | AA99: 100 | AB99: 100 | AC99: 1
A100: BANDEJA DE CARTON Nº 13 1/2 | B100: 0012COM00015 | C100: 93 | D100: 0012COM00015 | E100: .0000 | F100: .0000 | G100: .0000 | I100: Paquetes | K100: 1 | L100: PAQ | M100: 008 | N100: 1 | O100: Cartón | P100: 001 | Q100: Papel | R100: 1 | S100: 003 | T100: Purchased from 3rd Party | U100: 1 | V100: 005 | W100: Bandejas de Papel / Carton | X100: 1 | Z100: PAQ | AA100: 100 | AB100: 100 | AC100: 1 | AE100: 2024-04-11-00.00.00.000000
A101: BANDEJA KRAFT PURO N°1 (6PX100U) | B101: 0012COM00051 | C101: 775 | D101: 0012COM00051 | E101: .0000 | F101: 6.0000 | G101: .0000 | I101: Cajas | K101: 1 | L101: CAJ | M101: 008 | N101: 1 | O101: Cartón | P101: 001 | Q101: Papel | R101: 1 | S101: 001 | T101: Manufactured Group Locally | U101: 1 | V101: 005 | W101: Bandejas de Papel / Carton | X101: 1 | Z101: CAJ | AA101: 600 | AB101: 600 | AC101: 1
A102: BANDEJA KRAFT PURO N°2 (6PX100U) | B102: 0012COM00052 | C102: 94 | D102: 0012COM00052 | E102: .0000 | F102: 6.0000 | G102: .0000 | I102: Cajas | K102: 1 | L102: CAJ | M102: 008 | N102: 1 | O102: Cartón | P102: 001 | Q102: Papel | R102: 1 | S102: 001 | T102: Manufactured Group Locally | U102: 1 | V102: 005 | W102: Bandejas de Papel / Carton | X102: 1 | Z102: CAJ | AA102: 600 | AB102: 600 | AC102: 1
A103: BANDEJA KRAFT PURO N°3 (4PX100U) | B103: 0012COM00053 | C103: 95 | D103: 0012COM00053 | E103: .0000 | F103: 6.0000 | G103: .0000 | I103: Cajas | K103: 1 | L103: CAJ | M103: 008 | N103: 1 | O103: Cartón | P103: 001 | Q103: Papel | R103: 1 | S103: 001 | T103: Manufactured Group Locally | U103: 1 | V103: 005 | W103: Bandejas de Papel / Carton | X103: 1 | Z103: CAJ | AA103: 400 | AB103: 400 | AC103: 1
A104: BANDEJA KRAFT PURO N°4 (2PX100U) | B104: 0012COM00054 | C104: 96 | D104: 0012COM00054 | E104: .0000 | F104: 3.9000 | G104: .0000 | I104: Cajas | K104: 1 | L104: CAJ | M104: 008 | N104: 1 | O104: Cartón | P104: 001 | Q104: Papel | R104: 1 | S104: 001 | T104: Manufactured Group Locally | U104: 1 | V104: 005 | W104: Bandejas de Papel / Carton | X104: 1 | Z104: CAJ | AA104: 200 | AB104: 200 | AC104: 1
A105: BANDEJA MICRO CORRUGADO N° 2 (4PX100U) | B105: 0012COM10002 | C105: 97 | D105: 0012COM10002 | E105: .0000 | F105: 4.0000 | G105: .0000 | I105: Cajas | K105: 1 | L105: CAJ | M105: 008 | N105: 1 | O105: Cartón | P105: 001 | Q105: Papel | R105: 1 | S105: 001 | T105: Manufactured Group Locally | U105: 1 | V105: 005 | W105: Bandejas de Papel / Carton | X105: 1 | Z105: CAJ | AA105: 400 | AB105: 400 | AC105: 1
A106: BANDEJA MICRO CORRUGADO N° 3 (4PX100U) | B106: 0012COM10003 | C106: 98 | D106: 0012COM10003 | E106: .0000 | F106: 6.0000 | G106: .0000 | I106: Cajas | K106: 1 | L106: CAJ | M106: 008 | N106: 1 | O106: Cartón | P106: 001 | Q106: Papel | R106: 1 | S106: 001 | T106: Manufactured Group Locally | U106: 1 | V106: 005 | W106: Bandejas de Papel / Carton | X106: 1 | Z106: CAJ | AA106: 400 | AB106: 400 | AC106: 1
A107: BANDEJA MICRO CORRUGADO N° 4 (4PX100U) | B107: 0012COM10004 | C107: 99 | D107: 0012COM10004 | E107: .0000 | F107: 7.0000 | G107: .0000 | I107: Cajas | K107: 1 | L107: CAJ | M107: 008 | N107: 1 | O107: Cartón | P107: 001 | Q107: Papel | R107: 1 | S107: 001 | T107: Manufactured Group Locally | U107: 1 | V107: 005 | W107: Bandejas de Papel / Carton | X107: 1 | Z107: CAJ | AA107: 400 | AB107: 400 | AC107: 1
A108: BANDEJA MICRO CORRUGADO N° 5 (2PX100U) | B108: 0012COM10005 | C108: 100 | D108: 0012COM10005 | E108: .0000 | F108: 5.0000 | G108: .0000 | I108: Cajas | K108: 1 | L108: CAJ | M108: 008 | N108: 1 | O108: Cartón | P108: 001 | Q108: Papel | R108: 1 | S108: 001 | T108: Manufactured Group Locally | U108: 1 | V108: 005 | W108: Bandejas de Papel / Carton | X108: 1 | Z108: CAJ | AA108: 200 | AB108: 200 | AC108: 1
A109: BANDEJA MICRO CORRUGADO N° 6 (4P X 50U) | B109: 0012COM10006 | C109: 101 | D109: 0012COM10006 | E109: .0000 | F109: 3.6000 | G109: .0000 | I109: Cajas | K109: 1 | L109: CAJ | M109: 008 | N109: 1 | O109: Cartón | P109: 001 | Q109: Papel | R109: 1 | S109: 001 | T109: Manufactured Group Locally | U109: 1 | V109: 005 | W109: Bandejas de Papel / Carton | X109: 1 | Z109: CAJ | AA109: 200 | AB109: 200 | AC109: 1
A110: BANDEJA MICRO CORRUGADO N°2 IMPRESA | B110: 0012COM10012 | C110: 102 | D110: 0012COM10012 | E110: .0000 | F110: 5.0000 | G110: .0000 | I110: Cajas | K110: 1 | L110: CAJ | M110: 008 | N110: 1 | O110: Cartón | P110: 001 | Q110: Papel | R110: 1 | S110: 001 | T110: Manufactured Group Locally | U110: 1 | V110: 005 | W110: Bandejas de Papel / Carton | X110: 1 | Z110: CAJ | AA110: 400 | AB110: 400 | AC110: 1
A111: BANDEJA MICRO CORRUGADO N°3 IMPRESA | B111: 0012COM10013 | C111: 103 | D111: 0012COM10013 | E111: .0000 | F111: 6.0000 | G111: .0000 | I111: Cajas | K111: 1 | L111: CAJ | M111: 008 | N111: 1 | O111: Cartón | P111: 001 | Q111: Papel | R111: 1 | S111: 001 | T111: Manufactured Group Locally | U111: 1 | V111: 005 | W111: Bandejas de Papel / Carton | X111: 1 | Z111: CAJ | AA111: 400 | AB111: 400 | AC111: 1
A112: BANDEJA MICRO CORRUGADO N°4 IMPRESA | B112: 0012COM10014 | C112: 104 | D112: 0012COM10014 | E112: .0000 | F112: 7.0000 | G112: .0000 | I112: Cajas | K112: 1 | L112: CAJ | M112: 008 | N112: 1 | O112: Cartón | P112: 001 | Q112: Papel | R112: 1 | S112: 001 | T112: Manufactured Group Locally | U112: 1 | V112: 005 | W112: Bandejas de Papel / Carton | X112: 1 | Z112: CAJ | AA112: 400 | AB112: 400 | AC112: 1
... A122: PLATO DORADO N3 26 CM. | B122: 0015PLA00003 | C122: 113 | D122: 0015PLA00003 | E122: .0000 | F122: 2.6000 | G122: .0000 | I122: Paquetes | K122: 1 | L122: PAQ | M122: 008 | N122: 1 | O122: Cartón | P122: 001 | Q122: Papel | R122: 1 | S122: 003 | T122: Purchased from 3rd Party | U122: 1 | V122: 010 | W122: Platos de Carton | X122: 1 | Z122: PAQ | AA122: 50 | AB122: 50 | AC122: 1
A123: PLATO DORADO N5 31 CM. | B123: 0015PLA00005 | C123: 114 | D123: 0015PLA00005 | E123: .0000 | F123: 2.9000 | G123: .0000 | I123: Paquetes | K123: 1 | L123: PAQ | M123: 008 | N123: 1 | O123: Cartón | P123: 001 | Q123: Papel | R123: 1 | S123: 003 | T123: Purchased from 3rd Party | U123: 1 | V123: 010 | W123: Platos de Carton | X123: 1 | Z123: PAQ | AA123: 50 | AB123: 50 | AC123: 1 | AE123: 2025-05-22-00.00.00.000000
A124: PLATO DOR. N10 14X19 1/4KG | B124: 0015PLA00010 | C124: 115 | D124: 0015PLA00010 | E124: .0000 | F124: 2.1000 | G124: .0000 | I124: Paquetes | K124: 1 | L124: PAQ | M124: 008 | N124: 1 | O124: Cartón | P124: 001 | Q124: Papel | R124: 1 | S124: 003 | T124: Purchased from 3rd Party | U124: 1 | V124: 010 | W124: Platos de Carton | X124: 1 | Z124: PAQ | AA124: 100 | AB124: 100 | AC124: 1
A125: PLATO DOR. N11 17X23 1/2KG | B125: 0015PLA00011 | C125: 116 | D125: 0015PLA00011 | E125: .0000 | F125: 1.5000 | G125: .0000 | I125: Paquetes | K125: 1 | L125: PAQ | M125: 008 | N125: 1 | O125: Cartón | P125: 001 | Q125: Papel | R125: 1 | S125: 003 | T125: Purchased from 3rd Party | U125: 1 | V125: 010 | W125: Platos de Carton | X125: 1 | Z125: PAQ | AA125: 50 | AB125: 50 | AC125: 1
A126: PLATO DOR. N13 20X27 1KG | B126: 0015PLA00013 | C126: 117 | D126: 0015PLA00013 | E126: .0000 | F126: 2.8000 | G126: .0000 | I126: Paquetes | K126: 1 | L126: PAQ | M126: 008 | N126: 1 | O126: Cartón | P126: 001 | Q126: Papel | R126: 1 | S126: 003 | T126: Purchased from 3rd Party | U126: 1 | V126: 010 | W126: Platos de Carton | X126: 1 | Z126: PAQ | AA126: 50 | AB126: 50 | AC126: 1
A127: PLATO DOR. N14 22X30 1 1/2KG | B127: 0015PLA00014 | C127: 118 | D127: 0015PLA00014 | E127: .0000 | F127: 3.5000 | G127: .0000 | I127: Paquetes | K127: 1 | L127: PAQ | M127: 008 | N127: 1 | O127: Cartón | P127: 001 | Q127: Papel | R127: 1 | S127: 003 | T127: Purchased from 3rd Party | U127: 1 | V127: 010 | W127: Platos de Carton | X127: 1 | Z127: PAQ | AA127: 50 | AB127: 50 | AC127: 1
A128: PLATO DOR. N15 24X32 2KG | B128: 0015PLA00015 | C128: 119 | D128: 0015PLA00015 | E128: .0000 | F128: 4.0000 | G128: .0000 | I128: Paquetes | K128: 1 | L128: PAQ | M128: 008 | N128: 1 | O128: Cartón | P128: 001 | Q128: Papel | R128: 1 | S128: 003 | T128: Purchased from 3rd Party | U128: 1 | V128: 010 | W128: Platos de Carton | X128: 1 | Z128: PAQ | AA128: 50 | AB128: 50 | AC128: 1
A129: PLATO DOR. N17 31X41 3KG | B129: 0015PLA00017 | C129: 120 | D129: 0015PLA00017 | E129: .0000 | F129: 5.2500 | G129: .0000 | I129: Paquetes | K129: 1 | L129: PAQ | M129: 008 | N129: 1 | O129: Cartón | P129: 001 | Q129: Papel | R129: 1 | S129: 003 | T129: Purchased from 3rd Party | U129: 1 | V129: 010 | W129: Platos de Carton | X129: 1 | Z129: PAQ | AA129: 50 | AB129: 50 | AC129: 1
A130: CAJAS PIZZA GRIS CHICA | B130: 0016PIZ00001 | C130: 121 | D130: 0016PIZ00001 | E130: .0000 | F130: 6.3000 | G130: .0000 | I130: Paquetes | K130: 1 | L130: PAQ | M130: 008 | N130: 1 | O130: Cartón | P130: 001 | Q130: Papel | R130: 1 | S130: 003 | T130: Purchased from 3rd Party | U130: 1 | V130: 011 | W130: Cajas Carton | X130: 1 | Z130: PAQ | AA130: 100 | AB130: 100 | AC130: 1 | AE130: 2025-05-22-00.00.00.000000
A131: CAJAS PIZZA GRIS GRANDE | B131: 0016PIZ00002 | C131: 122 | D131: 0016PIZ00002 | E131: .0000 | F131: 7.9000 | G131: .0000 | I131: Paquetes | K131: 1 | L131: PAQ | M131: 008 | N131: 1 | O131: Cartón | P131: 001 | Q131: Papel | R131: 1 | S131: 003 | T131: Purchased from 3rd Party | U131: 1 | V131: 011 | W131: Cajas Carton | X131: 1 | Z131: PAQ | AA131: 100 | AB131: 100 | AC131: 1 | AE131: 2025-05-22-00.00.00.000000
A132: CAJAS PIZZA BLANCA CHICA | B132: 0016PIZ00005 | C132: 123 | D132: 0016PIZ00005 | E132: .0000 | F132: 6.1000 | G132: .0000 | I132: Paquetes | K132: 1 | L132: PAQ | M132: 008 | N132: 1 | O132: Cartón | P132: 001 | Q132: Papel | R132: 1 | S132: 003 | T132: Purchased from 3rd Party | U132: 1 | V132: 011 | W132: Cajas Carton | X132: 1 | Z132: PAQ | AA132: 100 | AB132: 100 | AC132: 1 | AE132: 2025-05-22-00.00.00.000000
A133: CAJAS PIZZA BLANCA GRANDE | B133: 0016PIZ00006 | C133: 124 | D133: 0016PIZ00006 | E133: .0000 | F133: 8.3500 | G133: .0000 | I133: Paquetes | K133: 1 | L133: PAQ | M133: 008 | N133: 1 | O133: Cartón | P133: 001 | Q133: Papel | R133: 1 | S133: 003 | T133: Purchased from 3rd Party | U133: 1 | V133: 011 | W133: Cajas Carton | X133: 1 | Z133: PAQ | AA133: 100 | AB133: 100 | AC133: 1 | AE133: 2025-05-22-00.00.00.000000
A134: CAJAS RAVIOLES | B134: 0016RAV00001 | C134: 125 | D134: 0016RAV00001 | E134: .0000 | F134: 5.0000 | G134: .0000 | I134: Paquetes | K134: 1 | L134: PAQ | M134: 008 | N134: 1 | O134: Cartón | P134: 001 | Q134: Papel | R134: 1 | S134: 003 | T134: Purchased from 3rd Party | U134: 1 | V134: 011 | W134: Cajas Carton | X134: 1 | Z134: PAQ | AA134: 100 | AB134: 100 | AC134: 1 | AE134: 2025-05-22-00.00.00.000000
A135: CARTON CORRUGADO 70 CM. | B135: 0017COR00070 | C135: 126 | D135: 0017COR00070 | E135: .0000 | F135: 3.1000 | G135: .0000 | I135: Rollos | K135: 1 | L135: ROL | M135: 008 | N135: 1 | O135: Cartón | P135: 001 | Q135: Papel | R135: 1 | S135: 003 | T135: Purchased from 3rd Party | U135: 1 | V135: 012 | W135: Rollos Carton | X135: 1 | Z135: ROL | AA135: 1 | AB135: 1 | AC135: 1 | AE135: 2025-05-22-00.00.00.000000
A136: CARTON CORRUGADO 90 CM. | B136: 0017COR00090 | C136: 127 | D136: 0017COR00090 | E136: .0000 | F136: 3.9000 | G136: .0000 | I136: Rollos | K136: 1 | L136: ROL | M136: 008 | N136: 1 | O136: Cartón | P136: 001 | Q136: Papel | R136: 1 | S136: 003 | T136: Purchased from 3rd Party | U136: 1 | V136: 012 | W136: Rollos Carton | X136: 1 | Z136: ROL | AA136: 1 | AB136: 1 | AC136: 1 | AE136: 2025-05-22-00.00.00.000000
...

Sheet Papeles-Cartulina
B2: LISTA DE PRECIOS de 26 DE OCTUBRE 2026 (B18)
B3: COMPAÑÍA LA PILARICA S. A. - DARNEL WWW.DARNELGROUP.COM
B4: CODIGO PILARICA | C4: CODIGO DARNEL | D4: U/M | E4: C/U | F4: DESCRIPCION | G4: COMENTARIO | H4: PRECIO
B5: PAPEL BIOXIDO Y DESMOLDANTE | P5: Marca | Q5: Modelo | R5: Código | S5: Ducha | T5: Bidet | U5: Lavatorio
B6: 0001BIO00002 | D6: kg | E6: 1 | F6: BIOXIDO 75 X 50 | G6: Resma 10 KG. | H6: =_xlfn.XLOOKUP(B6,lista!A:A,lista!C:C,0,0) -> 72428
B7: 0001BIO00004 | D7: kg | E7: 1 | F7: BIOXIDO 37 X 50 | G7: Resma 10 KG. | H7: =_xlfn.XLOOKUP(B7,lista!A:A,lista!C:C,0,0) -> 72428 | P7: FV | Q7: Puelo | R7: 0310/B5-CR | S7: 2
B8: 0001BIO00008 | D8: kg | E8: 1 | F8: BIOXIDO 37 X 25 | G8: Resma 10 KG. | H8: =_xlfn.XLOOKUP(B8,lista!A:A,lista!C:C,0,0) -> 72428 | P8: FV | Q8: Puelo | R8: 0181.01/B5-CR | U8: 1
B9: 0001BIO00016 | D9: kg | E9: 1 | F9: BIOXIDO 18 X 25 | G9: Resma 10 KG. | H9: =_xlfn.XLOOKUP(B9,lista!A:A,lista!C:C,0,0) -> 72428 | P9: FV | Q9: Puelo | R9: 0106/B5-CR | S9: 1
B10: 0002DES03246 | D10: res | E10: 1 | F10: DESMOLDANTE 32 X 46 | G10: Resma 5 KG. | H10: =_xlfn.XLOOKUP(B10,lista!A:A,lista!C:C,0,0) -> 64589 | P10: FV | Q10: Puelo | R10: 0189/B5 | T10: 1
B11: 0002DES04060 | D11: res | E11: 1 | F11: DESMOLDANTE 40 X 60 | G11: Resma 5 KG. | H11: =_xlfn.XLOOKUP(B11,lista!A:A,lista!C:C,0,0) -> 64589 | P11: FV | Q11: Libby | R11: 0206/39 | U11: 1
B12: 0002DES04565 | D12: res | E12: 1 | F12: DESMOLDANTE 45 X 64 | G12: Resma 5 KG. | H12: =_xlfn.XLOOKUP(B12,lista!A:A,lista!C:C,0,0) -> 64589 | P12: FV | Q12: Coty | R12: 0106/D9 | S12: 1
B13: 0002DES06080 | D13: res | E13: 1 | F13: DESMOLDANTE 60 X 80 | G13: Resma 5 KG. | H13: =_xlfn.XLOOKUP(B13,lista!A:A,lista!C:C,0,0) -> 64589 | P13: FV | Q13: Coty | R13: 0189/D9 | T13: 1
B14: 0002DES07090 | D14: res | E14: 1 | F14: DESMOLDANTE 70 X 90 | G14: Resma 5 KG. | H14: =_xlfn.XLOOKUP(B14,lista!A:A,lista!C:C,0,0) -> 64589 | P14: FV | Q14: Coty | R14: 0181.02/D9 | U14: 2
B15: PAPEL PARAFINADO | R15: Total | S15: =SUM(S7:S14) -> 4 | T15: =SUM(T7:T14) -> 2 | U15: =SUM(U7:U14) -> 4
B16: 0082ALL00009 | D16: res | E16: 1 | F16: PAPEL PARAFINADO LISO 40 x 40 cm | G16: Resma 1 KG. | H16: =_xlfn.XLOOKUP(B16,lista!A:A,lista!C:C,0,0) -> 12994
B17: 0082ALL00020 | D17: res | E17: 1 | F17: PAPEL PARAFINADO LISO 35 x 40 cm | G17: Resma 5 KG. | H17: =_xlfn.XLOOKUP(B17,lista!A:A,lista!C:C,0,0) -> 64439
B18: 0082ALL00021 | D18: res | E18: 1 | F18: PAPEL PARAFINADO GENERICO 35 x 40 cm | G18: Resma 5 KG. | H18: =_xlfn.XLOOKUP(B18,lista!A:A,lista!C:C,0,0) -> 64566
B19: 0082ALL00022 | D19: res | E19: 1 | F19: PAPEL PARAFINADO PERSONALIZADO | G19: Resma 5 KG. | H19: =_xlfn.XLOOKUP(B19,lista!A:A,lista!C:C,0,0) -> 64276
B20: PAPEL ALUMINIZADO
B21: 0082ALL00002 | D21: res | E21: 1 | F21: PAPEL ALUMINIO IMPRESO GENERICO 25 x 35 cm | G21: Resma 5 KG. | H21: =_xlfn.XLOOKUP(B21,lista!A:A,lista!C:C,0,0) -> 125496
B22: 0082ALL00003 | D22: res | E22: 1 | F22: PAPEL ALUMINIO PERSONALIZADO | G22: Resma 5 KG. | H22: =_xlfn.XLOOKUP(B22,lista!A:A,lista!C:C,0,0) -> 125185
B23: 0082ALL00004 | D23: res | E23: 1 | F23: PAPEL ALUMINIO LISO 25 x 35 cm | G23: Resma 5 KG. | H23: =_xlfn.XLOOKUP(B23,lista!A:A,lista!C:C,0,0) -> 126192
B24: 0082ALL00005 | D24: res | E24: 1 | F24: PAPEL ALUMINIO LISO 34 x 50 cm | G24: Resma 5 KG. | H24: =_xlfn.XLOOKUP(B24,lista!A:A,lista!C:C,0,0) -> 126192
B25: 0082ALL00006 | D25: res | E25: 1 | F25: PAPEL ALUMINIO IMPRESO GENERICO 34 x 50 cm | G25: Resma 5 KG. | H25: =_xlfn.XLOOKUP(B25,lista!A:A,lista!C:C,0,0) -> 125844
B26: CARTON - CARTULINA ANTIGRASA
B27: 0018DARBB0026 | C27: RPN02026101XC | D27: caja | E27: 200 | F27: CAJA PARA ALIMENTOS DARNEL NATURAL 26 Oz BLANCA PAQX50 Un. | G27: Nuevo | H27: =_xlfn.XLOOKUP(B27,lista!A:A,lista!C:C,0,0) -> 47151
B28: 0018DARBK0026 | C28: =_xlfn.XLOOKUP('Papeles-Cartulina'!B28,amb!B:B,amb!D:D,0,0) -> RPN02026102XC | D28: =_xlfn.XLOOKUP('Papeles-Cartulina'!B28,amb!B:B,amb!L:L,0,0) -> PAQ | E28: =_xlfn.XLOOKUP(B28,amb!B:B,amb!AA:AA,0,0) -> 200 | F28: =_xlfn.XLOOKUP(B28,amb!B:B,amb!A:A,0,0) -> CAJA PARA ALIMENTOS DARNEL NATURAL 26 Oz MOCA PAQX50 CAJ X200UNID | G28: Nuevo | H28: =_xlfn.XLOOKUP(B28,lista!A:A,lista!C:C,0,0) -> 43116
B29: 0018DARBB0045 | C29: =_xlfn.XLOOKUP('Papeles-Cartulina'!B29,amb!B:B,amb!D:D,0,0) -> RPN02045101XC | D29: =_xlfn.XLOOKUP('Papeles-Cartulina'!B29,amb!B:B,amb!L:L,0,0) -> PAQ | E29: =_xlfn.XLOOKUP(B29,amb!B:B,amb!AA:AA,0,0) -> 200 | F29: =_xlfn.XLOOKUP(B29,amb!B:B,amb!A:A,0,0) -> CAJA PARA ALIMENTOS DARNEL NATURAL 45 Oz BLANCO PQX50 CJX200 | G29: Nuevo | H29: =_xlfn.XLOOKUP(B29,lista!A:A,lista!C:C,0,0) -> 68591
B30: 0018DARBKS045 | C30: =_xlfn.XLOOKUP('Papeles-Cartulina'!B30,amb!B:B,amb!D:D,0,0) -> RPN02045102XTE | D30: =_xlfn.XLOOKUP('Papeles-Cartulina'!B30,amb!B:B,amb!L:L,0,0) -> PAQ | E30: =_xlfn.XLOOKUP(B30,amb!B:B,amb!AA:AA,0,0) -> 200 | F30: =_xlfn.XLOOKUP(B30,amb!B:B,amb!A:A,0,0) -> CAJA ALIMENTOS SAFETYPLUS DARNEL NATURALS 45 Oz MOCA PQX50 CAJX200 | G30: Nuevo | H30: =_xlfn.XLOOKUP(B30,lista!A:A,lista!C:C,0,0) -> 67623
B31: 0018DARBB0049 | C31: =_xlfn.XLOOKUP('Papeles-Cartulina'!B31,amb!B:B,amb!D:D,0,0) -> RPN02049101XC | D31: =_xlfn.XLOOKUP('Papeles-Cartulina'!B31,amb!B:B,amb!L:L,0,0) -> PAQ | E31: =_xlfn.XLOOKUP(B31,amb!B:B,amb!AA:AA,0,0) -> 200 | F31: =_xlfn.XLOOKUP(B31,amb!B:B,amb!A:A,0,0) -> CAJA PARA ALIMENTOS DARNEL NATURALS 49 Oz BLANCO PQX50 CAJX200 | G31: Nuevo | H31: =_xlfn.XLOOKUP(B31,lista!A:A,lista!C:C,0,0) -> 73442
B32: 0018DARBK0049 | C32: =_xlfn.XLOOKUP('Papeles-Cartulina'!B32,amb!B:B,amb!D:D,0,0) -> RPN02049102XC | D32: =_xlfn.XLOOKUP('Papeles-Cartulina'!B32,amb!B:B,amb!L:L,0,0) -> PAQ | E32: =_xlfn.XLOOKUP(B32,amb!B:B,amb!AA:AA,0,0) -> 200 | F32: =_xlfn.XLOOKUP(B32,amb!B:B,amb!A:A,0,0) -> CAJA PARA ALIMENTOS DARNEL NATURAL 49 Oz MOCA PQX50 CJX200 | G32: Nuevo | H32: =_xlfn.XLOOKUP(B32,lista!A:A,lista!C:C,0,0) -> 67949
B33: 0018DARBB0066 | C33: =_xlfn.XLOOKUP('Papeles-Cartulina'!B33,amb!B:B,amb!D:D,0,0) -> RPN02066101XC | D33: =_xlfn.XLOOKUP('Papeles-Cartulina'!B33,amb!B:B,amb!L:L,0,0) -> PAQ | E33: =_xlfn.XLOOKUP(B33,amb!B:B,amb!AA:AA,0,0) -> 200 | F33: =_xlfn.XLOOKUP(B33,amb!B:B,amb!A:A,0,0) -> CAJA PARA ALIMENTOS DARNEL NATURAL 66 Oz BLANCO PQX50 CJX200 | G33: Nuevo | H33: =_xlfn.XLOOKUP(B33,lista!A:A,lista!C:C,0,0) -> 80488
B34: 0018DARBK0066 | C34: =_xlfn.XLOOKUP('Papeles-Cartulina'!B34,amb!B:B,amb!D:D,0,0) -> RPN02066102XC | D34: =_xlfn.XLOOKUP('Papeles-Cartulina'!B34,amb!B:B,amb!L:L,0,0) -> PAQ | E34: =_xlfn.XLOOKUP(B34,amb!B:B,amb!AA:AA,0,0) -> 200 | F34: =_xlfn.XLOOKUP(B34,amb!B:B,amb!A:A,0,0) -> CAJA PARA ALIMENTOS DARNEL NATURAL 66 Oz MOCA PQX50 CJX200 | G34: Nuevo | H34: =_xlfn.XLOOKUP(B34,lista!A:A,lista!C:C,0,0) -> 74222
B35: 0018DARBB0072 | C35: =_xlfn.XLOOKUP('Papeles-Cartulina'!B35,amb!B:B,amb!D:D,0,0) -> RPN0207201X | D35: =_xlfn.XLOOKUP('Papeles-Cartulina'!B35,amb!B:B,amb!L:L,0,0) -> PAQ | E35: =_xlfn.XLOOKUP(B35,amb!B:B,amb!AA:AA,0,0) -> 100 | F35: =_xlfn.XLOOKUP(B35,amb!B:B,amb!A:A,0,0) -> CAJA PARA ALIMENTOS DARNEL NATURALS 72 Oz BLANCO BLX100 | G35: Nuevo | H35: =_xlfn.XLOOKUP(B35,lista!A:A,lista!C:C,0,0) -> 50051
B36: 0018DARBBK072 | C36: =_xlfn.XLOOKUP('Papeles-Cartulina'!B36,amb!B:B,amb!D:D,0,0) -> RPN0207202X | D36: =_xlfn.XLOOKUP('Papeles-Cartulina'!B36,amb!B:B,amb!L:L,0,0) -> PAQ | E36: =_xlfn.XLOOKUP(B36,amb!B:B,amb!AA:AA,0,0) -> 100 | F36: =_xlfn.XLOOKUP(B36,amb!B:B,amb!A:A,0,0) -> CAJA PARA ALIMENTOS DARNEL NATURALS 72 Oz MOCA BLX100 | G36: Nuevo | H36: =_xlfn.XLOOKUP(B36,lista!A:A,lista!C:C,0,0) -> 50375
B37: 0018DARBB0115 | C37: =_xlfn.XLOOKUP('Papeles-Cartulina'!B37,amb!B:B,amb!D:D,0,0) -> RPN02011501X | D37: =_xlfn.XLOOKUP('Papeles-Cartulina'!B37,amb!B:B,amb!L:L,0,0) -> PAQ | E37: =_xlfn.XLOOKUP(B37,amb!B:B,amb!AA:AA,0,0) -> 100 | F37: =_xlfn.XLOOKUP(B37,amb!B:B,amb!A:A,0,0) -> CAJA PARA ALIMENTOS DARNEL NATURALS 115 Oz BLANCO BLX100 UNID | G37: Nuevo | H37: 43095
B38: 0018DARBBK115 | C38: RPN02011502X | D38: caja | E38: 100 | F38: CAJA PARA ALIMENTOS DARNEL NATURAL 115oz MOCA | G38: Nuevo | H38: 43428
B39: CAJAS y ESTUCHES PARA PAPAS FRITAS
B40: 0018DARBBF0001 | C40: =_xlfn.XLOOKUP('Papeles-Cartulina'!B40,amb!B:B,amb!D:D,0,0) -> RPN02P08201X | D40: =_xlfn.XLOOKUP('Papeles-Cartulina'!B40,amb!B:B,amb!L:L,0,0) -> PAQ | E40: =_xlfn.XLOOKUP(B40,amb!B:B,amb!AA:AA,0,0) -> 600 | F40: =_xlfn.XLOOKUP(B40,amb!B:B,amb!A:A,0,0) -> CAJA PEQUEÑA PARA PAPAS FRITAS DARNEL NATURAL BLANCA PQX100 CJX600 | G40: Nuevo | H40: =_xlfn.XLOOKUP(B40,lista!A:A,lista!C:C,0,0) -> 33056
B41: 0018DARBBF0005 | C41: =_xlfn.XLOOKUP('Papeles-Cartulina'!B41,amb!B:B,amb!D:D,0,0) -> RPN02P08701X | D41: =_xlfn.XLOOKUP('Papeles-Cartulina'!B41,amb!B:B,amb!L:L,0,0) -> PAQ | E41: =_xlfn.XLOOKUP(B41,amb!B:B,amb!AA:AA,0,0) -> 600 | F41: =_xlfn.XLOOKUP(B41,amb!B:B,amb!A:A,0,0) -> CAJA MEDIANA PARA PAPAS FRITAS DARNEL NATURAL BLANCO PQX100 CJX600 | G41: Nuevo | H41: =_xlfn.XLOOKUP(B41,lista!A:A,lista!C:C,0,0) -> 60322
B42: 0018DARBBF0010 | C42: =_xlfn.XLOOKUP('Papeles-Cartulina'!B42,amb!B:B,amb!D:D,0,0) -> RPN02P12801X | D42: =_xlfn.XLOOKUP('Papeles-Cartulina'!B42,amb!B:B,amb!L:L,0,0) -> PAQ | E42: =_xlfn.XLOOKUP(B42,amb!B:B,amb!AA:AA,0,0) -> 600 | F42: =_xlfn.XLOOKUP(B42,amb!B:B,amb!A:A,0,0) -> CAJA GRANDE PARA PAPAS FRITAS DARNEL NATURAL BLANCO PQX100 CJX600 | G42: Nuevo | H42: =_xlfn.XLOOKUP(B42,lista!A:A,lista!C:C,0,0) -> 81948
B43: 0018DARBKF0001 | C43: =_xlfn.XLOOKUP('Papeles-Cartulina'!B43,amb!B:B,amb!D:D,0,0) -> RPN02P08202X | D43: =_xlfn.XLOOKUP('Papeles-Cartulina'!B43,amb!B:B,amb!L:L,0,0) -> PAQ | E43: =_xlfn.XLOOKUP(B43,amb!B:B,amb!AA:AA,0,0) -> 600 | F43: =_xlfn.XLOOKUP(B43,amb!B:B,amb!A:A,0,0) -> CAJA PEQUEÑA PARA PAPAS FRITAS DARNEL NATURAL MOCA PQX100 CJX600 | G43: Nuevo | H43: =_xlfn.XLOOKUP(B43,lista!A:A,lista!C:C,0,0) -> 29445
B44: 0018ESP00004 | C44: =_xlfn.XLOOKUP('Papeles-Cartulina'!B44,amb!B:B,amb!D:D,0,0) -> 0018ESP00004 | D44: =_xlfn.XLOOKUP('Papeles-Cartulina'!B44,amb!B:B,amb!L:L,0,0) -> PAQ | E44: =_xlfn.XLOOKUP(B44,amb!B:B,amb!AA:AA,0,0) -> 1000 | F44: =_xlfn.XLOOKUP(B44,amb!B:B,amb!A:A,0,0) -> ESTUCHES PAPAS FRITAS KRAFT X 1000 | G44: 210 Grs (Aprox) | H44: =_xlfn.XLOOKUP(B44,lista!A:A,lista!C:C,0,0) -> 97504
B45: CAJAS PARA ALIMENTOS SAFETYPLUS
B46: 0018DARBKS026 | C46: RPN02026102XTE | D46: caja | E46: 200 | F46: CAJA P/ALIMENTOS SAFETYPLUS DARNEL NAT. 26oz MOCA PQX50 Un. | G46: Nuevo | H46: =_xlfn.XLOOKUP(B46,lista!A:A,lista!C:C,0,0) -> 45268
B47: 0018DARBK0045 | C47: RPN02045102XC | D47: caja | E47: 200 | F47: CAJA PARA ALIMENTOS DARNEL NATURAL 45 Oz MOCA PQX50 Un. | G47: Nuevo | H47: =_xlfn.XLOOKUP(B47,lista!A:A,lista!C:C,0,0) -> 62476
B48: 0018DARBKS0049 | C48: RPN02049102XTE | D48: caja | E48: 200 | F48: CAJA P/ALIMENTOS SAFETYPLUS DARNEL NAT. 49oz MOCA PQX50 Un. | G48: Nuevo | H48: =_xlfn.XLOOKUP(B48,lista!A:A,lista!C:C,0,0) -> 72723
B49: 0018DARBKS0066 | C49: RPN02066102XTE | D49: caja | E49: 200 | F49: CAJA P/ALIMENTOS SAFETYPLUS DARNEL NAT 66oz MOCA PQX50 Un. | G49: Nuevo | H49: =_xlfn.XLOOKUP(B49,lista!A:A,lista!C:C,0,0) -> 79883
B50: CAJAS PARA HAMBURGUESAS
B51: 0018DARKH0001 | C51: RPN0209302X | D51: caja | E51: 300 | F51: CAJA PEQUEÑA P/HAMBURGUESA DARNEL NATURAL MOCA PAQX50 Un. | G51: Nuevo | H51: =_xlfn.XLOOKUP(B51,lista!A:A,lista!C:C,0,0) -> 44059
B52: 0018DARKH0005 | C52: RPN0209502X | D52: caja | E52: 300 | F52: CAJA MEDIANA P/HAMBURGUESA DARNEL NATURAL MOCA PAQX50 Un. | G52: Nuevo | H52: =_xlfn.XLOOKUP(B52,lista!A:A,lista!C:C,0,0) -> 45245
B53: 0018DARKH0010 | C53: RPN02011402X | D53: caja | E53: 400 | F53: CAJA GRANDE P/HAMBURGUESA DARNEL NATURAL MOCA PAQX50 Un. | G53: Nuevo | H53: =_xlfn.XLOOKUP(B53,lista!A:A,lista!C:C,0,0) -> 55794
B54: PORTA VASO CARTULINA
B55: 0018ESV00003 | D55: caja | E55: 400 | F55: PORTA VASOS DE CARTULINA | H55: =_xlfn.XLOOKUP(B55,lista!A:A,lista!C:C,0,0) -> 54611
B56: PAPEL SEDA
B57: 0002SED75100 | D57: res | E57: 1 | F57: PAPEL SEDA 75 x 100 cm. | G57: Resma 5 KG. | H57: =_xlfn.XLOOKUP(B57,lista!A:A,lista!C:C,0,0) -> 26092
B58: BANDEJAS KRAFT MICROCORRUGADAS
B59: 0012COM00052 | D59: caja | E59: 600 | F59: BAND. Kraft puro CARTULINA Nro 2 (10 x 6,5 x 3 cm) | G59: 3 paq x 200 Un. | H59: =_xlfn.XLOOKUP(B59,lista!A:A,lista!C:C,0,0) -> 37544
B60: 0012COM10012 | D60: caja | E60: 400 | F60: BAND Kraft microcorr IMPRESA nro 2 (17x13,8x1,5 cm) | G60: 4 paq x 100 Un. | H60: 33673
B61: 0012COM10013 | D61: caja | E61: 400 | F61: BAND Kraft microcorr IMPRESA nro 3 (20,5x18x2 cm) | G61: 4 paq x 100 Un. | H61: 39055
B62: 0012COM10014 | D62: caja | E62: 400 | F62: BAND Kraft microcorr. IMPRESA nro 4 (23,3x18x2 cm) | G62: 4 paq x 100 Un. | H62: 49140
B63: 0012COM10015 | D63: caja | E63: 200 | F63: BAND Kraft microcorr IMPRESA nro 5 (27x20,5x2,3 cm) | G63: 2 paq x 100 Un. | H63: 30348
B64: 0012COM10016 | D64: caja | E64: 200 | F64: BAND Kraft microcorr IMPRESA nro 6 (19x14x4 cm) | G64: 2 paq x 100 Un. | H64: =_xlfn.XLOOKUP(B64,lista!A:A,lista!C:C,0,0) -> 28301
B65: 0012COM10017 | D65: caja | E65: 200 | F65: BAND Kraft microcorr IMPRESA nro 7 (23x17x3,5 cm) | G65: 2 paq x 100 Un. | H65: =_xlfn.XLOOKUP(B65,lista!A:A,lista!C:C,0,0) -> 34372
B66: BOLSAS DE PAPEL Y SERVILLETAS ENSOBRADAS
B67: 0004KRA00090 | D67: paq | E67: 250 | F67: BOLSA CHICA PAPEL KRAFT Impresa "Delivery" | G67: 370x200x120mm | H67: =_xlfn.XLOOKUP(B67,lista!A:A,lista!C:C,0,0) -> 21515
B68: 0004KRA00091 | D68: paq | E68: 250 | F68: BOLSA GRANDE PAPEL KRAFT Impresa "Delivery" | G68: 470x200x120mm | H68: =_xlfn.XLOOKUP(B68,lista!A:A,lista!C:C,0,0) -> 26260
B69: 0005SERZ0001 | D69: paq | E69: 500 | F69: SERVILLETAS PAPEL KRAFT Ensobradas (2 Un x sobre) | G69: 400x145 mm | H69: =_xlfn.XLOOKUP(B69,lista!A:A,lista!C:C,0,0) -> 21216
B70: LOS PRECIOS SON MAS IVA | H70: ,. .

Sheet LISTA 22.09.2025
A1: VEN2140-Cons. Precios de venta
A3: Articulo | B3: Nombre | C3: U.M. | D3: Lista | E3: Precio Actual | F3: Vigencia hasta | G3: Conimpuesto | H3: Fecha act. | I3: Moneda | J3: Precio Actual | K3: MonedaAnterior | L3: PrecioAnterior | M3: Variación Absoluta | N3: Variación Porcentual | O3: LINEA | P3: MATERIAL DE PRODUCTOS | Q3: TIPO DE MANUFACTURA | R3: FAMILIA DE PRODUCTOS | S3: CANTIDAD X UM | T3: POSICION ARANCELARIA
A4: 0001BCO00002 | B4: BLANCO SEIN 40 X 50 | C4: RES | D4: 1, LISTA GENERAL | E4: 27785 | F4: 219512 | G4: 0 | H4: 45897 | I4: PS | J4: 27785 | K4: PS | L4: 25727 | M4: 2058 | N4: 8 | O4: 007, Papeles | P4: 001, Papel | Q4: 001, Manufactured Group Locall | R4: 001, Bolsas de Papel | S4: 1, 1 | T4: P01, 480256
A5: 0001BCO00003 | B5: BLANCO SEIN 64 X 90 | C5: RES | D5: 1, LISTA GENERAL | E5: 27785 | F5: 219512 | G5: 0 | H5: 45897 | I5: PS | J5: 27785 | K5: PS | L5: 25727 | M5: 2058 | N5: 8 | O5: 007, Papeles | P5: 001, Papel | Q5: 001, Manufactured Group Locall | R5: 001, Bolsas de Papel | S5: 1, 1 | T5: P01, 480256
A6: 0001BCO00004 | B6: BLANCO SEIN 64 X 45 | C6: RES | D6: 1, LISTA GENERAL | E6: 27785 | F6: 219512 | G6: 0 | H6: 45897 | I6: PS | J6: 27785 | K6: PS | L6: 25727 | M6: 2058 | N6: 8 | O6: 007, Papeles | P6: 001, Papel | Q6: 001, Manufactured Group Locall | R6: 001, Bolsas de Papel | S6: 1, 1 | T6: P01, 480256
A7: 0001BCO00005 | B7: BLANCO SEIN 32 X 45 | C7: RES | D7: 1, LISTA GENERAL | E7: 27785 | F7: 219512 | G7: 0 | H7: 45897 | I7: PS | J7: 27785 | K7: PS | L7: 25727 | M7: 2058 | N7: 8 | O7: 007, Papeles | P7: 001, Papel | Q7: 001, Manufactured Group Locall | R7: 001, Bolsas de Papel | S7: 1, 1 | T7: P01, 480256
A8: 0001BCO00006 | B8: BLANCO SEIN 52 X 72 | C8: RES | D8: 1, LISTA GENERAL | E8: 27785 | F8: 219512 | G8: 0 | H8: 45897 | I8: PS | J8: 27785 | K8: PS | L8: 25727 | M8: 2058 | N8: 8 | O8: 007, Papeles | P8: 001, Papel | Q8: 001, Manufactured Group Locall | R8: 001, Bolsas de Papel | S8: 1, 1 | T8: P01, 480256
A9: 0001BCO00007 | B9: BLANCO SEIN 52 X 36 | C9: RES | D9: 1, LISTA GENERAL | E9: 27785 | F9: 219512 | G9: 0 | H9: 45897 | I9: PS | J9: 27785 | K9: PS | L9: 25727 | M9: 2058 | N9: 8 | O9: 007, Papeles | P9: 001, Papel | Q9: 001, Manufactured Group Locall | R9: 001, Bolsas de Papel | S9: 1, 1 | T9: P01, 480256
A10: 0001BCO00008 | B10: BLANCO SEIN 26 X 36 | C10: RES | D10: 1, LISTA GENERAL | E10: 27785 | F10: 219512 | G10: 0 | H10: 45897 | I10: PS | J10: 27785 | K10: PS | L10: 25727 | M10: 2058 | N10: 8 | O10: 007, Papeles | P10: 001, Papel | Q10: 001, Manufactured Group Locall | R10: 001, Bolsas de Papel | S10: 1, 1 | T10: P01, 480256
A11: 0001BCO00009 | B11: BLANCO SEIN 26 X 18 | C11: RES | D11: 1, LISTA GENERAL | E11: 27785 | F11: 219512 | G11: 0 | H11: 45897 | I11: PS | J11: 27785 | K11: PS | L11: 25727 | M11: 2058 | N11: 8 | O11: 007, Papeles | P11: 001, Papel | Q11: 001, Manufactured Group Locall | R11: 001, Bolsas de Papel | S11: 1, 1 | T11: P01, 480256
A12: 0001BCO00010 | B12: BLANCO SEIN 58 X 81 | C12: RES | D12: 1, LISTA GENERAL | E12: 27785 | F12: 219512 | G12: 0 | H12: 45897 | I12: PS | J12: 27785 | K12: PS | L12: 25727 | M12: 2058 | N12: 8 | O12: 007, Papeles | P12: 001, Papel | Q12: 001, Manufactured Group Locall | R12: 001, Bolsas de Papel | S12: 1, 1 | T12: P01, 480256
A13: 0001BCO00011 | B13: BLANCO SEIN 58 X 40 | C13: RES | D13: 1, LISTA GENERAL | E13: 27785 | F13: 219512 | G13: 0 | H13: 45897 | I13: PS | J13: 27785 | K13: PS | L13: 25727 | M13: 2058 | N13: 8 | O13: 007, Papeles | P13: 001, Papel | Q13: 001, Manufactured Group Locall | R13: 001, Bolsas de Papel | S13: 1, 1 | T13: P01, 480256
A14: 0001BCO00014 | B14: BLANCO SEIN 9 X 13 PIZZERO | C14: RES | D14: 1, LISTA GENERAL | E14: 27785 | F14: 219512 | G14: 0 | H14: 45897 | I14: PS | J14: 27785 | K14: PS | L14: 25727 | M14: 2058 | N14: 8 | O14: 007, Papeles | P14: 001, Papel | Q14: 001, Manufactured Group Locall | R14: 001, Bolsas de Papel | S14: 1, 1 | T14: P01, 480256
A15: 0001BCO00015 | B15: BLANCO SEIN 30 X 40 | C15: RES | D15: 1, LISTA GENERAL | E15: 27785 | F15: 219512 | G15: 0 | H15: 45897 | I15: PS | J15: 27785 | K15: PS | L15: 25727 | M15: 2058 | N15: 8 | O15: 007, Papeles | P15: 001, Papel | Q15: 001, Manufactured Group Locall | R15: 001, Bolsas de Papel | S15: 1, 1 | T15: P01, 480256
... A71: 0005SER03333 | B71: SERVILLETA 33 X 33 | C71: CAJ | D71: 1, LISTA GENERAL | E71: 8972 | F71: 219512 | G71: 0 | H71: 45817 | I71: PS | J71: 8972 | K71: PS | L71: 9444 | M71: -472 | N71: -5 | O71: 007, Papeles | P71: 001, Papel | Q71: 003, Purchased from 3rd Party | R71: 002, Servilletas/Papel Cocina | S71: 1000, 1000 | T71: P07, 481830
A72: 0005SER10000 | B72: SERVILLETA (X 10.000) | C72: CAJ | D72: 1, LISTA GENERAL | E72: 3248 | F72: 219512 | G72: 0 | H72: 45352 | I72: PS | J72: 3248 | L72: 0 | M72: 3248 | N72: 0 | O72: 007, Papeles | P72: 001, Papel | Q72: 003, Purchased from 3rd Party | R72: 002, Servilletas/Papel Cocina | S72: 10000, 10000 | T72: P07, 481830
A73: 0005SERZ0001 | B73: SERVILLETAS DELIVERY ENSOBRADO x 2 (X 500) | C73: CAJ | D73: 1, LISTA GENERAL | E73: 21427 | F73: 219512 | G73: 0 | H73: 45919 | I73: PS | J73: 21427 | K73: PS | L73: 19131 | M73: 2296 | N73: 12 | O73: 007, Papeles | P73: 001, Papel | Q73: 003, Purchased from 3rd Party | R73: 002, Servilletas/Papel Cocina | S73: 500, 500 | T73: P07, 481830
A74: 0006BOR03441 | B74: CARPETA BORDADA 34X41 | C74: PAQ | D74: 1, LISTA GENERAL | E74: 7390 | F74: 219512 | G74: 0 | H74: 45762 | I74: PS | J74: 7390 | K74: PS | L74: 6718 | M74: 672 | N74: 10 | O74: 007, Papeles | P74: 001, Papel | Q74: 003, Purchased from 3rd Party | R74: 003, Moldes de Papel | S74: 100, 100 | T74: P08, 482390
A75: 0008MBI00016 | B75: MOLDE BIZCOCHUELO Nº 16 | C75: PAQ | D75: 1, LISTA GENERAL | E75: 33429 | F75: 219512 | G75: 0 | H75: 45817 | I75: PS | J75: 33429 | K75: PS | L75: 35188 | M75: -1759 | N75: -5 | O75: 007, Papeles | P75: 001, Papel | Q75: 003, Purchased from 3rd Party | R75: 003, Moldes de Papel | S75: 200, 200 | T75: P09, 482360
A76: 0008MBI00020 | B76: MOLDE BIZCOCHUELO Nº 20 | C76: PAQ | D76: 1, LISTA GENERAL | E76: 36634 | F76: 219512 | G76: 0 | H76: 45817 | I76: PS | J76: 36634 | K76: PS | L76: 37767 | M76: -1133 | N76: -3 | O76: 007, Papeles | P76: 001, Papel | Q76: 003, Purchased from 3rd Party | R76: 003, Moldes de Papel | S76: 200, 200 | T76: P09, 482360
A77: 0008MBI00022 | B77: MOLDE BIZCOCHUELO Nº 22 | C77: PAQ | D77: 1, LISTA GENERAL | E77: 41648 | F77: 219512 | G77: 0 | H77: 45762 | I77: PS | J77: 41648 | K77: PS | L77: 37862 | M77: 3786 | N77: 10 | O77: 007, Papeles | P77: 001, Papel | Q77: 003, Purchased from 3rd Party | R77: 003, Moldes de Papel | S77: 200, 200 | T77: P09, 482360
A78: 0008MRO00020 | B78: MOLDE ROSCA Nº 20 | C78: PAQ | D78: 1, LISTA GENERAL | E78: 21441 | F78: 219512 | G78: 0 | H78: 45817 | I78: PS | J78: 21441 | K78: PS | L78: 22569 | M78: -1128 | N78: -5 | O78: 007, Papeles | P78: 001, Papel | Q78: 003, Purchased from 3rd Party | R78: 003, Moldes de Papel | S78: 100, 100 | T78: P09, 482360
A79: 0008MRO00022 | B79: MOLDE ROSCA Nº 22 | C79: PAQ | D79: 1, LISTA GENERAL | E79: 26992 | F79: 219512 | G79: 0 | H79: 45762 | I79: PS | J79: 26992 | K79: PS | L79: 24538 | M79: 2454 | N79: 10 | O79: 007, Papeles | P79: 001, Papel | Q79: 003, Purchased from 3rd Party | R79: 003, Moldes de Papel | S79: 100, 100 | T79: P09, 482360
A80: 0008PIR00005 | B80: PIROTINES Nº 5 | C80: CAJ | D80: 1, LISTA GENERAL | E80: 6162 | F80: 219512 | G80: 0 | H80: 45762 | I80: PS | J80: 6162 | K80: PS | L80: 5602 | M80: 560 | N80: 10 | O80: 007, Papeles | P80: 001, Papel | Q80: 003, Purchased from 3rd Party | R80: 003, Moldes de Papel | S80: 1000, 1000 | T80: P09, 482360
A81: 0008PIR00010 | B81: PIROTINES Nº 10 | C81: CAJ | D81: 1, LISTA GENERAL | E81: 18143 | F81: 219512 | G81: 0 | H81: 45762 | I81: PS | J81: 18143 | K81: PS | L81: 16494 | M81: 1649 | N81: 10 | O81: 007, Papeles | P81: 001, Papel | Q81: 003, Purchased from 3rd Party | R81: 003, Moldes de Papel | S81: 1000, 1000 | T81: P09, 482360
A82: 0011PRI00003 | B82: CARTON BLANCO CIFIVE | C82: KG | D82: 1, LISTA GENERAL | E82: 2504 | F82: 219512 | G82: 0 | H82: 45817 | I82: PS | J82: 2504 | K82: PS | L82: 2782 | M82: -278 | N82: -9.99 | O82: 008, Cartón | P82: 001, Papel | Q82: 003, Purchased from 3rd Party | R82: 004, Carton en Hojas | S82: 1, 1 | T82: P10, 480442
A83: 0011SEG00030 | B83: CARTON GRIS Nº 30 | C83: KG | D83: 1, LISTA GENERAL | E83: 1387 | F83: 219512 | G83: 0 | H83: 45817 | I83: PS | J83: 1387 | K83: PS | L83: 1541 | M83: -154 | N83: -9.99 | O83: 008, Cartón | P83: 001, Papel | Q83: 003, Purchased from 3rd Party | R83: 004, Carton en Hojas | S83: 1, 1 | T83: P10, 480442
A84: 0011SEG00040 | B84: CARTON GRIS Nº 40 | C84: KG | D84: 1, LISTA GENERAL | E84: 1387 | F84: 219512 | G84: 0 | H84: 45817 | I84: PS | J84: 1387 | K84: PS | L84: 1541 | M84: -154 | N84: -9.99 | O84: 008, Cartón | P84: 001, Papel | Q84: 003, Purchased from 3rd Party | R84: 004, Carton en Hojas | S84: 1, 1 | T84: P10, 480442
... A90: 0012COM00006 | B90: BANDEJA DE CARTON Nº 6 21X29 | C90: PAQ | D90: 1, LISTA GENERAL | E90: 11530 | F90: 219512 | G90: 0 | H90: 45762 | I90: PS | J90: 11530 | K90: PS | L90: 10482 | M90: 1048 | N90: 10 | O90: 008, Cartón | P90: 001, Papel | Q90: 003, Purchased from 3rd Party | R90: 005, Bandejas de Papel / Carto | S90: 100, 100 | T90: P11, 482370
A91: 0012COM00051 | B91: BANDEJA KRAFT PURO N°1 (6PX100U) | C91: CAJ | D91: 1, LISTA GENERAL | E91: 15716 | F91: 219512 | G91: 0 | H91: 45897 | I91: PS | J91: 15716 | L91: 0 | M91: 15716 | N91: 0 | O91: 008, Cartón | P91: 001, Papel | Q91: 001, Manufactured Group Locall | R91: 005, Bandejas de Papel / Carto | S91: 600, 600 | T91: P11, 482370
A92: 0012COM00052 | B92: BANDEJA KRAFT PURO N°2 (6PX100U) | C92: CAJ | D92: 1, LISTA GENERAL | E92: 43825 | F92: 219512 | G92: 0 | H92: 45766 | I92: PS | J92: 43825 | K92: PS | L92: 48208 | M92: -4383 | N92: -9.09 | O92: 008, Cartón | P92: 001, Papel | Q92: 001, Manufactured Group Locall | R92: 005, Bandejas de Papel / Carto | S92: 600, 600 | T92: P11, 482370
A93: 0012COM00053 | B93: BANDEJA KRAFT PURO N°3 (4PX100U) | C93: CAJ | D93: 1, LISTA GENERAL | E93: 37089 | F93: 219512 | G93: 0 | H93: 45766 | I93: PS | J93: 37089 | K93: PS | L93: 40798 | M93: -3709 | N93: -9.09 | O93: 008, Cartón | P93: 001, Papel | Q93: 001, Manufactured Group Locall | R93: 005, Bandejas de Papel / Carto | S93: 400, 400 | T93: P11, 482370
A94: 0012COM00054 | B94: BANDEJA KRAFT PURO N°4 (2PX100U) | C94: CAJ | D94: 1, LISTA GENERAL | E94: 23042 | F94: 219512 | G94: 0 | H94: 45766 | I94: PS | J94: 23042 | K94: PS | L94: 25346 | M94: -2304 | N94: -9.09 | O94: 008, Cartón | P94: 001, Papel | Q94: 001, Manufactured Group Locall | R94: 005, Bandejas de Papel / Carto | S94: 200, 200 | T94: P11, 482370
A95: 0012COM10002 | B95: BANDEJA MICRO CORRUGADO N° 2 (4PX100U) | C95: CAJ | D95: 1, LISTA GENERAL | E95: 25792 | F95: 219512 | G95: 0 | H95: 45766 | I95: PS | J95: 25792 | K95: PS | L95: 28371 | M95: -2579 | N95: -9.09 | O95: 008, Cartón | P95: 001, Papel | Q95: 001, Manufactured Group Locall | R95: 005, Bandejas de Papel / Carto | S95: 400, 400 | T95: P11, 482370
A96: 0012COM10003 | B96: BANDEJA MICRO CORRUGADO N° 3 (4PX100U) | C96: CAJ | D96: 1, LISTA GENERAL | E96: 29631 | F96: 219512 | G96: 0 | H96: 45766 | I96: PS | J96: 29631 | K96: PS | L96: 32594 | M96: -2963 | N96: -9.09 | O96: 008, Cartón | P96: 001, Papel | Q96: 001, Manufactured Group Locall | R96: 005, Bandejas de Papel / Carto | S96: 400, 400 | T96: P11, 482370
A97: 0012COM10004 | B97: BANDEJA MICRO CORRUGADO N° 4 (4PX100U) | C97: CAJ | D97: 1, LISTA GENERAL | E97: 37337 | F97: 219512 | G97: 0 | H97: 45766 | I97: PS | J97: 37337 | K97: PS | L97: 41071 | M97: -3734 | N97: -9.09 | O97: 008, Cartón | P97: 001, Papel | Q97: 001, Manufactured Group Locall | R97: 005, Bandejas de Papel / Carto | S97: 400, 400 | T97: P11, 482370
A98: 0012COM10005 | B98: BANDEJA MICRO CORRUGADO N° 5 (2PX100U) | C98: CAJ | D98: 1, LISTA GENERAL | E98: 23204 | F98: 219512 | G98: 0 | H98: 45766 | I98: PS | J98: 23204 | K98: PS | L98: 25524 | M98: -2320 | N98: -9.09 | O98: 008, Cartón | P98: 001, Papel | Q98: 001, Manufactured Group Locall | R98: 005, Bandejas de Papel / Carto | S98: 200, 200 | T98: P11, 482370
A99: 0012COM10006 | B99: BANDEJA MICRO CORRUGADO N° 6 (4P X 50U) | C99: CAJ | D99: 1, LISTA GENERAL | E99: 20178 | F99: 219512 | G99: 0 | H99: 45766 | I99: PS | J99: 20178 | K99: PS | L99: 22196 | M99: -2018 | N99: -9.09 | O99: 008, Cartón | P99: 001, Papel | Q99: 001, Manufactured Group Locall | R99: 005, Bandejas de Papel / Carto | S99: 200, 200 | T99: P11, 482370
A100: 0012COM10012 | B100: BANDEJA MICRO CORRUGADO N°2 IMPRESA | C100: CAJ | D100: 1, LISTA GENERAL | E100: 37046 | F100: 219512 | G100: 0 | H100: 45919 | I100: PS | J100: 37046 | K100: PS | L100: 34622 | M100: 2424 | N100: 7 | O100: 008, Cartón | P100: 001, Papel | Q100: 001, Manufactured Group Locall | R100: 005, Bandejas de Papel / Carto | S100: 400, 400 | T100: P11, 482370
A101: 0012COM10013 | B101: BANDEJA MICRO CORRUGADO N°3 IMPRESA | C101: CAJ | D101: 1, LISTA GENERAL | E101: 42967 | F101: 219512 | G101: 0 | H101: 45919 | I101: PS | J101: 42967 | K101: PS | L101: 40156 | M101: 2811 | N101: 7 | O101: 008, Cartón | P101: 001, Papel | Q101: 001, Manufactured Group Locall | R101: 005, Bandejas de Papel / Carto | S101: 400, 400 | T101: P11, 482370
A102: 0012COM10014 | B102: BANDEJA MICRO CORRUGADO N°4 IMPRESA | C102: CAJ | D102: 1, LISTA GENERAL | E102: 52489 | F102: 219512 | G102: 0 | H102: 45919 | I102: PS | J102: 52489 | K102: PS | L102: 49055 | M102: 3434 | N102: 7 | O102: 008, Cartón | P102: 001, Papel | Q102: 001, Manufactured Group Locall | R102: 005, Bandejas de Papel / Carto | S102: 400, 400 | T102: P11, 482370
A103: 0012COM10015 | B103: BANDEJA MICRO CORRUGADO N°5 IMPRESA | C103: CAJ | D103: 1, LISTA GENERAL | E103: 32415 | F103: 219512 | G103: 0 | H103: 45919 | I103: PS | J103: 32415 | K103: PS | L103: 30294 | M103: 2121 | N103: 7 | O103: 008, Cartón | P103: 001, Papel | Q103: 001, Manufactured Group Locall | R103: 005, Bandejas de Papel / Carto | S103: 200, 200 | T103: P11, 482370
... A118: 0015PLA00017 | B118: PLATO DOR. N17 31X41 3KG | C118: PAQ | D118: 1, LISTA GENERAL | E118: 50564 | F118: 219512 | G118: 0 | H118: 45762 | I118: PS | J118: 50564 | K118: PS | L118: 45967 | M118: 4597 | N118: 10 | O118: 008, Cartón | P118: 001, Papel | Q118: 003, Purchased from 3rd Party | R118: 010, Platos de Carton | S118: 50, 50 | T118: P11, 482370
A119: 0016PIZ00001 | B119: CAJAS PIZZA GRIS CHICA | C119: PAQ | D119: 1, LISTA GENERAL | E119: 1 | F119: 219512 | G119: 0 | H119: 45766 | I119: PS | J119: 1 | L119: 0 | M119: 1 | N119: 0 | O119: 008, Cartón | P119: 001, Papel | Q119: 003, Purchased from 3rd Party | R119: 011, Cajas Carton | S119: 100, 100 | T119: P12, 481920
A120: 0016PIZ00002 | B120: CAJAS PIZZA GRIS GRANDE | C120: PAQ | D120: 1, LISTA GENERAL | E120: 1 | F120: 219512 | G120: 0 | H120: 45766 | I120: PS | J120: 1 | L120: 0 | M120: 1 | N120: 0 | O120: 008, Cartón | P120: 001, Papel | Q120: 003, Purchased from 3rd Party | R120: 011, Cajas Carton | S120: 100, 100 | T120: P12, 481920
A121: 0016PIZ00005 | B121: CAJAS PIZZA BLANCA CHICA | C121: PAQ | D121: 1, LISTA GENERAL | E121: 1 | F121: 219512 | G121: 0 | H121: 45766 | I121: PS | J121: 1 | L121: 0 | M121: 1 | N121: 0 | O121: 008, Cartón | P121: 001, Papel | Q121: 003, Purchased from 3rd Party | R121: 011, Cajas Carton | S121: 100, 100 | T121: P12, 481920
A122: 0016PIZ00006 | B122: CAJAS PIZZA BLANCA GRANDE | C122: PAQ | D122: 1, LISTA GENERAL | E122: 1 | F122: 219512 | G122: 0 | H122: 45766 | I122: PS | J122: 1 | L122: 0 | M122: 1 | N122: 0 | O122: 008, Cartón | P122: 001, Papel | Q122: 003, Purchased from 3rd Party | R122: 011, Cajas Carton | S122: 100, 100 | T122: P12, 481920
A123: 0016RAV00001 | B123: CAJAS RAVIOLES | C123: PAQ | D123: 1, LISTA GENERAL | E123: 1 | F123: 219512 | G123: 0 | H123: 45766 | I123: PS | J123: 1 | K123: PS | L123: 31110 | M123: -31109 | N123: -100 | O123: 008, Cartón | P123: 001, Papel | Q123: 003, Purchased from 3rd Party | R123: 011, Cajas Carton | S123: 100, 100 | T123: P12, 481920
A124: 0017COR00070 | B124: CARTON CORRUGADO 70 CM. | C124: ROL | D124: 1, LISTA GENERAL | E124: 1 | F124: 219512 | G124: 0 | H124: 45766 | I124: PS | J124: 1 | L124: 0 | M124: 1 | N124: 0 | O124: 008, Cartón | P124: 001, Papel | Q124: 003, Purchased from 3rd Party | R124: 012, Rollos Carton | S124: 1, 1 | T124: P13, 480810
A125: 0017COR00090 | B125: CARTON CORRUGADO 90 CM. | C125: ROL | D125: 1, LISTA GENERAL | E125: 1 | F125: 219512 | G125: 0 | H125: 45766 | I125: PS | J125: 1 | L125: 0 | M125: 1 | N125: 0 | O125: 008, Cartón | P125: 001, Papel | Q125: 003, Purchased from 3rd Party | R125: 012, Rollos Carton | S125: 1, 1 | T125: P13, 480810
A126: 0017COR00100 | B126: CARTON CORRUGADO 100 CM. | C126: ROL | D126: 1, LISTA GENERAL | E126: 1 | F126: 219512 | G126: 0 | H126: 45766 | I126: PS | J126: 1 | L126: 0 | M126: 1 | N126: 0 | O126: 008, Cartón | P126: 001, Papel | Q126: 003, Purchased from 3rd Party | R126: 012, Rollos Carton | S126: 1, 1 | T126: P13, 480810
A127: 0017COR00120 | B127: CARTON CORRUGADO 120 CM. | C127: ROL | D127: 1, LISTA GENERAL | E127: 1 | F127: 219512 | G127: 0 | H127: 45766 | I127: PS | J127: 1 | L127: 0 | M127: 1 | N127: 0 | O127: 008, Cartón | P127: 001, Papel | Q127: 003, Purchased from 3rd Party | R127: 012, Rollos Carton | S127: 1, 1 | T127: P13, 480810
A128: 0018DARBB0026 | B128: CAJA PARA ALIMENTOS DARNEL NATURAL 26 Oz BLANCA PAQX50 CAJ X200 UNI | C128: PAQ | D128: 1, LISTA GENERAL | E128: 41631 | F128: 219512 | G128: 0 | H128: 45919 | I128: PS | J128: 41631 | K128: PS | L128: 37846 | M128: 3785 | N128: 10 | O128: 008, Cartón | P128: 001, Papel | Q128: 002, Manufactured Group | R128: 013, Estuches de cartulina | S128: 200, 200 | T128: P14, 481820
A129: 0018DARBB0045 | B129: CAJA PARA ALIMENTOS DARNEL NATURAL 45 Oz BLANCO PQX50 CJX200 | C129: PAQ | D129: 1, LISTA GENERAL | E129: 60561 | F129: 219512 | G129: 0 | H129: 45919 | I129: PS | J129: 60561 | K129: PS | L129: 55055 | M129: 5506 | N129: 10 | O129: 008, Cartón | P129: 001, Papel | Q129: 002, Manufactured Group | R129: 013, Estuches de cartulina | S129: 200, 200 | T129: P14, 481820
A130: 0018DARBB0049 | B130: CAJA PARA ALIMENTOS DARNEL NATURALS 49 Oz BLANCO PQX50 CAJX200 | C130: PAQ | D130: 1, LISTA GENERAL | E130: 66037 | F130: 219512 | G130: 0 | H130: 45919 | I130: PS | J130: 66037 | L130: 0 | M130: 66037 | N130: 0 | O130: 008, Cartón | P130: 001, Papel | Q130: 002, Manufactured Group | R130: 013, Estuches de cartulina | S130: 200, 200 | T130: P14, 481820
A131: 0018DARBB0066 | B131: CAJA PARA ALIMENTOS DARNEL NATURAL 66 Oz BLANCO PQX50 CJX200 | C131: PAQ | D131: 1, LISTA GENERAL | E131: 72059 | F131: 219512 | G131: 0 | H131: 45919 | I131: PS | J131: 72059 | K131: PS | L131: 65508 | M131: 6551 | N131: 10 | O131: 008, Cartón | P131: 001, Papel | Q131: 002, Manufactured Group | R131: 013, Estuches de cartulina | S131: 200, 200 | T131: P14, 481820
A132: 0018DARBB0072 | B132: CAJA PARA ALIMENTOS DARNEL NATURALS 72 Oz BLANCO BLX100 | C132: PAQ | D132: 1, LISTA GENERAL | E132: 61831 | F132: 219512 | G132: 0 | H132: 45919 | I132: PS | J132: 61831 | L132: 0 | M132: 61831 | N132: 0 | O132: 008, Cartón | P132: 001, Papel | Q132: 002, Manufactured Group | R132: 013, Estuches de cartulina | S132: 100, 100 | T132: P14, 481820
A133: 0018DARBB0115 | B133: CAJA PARA ALIMENTOS DARNEL NATURALS 115 Oz BLANCO BLX100 UNID | C133: PAQ | D133: 1, LISTA GENERAL | E133: 85835 | F133: 219512 | G133: 0 | H133: 45919 | I133: PS | J133: 85835 | L133: 0 | M133: 85835 | N133: 0 | O133: 008, Cartón | P133: 001, Papel | Q133: 002, Manufactured Group | R133: 013, Estuches de cartulina | S133: 100, 100 | T133: P14, 481820
A134: 0018DARBBF0001 | B134: CAJA PEQUEÑA PARA PAPAS FRITAS DARNEL NATURAL BLANCA PQX100 CJX600 | C134: PAQ | D134: 1, LISTA GENERAL | E134: 28807 | F134: 219512 | G134: 0 | H134: 45919 | I134: PS | J134: 28807 | K134: PS | L134: 26188 | M134: 2619 | N134: 10 | O134: 008, Cartón | P134: 001, Papel | Q134: 002, Manufactured Group | R134: 013, Estuches de cartulina | S134: 600, 600 | T134: P14, 481820
A135: 0018DARBBF0005 | B135: CAJA MEDIANA PARA PAPAS FRITAS DARNEL NATURAL BLANCO PQX100 CJX600 | C135: PAQ | D135: 1, LISTA GENERAL | E135: 53086 | F135: 219512 | G135: 0 | H135: 45919 | I135: PS | J135: 53086 | K135: PS | L135: 48260 | M135: 4826 | N135: 10 | O135: 008, Cartón | P135: 001, Papel | Q135: 002, Manufactured Group | R135: 013, Estuches de cartulina | S135: 600, 600 | T135: P14, 481820
A136: 0018DARBBF0010 | B136: CAJA GRANDE PARA PAPAS FRITAS DARNEL NATURAL BLANCO PQX100 CJX600 | C136: PAQ | D136: 1, LISTA GENERAL | E136: 70615 | F136: 219512 | G136: 0 | H136: 45919 | I136: PS | J136: 70615 | K136: PS | L136: 64195 | M136: 6420 | N136: 10 | O136: 008, Cartón | P136: 001, Papel | Q136: 002, Manufactured Group | R136: 013, Estuches de cartulina | S136: 600, 600 | T136: P14, 481820
A137: 0018DARBBK072 | B137: CAJA PARA ALIMENTOS DARNEL NATURALS 72 Oz MOCA BLX100 | C137: PAQ | D137: 1, LISTA GENERAL | E137: 49141 | F137: 219512 | G137: 0 | H137: 45919 | I137: PS | J137: 49141 | L137: 0 | M137: 49141 | N137: 0 | O137: 008, Cartón | P137: 001, Papel | Q137: 002, Manufactured Group | R137: 013, Estuches de cartulina | S137: 100, 100 | T137: P14, 481820
A138: 0018DARBBK115 | B138: CAJA PARA ALIMENTOS DARNEL NATURALS 115 Oz MOCA BLX100 | C138: PAQ | D138: 1, LISTA GENERAL | E138: 31690 | F138: 219512 | G138: 0 | H138: 45919 | I138: PS | J138: 31690 | L138: 0 | M138: 31690 | N138: 0 | O138: 008, Cartón | P138: 001, Papel | Q138: 002, Manufactured Group | R138: 013, Estuches de cartulina | S138: 100, 100 | T138: P14, 481820
A139: 0018DARBK0026 | B139: CAJA PARA ALIMENTOS DARNEL NATURAL 26 Oz MOCA PAQX50 CAJ X200UNID | C139: PAQ | D139: 1, LISTA GENERAL | E139: 41473 | F139: 219512 | G139: 0 | H139: 45919 | I139: PS | J139: 41473 | K139: PS | L139: 37703 | M139: 3770 | N139: 10 | O139: 008, Cartón | P139: 001, Papel | Q139: 002, Manufactured Group | R139: 013, Estuches de cartulina | S139: 200, 200 | T139: P14, 481820
A140: 0018DARBK0045 | B140: CAJA PARA ALIMENTOS DARNEL NATURAL 45 Oz MOCA PQX50 CJX200 | C140: PAQ | D140: 1, LISTA GENERAL | E140: 60377 | F140: 219512 | G140: 0 | H140: 45919 | I140: PS | J140: 60377 | K140: PS | L140: 54888 | M140: 5489 | N140: 10 | O140: 008, Cartón | P140: 001, Papel | Q140: 002, Manufactured Group | R140: 013, Estuches de cartulina | S140: 200, 200 | T140: P14, 481820
A141: 0018DARBK0049 | B141: CAJA PARA ALIMENTOS DARNEL NATURAL 49 Oz MOCA PQX50 CJX200 | C141: PAQ | D141: 1, LISTA GENERAL | E141: 65361 | F141: 219512 | G141: 0 | H141: 45919 | I141: PS | J141: 65361 | K141: PS | L141: 59419 | M141: 5942 | N141: 10 | O141: 008, Cartón | P141: 001, Papel | Q141: 002, Manufactured Group | R141: 013, Estuches de cartulina | S141: 200, 200 | T141: P14, 481820
A142: 0018DARBK0066 | B142: CAJA PARA ALIMENTOS DARNEL NATURAL 66 Oz MOCA PQX50 CJX200 | C142: PAQ | D142: 1, LISTA GENERAL | E142: 71394 | F142: 219512 | G142: 0 | H142: 45919 | I142: PS | J142: 71394 | K142: PS | L142: 64904 | M142: 6490 | N142: 10 | O142: 008, Cartón | P142: 001, Papel | Q142: 002, Manufactured Group | R142: 013, Estuches de cartulina | S142: 200, 200 | T142: P14, 481820
A143: 0018DARBKF0001 | B143: CAJA PEQUEÑA PARA PAPAS FRITAS DARNEL NATURAL MOCA PQX100 CJX600 | C143: PAQ | D143: 1, LISTA GENERAL | E143: 28725 | F143: 219512 | G143: 0 | H143: 45919 | I143: PS | J143: 28725 | K143: PS | L143: 26114 | M143: 2611 | N143: 10 | O143: 008, Cartón | P143: 001, Papel | Q143: 002, Manufactured Group | R143: 013, Estuches de cartulina | S143: 600, 600 | T143: P14, 481820
A144: 0018DARBKS0049 | B144: CAJA PARA ALIMENTOS SAFETYPLUS DARNEL NATURAL 49 Oz MOCA PQX50CJX200 | C144: PAQ | D144: 1, LISTA GENERAL | E144: 70279 | F144: 219512 | G144: 0 | H144: 45919 | I144: PS | J144: 70279 | K144: PS | L144: 63890 | M144: 6389 | N144: 10 | O144: 008, Cartón | P144: 001, Papel | Q144: 002, Manufactured Group | R144: 013, Estuches de cartulina | S144: 200, 200 | T144: P14, 481820
A145: 0018DARBKS0066 | B145: CAJA PARA ALIMENTOS SAFETYPLUS DARNEL NAT 66oz MOCA PQX50 CJX200 | C145: PAQ | D145: 1, LISTA GENERAL | E145: 77199 | F145: 219512 | G145: 0 | H145: 45919 | I145: PS | J145: 77199 | K145: PS | L145: 70181 | M145: 7018 | N145: 10 | O145: 008, Cartón | P145: 001, Papel | Q145: 002, Manufactured Group | R145: 013, Estuches de cartulina | S145: 200, 200 | T145: P14, 481820
A146: 0018DARBKS026 | B146: CAJA PARA ALIMENTOS SAFETYPLUS DARNEL NATURAL 26 Oz MOCA PQX50 CAJX200 | C146: PAQ | D146: 1, LISTA GENERAL | E146: 43544 | F146: 219512 | G146: 0 | H146: 45919 | I146: PS | J146: 43544 | K146: PS | L146: 39585 | M146: 3959 | N146: 10 | O146: 008, Cartón | P146: 001, Papel | Q146: 002, Manufactured Group | R146: 013, Estuches de cartulina | S146: 200, 200 | T146: P14, 481820
A147: 0018DARBKS045 | B147: CAJA ALIMENTOS SAFETYPLUS DARNEL NATURALS 45 Oz MOCA PQX50 CAJX200 | C147: PAQ | D147: 1, LISTA GENERAL | E147: 65350 | F147: 219512 | G147: 0 | H147: 45919 | I147: PS | J147: 65350 | L147: 0 | M147: 65350 | N147: 0 | O147: 008, Cartón | P147: 001, Papel | Q147: 002, Manufactured Group | R147: 013, Estuches de cartulina | S147: 200, 200 | T147: P14, 481820
A148: 0018DARKH0001 | B148: CAJA PEQUEÑA PARA HAMBURGUESA DARNEL NATURAL MOCA PAQX50 CAJ X300UNI | C148: PAQ | D148: 1, LISTA GENERAL | E148: 42778 | F148: 219512 | G148: 0 | H148: 45919 | I148: PS | J148: 42778 | K148: PS | L148: 38889 | M148: 3889 | N148: 10 | O148: 008, Cartón | P148: 001, Papel | Q148: 002, Manufactured Group | R148: 013, Estuches de cartulina | S148: 300, 300 | T148: P14, 481820
A149: 0018DARKH0005 | B149: CAJA MEDIANA PARA HAMBURGUESA DARNEL NATURAL MOCA PAQX50 CAJ X300 UNI | C149: PAQ | D149: 1, LISTA GENERAL | E149: 43930 | F149: 219512 | G149: 0 | H149: 45919 | I149: PS | J149: 43930 | K149: PS | L149: 39936 | M149: 3994 | N149: 10 | O149: 008, Cartón | P149: 001, Papel | Q149: 002, Manufactured Group | R149: 013, Estuches de cartulina | S149: 300, 300 | T149: P14, 481820
A150: 0018DARKH0010 | B150: CAJA GRANDE PARA HAMBURGUESA DARNEL NATURAL MOCA PAQX50 CAJX300 | C150: PAQ | D150: 1, LISTA GENERAL | E150: 52688 | F150: 219512 | G150: 0 | H150: 45919 | I150: PS | J150: 52688 | K150: PS | L150: 47898 | M150: 4790 | N150: 10 | O150: 008, Cartón | P150: 001, Papel | Q150: 002, Manufactured Group | R150: 013, Estuches de cartulina | S150: 200, 200 | T150: P14, 481820
A151: 0018ESP00003 | B151: ESTUCHES PAPAS FRITAS GDE. | C151: CAJ | D151: 1, LISTA GENERAL | E151: 16194 | F151: 219512 | G151: 0 | H151: 45817 | I151: PS | J151: 16194 | K151: PS | L151: 14722 | M151: 1472 | N151: 10 | O151: 008, Cartón | P151: 001, Papel | Q151: 001, Manufactured Group Locall | R151: 013, Estuches de cartulina | S151: 450, 450 | T151: P14, 481820
A152: 0018ESP00004 | B152: ESTUCHES PAPAS FRITAS KRAFT X 1000 | C152: PAQ | D152: 1, LISTA GENERAL | E152: 30214 | F152: 219512 | G152: 0 | H152: 45817 | I152: PS | J152: 30214 | K152: PS | L152: 30831 | M152: -617 | N152: -2 | O152: 008, Cartón | P152: 001, Papel | Q152: 001, Manufactured Group Locall | R152: 013, Estuches de cartulina | S152: 1000, 1000 | T152: P14, 481820
A153: 0018ESV00003 | B153: PORTAVASO DE CARTULINA | C153: CAJ | D153: 1, LISTA GENERAL | E153: 33098 | F153: 219512 | G153: 0 | H153: 45769 | I153: PS | J153: 33098 | K153: PS | L153: 11721 | M153: 21377 | N153: 182.38 | O153: 008, Cartón | P153: 001, Papel | Q153: 003, Purchased from 3rd Party | R153: 013, Estuches de cartulina | S153: 400, 400 | T153: P14, 481820
A154: 0021ARR02026 | B154: ARRANQUE A.D. 20X25 (750 GR.) | C154: ROL | D154: 1, LISTA GENERAL | E154: 4187 | F154: 219512 | G154: 0 | H154: 45766 | I154: PS | J154: 4187 | K154: PS | L154: 4606 | M154: -419 | N154: -9.1 | O154: 011, Otros | P154: 002, Polietileno | Q154: 003, Purchased from 3rd Party | R154: 014, Bolsas | S154: 1, 1 | T154: P15, 392321
A155: 0021ARR02030 | B155: ARRANQUE A.D. 20X30 (1.5 KG.) | C155: ROL | D155: 1, LISTA GENERAL | E155: 7168 | F155: 219512 | G155: 0 | H155: 45897 | I155: PS | J155: 7168 | K155: PS | L155: 7877 | M155: -709 | N155: -9 | O155: 011, Otros | P155: 002, Polietileno | Q155: 003, Purchased from 3rd Party | R155: 014, Bolsas | S155: 1, 1 | T155: P15, 392321
A156: 0021ARR02535 | B156: ARRANQUE A.D. 25X35 (1.5 KG.) | C156: ROL | D156: 1, LISTA GENERAL | E156: 7168 | F156: 219512 | G156: 0 | H156: 45897 | I156: PS | J156: 7168 | K156: PS | L156: 7877 | M156: -709 | N156: -9 | O156: 011, Otros | P156: 002, Polietileno | Q156: 003, Purchased from 3rd Party | R156: 014, Bolsas | S156: 1, 1 | T156: P15, 392321
A157: 0021ARR03040 | B157: ARRANQUE A.D. 30X40 (1.5 KG.) | C157: ROL | D157: 1, LISTA GENERAL | E157: 7168 | F157: 219512 | G157: 0 | H157: 45897 | I157: PS | J157: 7168 | K157: PS | L157: 7877 | M157: -709 | N157: -9 | O157: 011, Otros | P157: 002, Polietileno | Q157: 003, Purchased from 3rd Party | R157: 014, Bolsas | S157: 1, 1 | T157: P15, 392321
A158: 0021ARR03545 | B158: ARRANQUE A.D. 35X45 (1.5 KG.) | C158: ROL | D158: 1, LISTA GENERAL | E158: 7168 | F158: 219512 | G158: 0 | H158: 45897 | I158: PS | J158: 7168 | K158: PS | L158: 7877 | M158: -709 | N158: -9 | O158: 011, Otros | P158: 002, Polietileno | Q158: 003, Purchased from 3rd Party | R158: 014, Bolsas | S158: 1, 1 | T158: P15, 392321
A159: 0021ARR04050 | B159: ARRANQUE A.D.40X50 (1.5kG) | C159: ROL | D159: 1, LISTA GENERAL | E159: 7168 | F159: 219512 | G159: 0 | H159: 45897 | I159: PS | J159: 7168 | K159: PS | L159: 7877 | M159: -709 | N159: -9 | O159: 011, Otros | P159: 002, Polietileno | Q159: 003, Purchased from 3rd Party | R159: 014, Bolsas | S159: 1, 1 | T159: P15, 392321
... A169: 0027AUT00045 | B169: PVC AUTOMATICO 18" FV 50 | C169: ROL | D169: 1, LISTA GENERAL | E169: 79433 | F169: 219512 | G169: 0 | H169: 45769 | I169: PS | J169: 79433 | K169: PS | L169: 83215 | M169: -3782 | N169: -4.54 | O169: 004, PVC Automatico | P169: 003, PVCF | Q169: 002, Manufactured Group | R169: 016, Wrap Alimentos | S169: 1, 1 | T169: P17, 392043
A170: 0027BIO28100 | B170: PVC BIO DARNEL WRAP 31X28X100MTS | C170: ROL | D170: 1, LISTA GENERAL | E170: 2928 | F170: 219512 | G170: 0 | H170: 45897 | I170: PS | J170: 2928 | L170: 0 | M170: 2928 | N170: 0 | O170: 016, PVC 1400 | P170: 003, PVCF | Q170: 002, Manufactured Group | R170: 016, Wrap Alimentos | S170: 1, 1 | T170: P17, 392043
A171: 0027BIO28300 | B171: PVC BIO DARNEL WRAP 31X28X300 MTS | C171: ROL | D171: 1, LISTA GENERAL | E171: 9185 | F171: 219512 | G171: 0 | H171: 45897 | I171: PS | J171: 9185 | L171: 0 | M171: 9185 | N171: 0 | O171: 016, PVC 1400 | P171: 003, PVCF | Q171: 002, Manufactured Group | R171: 016, Wrap Alimentos | S171: 1, 1 | T171: P17, 392043
A172: 0027BIO38100 | B172: PVC BIO DARNEL WRAP 35X38X1000 MTS | C172: ROL | D172: 1, LISTA GENERAL | E172: 41315 | F172: 219512 | G172: 0 | H172: 45897 | I172: PS | J172: 41315 | L172: 0 | M172: 41315 | N172: 0 | O172: 016, PVC 1400 | P172: 003, PVCF | Q172: 002, Manufactured Group | R172: 016, Wrap Alimentos | S172: 1, 1 | T172: P17, 392043
A173: 0027EST00012 | B173: PVC 12 " (X 1400 MTS.) | C173: ROL | D173: 1, LISTA GENERAL | E173: 33438 | F173: 219512 | G173: 0 | H173: 45880 | I173: PS | J173: 33438 | K173: PS | L173: 30398 | M173: 3040 | N173: 10 | O173: 016, PVC 1400 | P173: 003, PVCF | Q173: 002, Manufactured Group | R173: 016, Wrap Alimentos | S173: 1, 1 | T173: P17, 392043
A174: 0027EST00015 | B174: PVC 15 " (X 1400 MTS.) | C174: ROL | D174: 1, LISTA GENERAL | E174: 42424 | F174: 219512 | G174: 0 | H174: 45880 | I174: PS | J174: 42424 | K174: PS | L174: 38567 | M174: 3857 | N174: 10 | O174: 016, PVC 1400 | P174: 003, PVCF | Q174: 002, Manufactured Group | R174: 016, Wrap Alimentos | S174: 1, 1 | T174: P17, 392043
A175: 0027EST00018 | B175: PVC 18 " (X 1400 MTS.) | C175: ROL | D175: 1, LISTA GENERAL | E175: 50280 | F175: 219512 | G175: 0 | H175: 45880 | I175: PS | J175: 50280 | K175: PS | L175: 45709 | M175: 4571 | N175: 10 | O175: 016, PVC 1400 | P175: 003, PVCF | Q175: 002, Manufactured Group | R175: 016, Wrap Alimentos | S175: 1, 1 | T175: P17, 392043
A176: 0027EST00022 | B176: PVC 400 MM (X 1400 MTS.) | C176: ROL | D176: 1, LISTA GENERAL | E176: 48172 | F176: 219512 | G176: 0 | H176: 45769 | I176: PS | J176: 48172 | K176: PS | L176: 50466 | M176: -2294 | N176: -4.55 | O176: 016, PVC 1400 | P176: 003, PVCF | Q176: 002, Manufactured Group | R176: 016, Wrap Alimentos | S176: 1, 1 | T176: P17, 392043
A177: 0027LIG00030 | B177: PVC X 500 MTS. 12" | C177: ROL | D177: 1, LISTA GENERAL | E177: 11505 | F177: 219512 | G177: 0 | H177: 45880 | I177: PS | J177: 11505 | K177: PS | L177: 10459 | M177: 1046 | N177: 10 | O177: 014, PVC 500 | P177: 003, PVCF | Q177: 002, Manufactured Group | R177: 016, Wrap Alimentos | S177: 1, 1 | T177: P17, 392043
A178: 0027LIG00038 | B178: PVC X 500 MTS. 15" | C178: ROL | D178: 1, LISTA GENERAL | E178: 14366 | F178: 219512 | G178: 0 | H178: 45880 | I178: PS | J178: 14366 | K178: PS | L178: 12827 | M178: 1539 | N178: 12 | O178: 014, PVC 500 | P178: 003, PVCF | Q178: 002, Manufactured Group | R178: 016, Wrap Alimentos | S178: 1, 1 | T178: P17, 392043
A179: 0027LIG00045 | B179: PVC X 500 MTS. 18" | C179: ROL | D179: 1, LISTA GENERAL | E179: 16769 | F179: 219512 | G179: 0 | H179: 45880 | I179: PS | J179: 16769 | K179: PS | L179: 15672 | M179: 1097 | N179: 7 | O179: 014, PVC 500 | P179: 003, PVCF | Q179: 002, Manufactured Group | R179: 016, Wrap Alimentos | S179: 1, 1 | T179: P17, 392043
A180: 0027LIG00138 | B180: PVC 762 MTS. 15" | C180: ROL | D180: 1, LISTA GENERAL | E180: 19922 | F180: 219512 | G180: 0 | H180: 45897 | I180: PS | J180: 19922 | L180: 0 | M180: 19922 | N180: 0 | O180: 014, PVC 500 | P180: 003, PVCF | Q180: 002, Manufactured Group | R180: 016, Wrap Alimentos | S180: 1, 1 | T180: P17, 392043
A181: 0027LIG00145 | B181: PVC 752 MTS. X 18" | C181: ROL | D181: 1, LISTA GENERAL | E181: 24600 | F181: 219512 | G181: 0 | H181: 45766 | I181: PS | J181: 24600 | L181: 0 | M181: 24600 | N181: 0 | O181: 014, PVC 500 | P181: 003, PVCF | Q181: 002, Manufactured Group | R181: 016, Wrap Alimentos | S181: 1, 1 | T181: P17, 392043
A182: 0027LIG00238 | B182: PVC 677 MTS. X 15" | C182: ROL | D182: 1, LISTA GENERAL | E182: 18892 | F182: 219512 | G182: 0 | H182: 45897 | I182: PS | J182: 18892 | L182: 0 | M182: 18892 | N182: 0 | O182: 014, PVC 500 | P182: 003, PVCF | Q182: 002, Manufactured Group | R182: 016, Wrap Alimentos | S182: 1, 1 | T182: P17, 392043
A183: 0027LIG01012 | B183: PVC ECONO FILM 12" | C183: ROL | D183: 1, LISTA GENERAL | E183: 20496 | F183: 219512 | G183: 0 | H183: 45769 | I183: PS | J183: 20496 | K183: PS | L183: 21472 | M183: -976 | N183: -4.55 | O183: 015, PVC 1000 | P183: 003, PVCF | Q183: 002, Manufactured Group | R183: 016, Wrap Alimentos | S183: 1, 1 | T183: P17, 392043
A184: 0027LIG01015 | B184: PVC ECONO FILM 15" | C184: ROL | D184: 1, LISTA GENERAL | E184: 25962 | F184: 219512 | G184: 0 | H184: 45769 | I184: PS | J184: 25962 | K184: PS | L184: 27199 | M184: -1237 | N184: -4.55 | O184: 015, PVC 1000 | P184: 003, PVCF | Q184: 002, Manufactured Group | R184: 016, Wrap Alimentos | S184: 1, 1 | T184: P17, 392043
...

Sheet PVC
B2: LISTA DE PRECIOS de 26 DE OCTUBRE 2026 (B18)
B3: COMPAÑÍA LA PILARICA S. A. - DARNEL WWW.DARNELGROUP.COM
B4: CODIGO PILARICA | C4: CODIGO DARNEL | D4: U/M | E4: C/U | F4: DESCRIPCION | G4: COMENTARIO | H4: PRECIO
B5: FILM DE PVC
B6: PVC DARNEL 500 Mts.
B7: 0027LIG00030 | C7: SA135-300-500L | D7: Rollo | E7: 1 | F7: PVC 300mm (12") 300MM x 500 MTS. | H7: 13343
B8: 0027LIG00038 | C8: SA135-380-500L | D8: Rollo | E8: 1 | F8: PVC 380mm (15") 380MM x 500 MTS. | H8: 16489
B9: 0027LIG00045 | C9: SA135-450-500L | D9: Rollo | E9: 1 | F9: PVC 450mm (18") 450MM x 500 MTS. | H9: 19249
B10: PVC DARNEL 1000 Mts.
B11: 0027LIG01012 | C11: SA1D353001000 | D11: Rollo | E11: 1 | F11: PVC ECONO FILM 12" (300MM x 1000 MTS.) | H11: 23283
B12: 0027LIG01015 | C12: SA1D353801000 | D12: Rollo | E12: 1 | F12: PVC ECONO FILM 15" (380MM x 1000 MTS.) | H12: 29490
B13: 0027LIG01018 | C13: SA1D354501000 | D13: Rollo | E13: 1 | F13: PVC ECONO FILM 18" (450MM x 1000 MTS.) | H13: 34282
B14: PVC DARNEL 1400 Mts.
B15: 0027EST00012 | C15: SA1D35-300-1400 | D15: Rollo | E15: 1 | F15: PVC 12 " (300 MM X 1400 MTS.) | H15: =_xlfn.XLOOKUP(B15,lista!A:A,lista!C:C,0,0) -> 34508
B16: 0027EST00015 | C16: SA1D35-380-1400 | D16: Rollo | E16: 1 | F16: PVC 15 " (380MM X 1400 MTS.) | H16: =_xlfn.XLOOKUP(B16,lista!A:A,lista!C:C,0,0) -> 43780
B17: 0027EST00018 | C17: SA1D35-450-1400 | D17: Rollo | E17: 1 | F17: PVC 18 " (450MM X 1400 MTS.) | H17: =_xlfn.XLOOKUP(B17,lista!A:A,lista!C:C,0,0) -> 51888
B18: PVC LINEA TAMI
B19: 0027TAM28050 | C19: ST2-280-50R | D19: Rollo | E19: 1 | F19: PVC TAMI WRAP 280 MM X 50 MTS | G19: 35 unid./caja | H19: 1375
B20: 0027TAM28100 | C20: ST2-280-100R | D20: Rollo | E20: 1 | F20: PVC TAMI WRAP 280 MM X 100 MTS | G20: 24 unid./caja | H20: 2287
B21: PVC LINEA DOMESTICA
B22: 0027REP00282 | C22: ST3-280-200 | D22: Rollo | E22: 1 | F22: PVC REPUESTO 12" (300MM X 200 MTS) | G22: 15 unid./caja | H22: 4416
B23: 0027REP00382 | C23: ST3-380-200 | D23: Rollo | E23: 1 | F23: PVC REPUESTO 15" (380MM X 200 MTS) | G23: 15 Unid./caja | H23: 5733
B24: 0027REP00015 | C24: SD135-380-300R | D24: Rollo | E24: 1 | F24: PVC REPUESTO 15" (380MM X 300 MTS.) | G24: 12 unid./caja | H24: 9255
B25: 0027REP00030 | C25: SD135-380-300D | D25: Rollo | E25: 1 | F25: REPUESTO 15" (380MM X 300 MTS.) C/Dispenser | G25: 6 unid./caja | H25: 13184
B26: 0027REP00018 | C26: SD135-450-300DRB | D26: Rollo | E26: 1 | F26: PVC REPUESTO 18" (450MM X 300 MTS) | G26: 12 unid./caja | H26: 11297
B27: 0027REP00036 | C27: SD135-450-300D | D27: Rollo | E27: 1 | F27: PVC REPUESTO 18" (450mm X 300mts) C/Dispenser | G27: 6 unid./caja | H27: 14713
B28: PVC LINEA BIODEGRADABLE
B29: 0027BIO38100 | C29: SA4B35-380-1000 | D29: Rollo | E29: 1 | F29: PVC BIODEG. DARNEL 380MM X 1000 MTS | H29: 33577
B30: 0027BIO28100 | C30: SA4B31-280-100DR | D30: Rollo | E30: 1 | F30: PVC BIODEG. DARNEL 280MM X 100 MTS | G30: 24 unid./caja | H30: 2683
B31: 0027BIO28300 | C31: SA4B31-280-300D | D31: Rollo | E31: 1 | F31: PVC BIODEG DARNEL 280mm x 300 Mts C/Dispenser | G31: 6 unid./caja | H31: 9310
B32: LOS PRECIOS SON MAS IVA

Sheet Porta Comida XPS
B2: LISTA DE PRECIOS de 26 DE OCTUBRE 2026 (B18)
C3: COMPAÑÍA LA PILARICA S. A. - DARNEL WWW.DARNELGROUP.COM
B4: CODIGO PILARICA | C4: CODIGO DARNEL | D4: U/M | E4: C/U | F4: DESCRIPCION | G4: COMENTARIO | H4: PRECIO BULTO $
B5: PLATO TERMICO DE EXPANDIDO (MARMITAS)
B6: 0034CON00020 | C6: D742801RLFY | D6: paq | E6: 100 | F6: PLATO TERMICO C/TAPA R102 850ml (base/tapa) | G6: diam 190x50mm | H6: 24084
B7: 0034CON00021 | C7: D741701RY | D7: paq | E7: 100 | F7: PLATO TERMICO C/TAPA R100 500ml (base/tapa) | G7: diam 190x35mm | H7: 24509
B8: 0034CON00022 | C8: D744001RY | D8: paq | E8: 100 | F8: PLATO TERMICO C/TAPA R104 1200ml (base/tapa) | G8: diam 190x68mm | H8: 28822
B9: PLATOS ESPUMADOS
B10: 0034DARPWH05 | C10: D5105101NW | D10: caja | E10: 480 | F10: DARNEL PLATO HONDO BLANCO 5oz x 20u. | G10: Nuevo | H10: =_xlfn.XLOOKUP(B10,lista!A:A,lista!C:C,0,0) -> 15646
B11: 0034DARPW0015 | C11: D510601NW | D11: caja | E11: 480 | F11: DARNEL PLATO BLANCO 15,5 cm x 20u. | G11: Nuevo | H11: =_xlfn.XLOOKUP(B11,lista!A:A,lista!C:C,0,0) -> 22123
B12: 0034DARPW0023 | C12: D510901NW | D12: caja | E12: 480 | F12: DARNEL PLATO BLANCO 23 cm x 20u. | G12: Nuevo | H12: =_xlfn.XLOOKUP(B12,lista!A:A,lista!C:C,0,0) -> 43919
B13: ESTUCHES RECTANGULAR DE EXPANDIDO
B14: 0034DARP0001 | C14: NUEVO | D14: Bolson | E14: 200 | F14: PORTACOMIDA UY EXPANDIDO NR-J1 S/DIV x 200 un | G14: 230x160x60mm | H14: 28791
B15: 0034DARP0002 | C15: NUEVO | D15: Bolson | E15: 200 | F15: PORTACOMIDA UY EXPANDIDO NR-J2 C/DIV x 200 un | G15: 230x160x60mm | H15: 30819
B16: 0034DARP0011 | C16: NUEVO | D16: Bolson | E16: 200 | F16: PORTACOMIDA Uy EXPAND. NR-J1 BIO S/DIV x 200un | G16: 230x160x60mm | H16: 34510
B17: 0034DARP0022 | C17: NUEVO | D17: Bolson | E17: 200 | F17: PORTACOMIDA UY EXPAND. NR-J2 BIO C/DIV x 200un | G17: 230x160x60mm | H17: 36469
B18: ESTUCHES HAMBURGUESA DE EXPANDIDO
B19: 0034CON00017 | C19: D401101LNWCFY | D19: paq | E19: 400 | F19: ESTUCHE HAMBURGUESA CHICO G-1 | G19: 150x150x75mm | H19: 42029
B20: 0034CON00018 | C20: D402103CFY | D20: paq | E20: 400 | F20: ESTUCHE HAMBURGUESA GRANDE DH-03 | G20: 170x170x80mm | H20: 50045
B21: PORTA COMIDAS DE EXPANDIDO
B22: 0034CON00010 | C22: D7416015FY | D22: paq | E22: 400 | F22: BANDEJA TERMICA DM70 de 500ml (simil 102) | G22: 116x162x39mm | H22: 29616
B23: 0034CON00011 | C23: D7416015LTFY | D23: paq | E23: 400 | F23: TAPA PARA BAND. TERMICA DM70 de 500ml | G23: 130x170x10mm | H23: 22679
B24: 0034CON00012 | C24: D743001RFY | D24: paq | E24: 200 | F24: BANDEJA TERMICA DM90-A3 con 3 DIVIS 900ml | G24: 162x220x52mm | H24: 34952
B25: 0034CON00013 | C25: D743401RFY | D25: paq | E25: 200 | F25: BANDEJA TERMICA DM90-A1 (1000ml) | G25: 162x220x52mm | H25: 28097
B26: 0034CON00014 | C26: D742001RLTFY | D26: paq | E26: 200 | F26: TAPA PARA BAND. TERMICA DM90 para (900 y 1000ml) | G26: 173x225x12mm | H26: 24555
B27: 0034CON00015 | C27: D744101RFY | D27: paq | E27: 200 | F27: BANDEJA TERMICA con 3 DIVIS DM100 (1200ml) | G27: 205x260x40mm | H27: 42304
B28: 0034CON00016 | C28: D744101RLTFY | D28: paq | E28: 200 | F28: TAPA PARA BAND TERMICA DM 100 (para 1200ml) | G28: 216x275x12mm | H28: 40979
B29: LOS PRECIOS SON MAS IVA

Sheet Band. Expandido
B3: LISTA DE PRECIOS de 26 DE OCTUBRE 2026 (B18)
C4: COMPAÑÍA LA PILARICA S. A. - DARNEL WWW.DARNELGROUP.COM
B5: CODIGO PILARICA | C5: CODIGO DARNEL | D5: U/M | E5: C/U | F5: DESCRIPCION | G5: COMENTARIO | H5: PRECIO BULTO $
B6: BANDEJAS DE EXPANDIDO ECONOMICAS
B7: 0032ECO00615 | C7: D2001001LE | D7: Bolson | E7: 400 | F7: BANDEJA 615 ECO BLANCA | H7: 23381
B8: 0032ECO00617 | C8: D2001101L | D8: Bolson | E8: 400 | F8: BANDEJA 617 ECO BLANCA | H8: 13789
B9: 0032ECO00618 | C9: D2000201LEE | D9: Bolson | E9: 400 | F9: BANDEJA 618 ECO BLANCA | H9: 17700
B10: 0032ECO00619 | C10: D2000401LEE | D10: Bolson | E10: 400 | F10: BANDEJA 619 ECO BLANCA | H10: 24844
B11: 0032ECO00625 | C11: D2000801LE | D11: Bolson | E11: 200 | F11: BANDEJA 625 ECO BLANCA | H11: 17503
B12: 0032ECO00628 | C12: D20028R01LE | D12: Bolson | E12: 200 | F12: BANDEJA 628 ECO BLANCA PIZZERA | H12: 28905
B13: BANDEJAS DE EXPANDIDO STANDARD
B14: 0032STD00615 | C14: D2001001LE | D14: Bolson | E14: 400 | F14: BANDEJA 615 BLANCA Standard | H14: 28861
B15: 0032STD00617 | C15: D2001101LA | D15: Bolson | E15: 400 | F15: BANDEJA 617 BLANCA Standard | H15: 18115
B16: 0032STD00618 | C16: D2000201LE | D16: Bolson | E16: 400 | F16: BANDEJA 618 BLANCA Standard | H16: 22010
B17: 0032STD00619 | C17: D2000401LE | D17: Bolson | E17: 400 | F17: BANDEJA 619 BLANCA Standard | H17: 30722
B18: 0032STD00625 | C18: D2000801L | D18: Bolson | E18: 200 | F18: BANDEJA 625 BLANCA Standard | H18: 21488
B19: 0032STD00628 | C19: D20028R01L | D19: Bolson | E19: 200 | F19: BANDEJA 628 BLANCA PIZZERA Standard | H19: 37446
B20: OBLEAS DE EXPANDIDO STANDARD
B21: 0032STDO0618 | C21: D00211401L | D21: Bolson | E21: 400 | F21: OBLEA 618 BLANCA Standard | H21: 21712
B22: 0032STDO0619 | C22: D00231801L | D22: Bolson | E22: 400 | F22: OBLEA 619 BLANCA Standard | H22: 27440
B23: BANDEJAS DE EXPANDIDO AUTOABSORBENTES BLANCAS
B24: 0031LIE00615 | C24: D2001001LBB | D24: Bolson | E24: 400 | F24: BAND N° 10BB Bca (10SLE BCA) Absorbentes | H24: =_xlfn.XLOOKUP(B24,lista!A:A,lista!C:C,0,0) -> 52040
B25: 0031LIE00618 | C25: D2000201LBB | D25: Bolson | E25: 400 | F25: BAND N° 2BB Bca (2SLE BCA) Absorbentes | H25: =_xlfn.XLOOKUP(B25,lista!A:A,lista!C:C,0,0) -> 39300
B26: 0031LIE00619 | C26: D2000401LBB | D26: Bolson | E26: 400 | F26: BAND N° 4BB Bca (4SLE BCA) Absorbentes | H26: =_xlfn.XLOOKUP(B26,lista!A:A,lista!C:C,0,0) -> 52858
B27: 0031LIN00625 | C27: D2000801LBBC | D27: Bolson | E27: 200 | F27: BAND N° 8BBC Bca (8SL BCA) Absorbentes | H27: =_xlfn.XLOOKUP(B27,lista!A:A,lista!C:C,0,0) -> 47057
B28: BANDEJAS DE EXPANDIDO STANDARD COLOR
B29: 0032STD02615 | D29: Bolson | E29: 400 | F29: BANDEJA 615 COLOR (AMA, ROSA, NEGRA) Std. | H29: 30175
B30: 0032STD02618 | D30: Bolson | E30: 400 | F30: BANDEJA 618 COLOR (AMA, ROSA, NEGRA) Std. | H30: 23685
B31: 0032STD02619 | D31: Bolson | E31: 400 | F31: BANDEJA 619 COLOR (AMA, ROSA, NEGRA) Std. | H31: 32980
B32: BANDEJAS DE EXPANDIDO REGULARES BIODEGRADABLES
B33: 0032BIO00615 | C33: D2001003LE | D33: Bolson | E33: 400 | F33: BAND N° 10 STD Blanca BIO (615 BIO) | H33: =_xlfn.XLOOKUP(B33,lista!A:A,lista!C:C,0,0) -> 33143
B34: 0032BIO00617 | C34: D2001103LA | D34: Bolson | E34: 400 | F34: BAND N° 11 STD Blanca BIO (617 BIO) | H34: =_xlfn.XLOOKUP(B34,lista!A:A,lista!C:C,0,0) -> 20454
B35: 0032BIO00618 | C35: D2000203LE | D35: Bolson | E35: 400 | F35: BAND. N° 2 STD Blanca BIO (618 BIO) | H35: =_xlfn.XLOOKUP(B35,lista!A:A,lista!C:C,0,0) -> 25667
B36: 0032BIO00619 | C36: D2000403LE | D36: Bolson | E36: 400 | F36: BAND. N° 4 STD Blanca BIO (619 BIO) | H36: =_xlfn.XLOOKUP(B36,lista!A:A,lista!C:C,0,0) -> 35844
B37: 0032BIO00628 | C37: D20028R03L | D37: Bolson | E37: 200 | F37: BAND. N° 28 STD Blanca BIO (628 BIO) | H37: =_xlfn.XLOOKUP(B37,lista!A:A,lista!C:C,0,0) -> 0
B38: BANDEJAS DE EXPANDIDO AUTOABSORBENTES BIODEGRADABLES
C39: D2000203LBB | D39: Bolson | F39: BAND 2SL Absorb. BIO (618 Abs.) | G39: NUEVO | H39: =_xlfn.XLOOKUP(B39,lista!A:A,lista!C:C,0,0) -> 0
C40: D2000403LBB | D40: Bolson | F40: BAND 4SL Absorb. BIO (619 Abs.) | G40: NUEVO | H40: =_xlfn.XLOOKUP(B40,lista!A:A,lista!C:C,0,0) -> 0
C41: D2001003LBB | D41: Bolson | F41: BAND 10SL Absorb. BIO (615 Abs.) | G41: NUEVO | H41: =_xlfn.XLOOKUP(B41,lista!A:A,lista!C:C,0,0) -> 0
C42: D2100803LBBA | D42: Bolson | F42: BAND 8SL Absorb. BIO (625 Abs.) | G42: NUEVO | H42: =_xlfn.XLOOKUP(B42,lista!A:A,lista!C:C,0,0) -> 0
B43: PORTA COMIDAS DE EXPANDIDO BIO
B44: 0034DARPB001 | C44: D403103LNW | D44: Caja | E44: 200 | F44: PORTACOMIDA JL-1 BIO | G44: Nuevo | H44: =_xlfn.XLOOKUP(B44,lista!A:A,lista!C:C,0,0) -> 45748
B45: 0034DARPB002 | C45: D403103NW | D45: Caja | E45: 200 | F45: PORTACOMIDA J-1 BIO | G45: Nuevo | H45: =_xlfn.XLOOKUP(B45,lista!A:A,lista!C:C,0,0) -> 49737
B46: 0034DARPB003 | C46: D405103NW | D46: Caja | E46: 200 | F46: PORTACOMIDA P-1 BIO | G46: Nuevo | H46: =_xlfn.XLOOKUP(B46,lista!A:A,lista!C:C,0,0) -> 52087
B47: 0034DARPB004 | C47: D405303NW | D47: Caja | E47: 200 | F47: PORTACOMIDA P-3 (3 Div.) BIO | G47: Nuevo | H47: =_xlfn.XLOOKUP(B47,lista!A:A,lista!C:C,0,0) -> 50977
B51: LOS PRECIOS SON MAS IVA

Sheet Linea Aluminio
B2: LISTA DE PRECIOS de 26 DE OCTUBRE 2026 (B18)
C3: COMPAÑÍA LA PILARICA S. A. - DARNEL WWW.DARNELGROUP.COM
B4: CODIGO PILARICA | C4: CODIGO DARNEL | D4: U/M | E4: C/U | F4: DESCRIPCION | G4: COMENTARIO | H4: PRECIO BULTO $
B5: ROLLOS LINEA ALUMINIO
B6: 0063DAR00003 | C6: Q12301000Y | D6: Rollo | E6: 9 | F6: Papel ALUMINIO 30cm x 100mts c/Dispens. | G6: 9 unid x caja | H6: 176828.93
B7: 0063DAR00004 | C7: Q12300040Y | D7: Rollo | E7: 25 | F7: Papel ALUMINO 30cm x 4mts | G7: 25 un. x caja | H7: 25791.23
B8: 0063DAR00005 | C8: Q12300075Y | D8: Rollo | E8: 25 | F8: Papel ALUMINO 30cm x 7,5mts | G8: 25 un. x caja | H8: 42004.664
B9: 0063DAR00006 | C9: Q12450040Y | D9: Rollo | E9: 25 | F9: Papel ALUMINO 45cm x 4mts | G9: 25 un. x caja | H9: 42351.36
B10: 0063DAR00007 | C10: Q12450650Y | D10: Rollo | E10: 9 | F10: Papel ALUMINO 45cm x 65mts c/Dispens. | G10: 9 unid x caja | H10: 193448.47
B11: 0063DAR00008 | C11: Q12450075Y | D11: Rollo | E11: 25 | F11: Papel ALUMINO 45cm x 7,5mts | G11: 25 un. x caja | H11: 68530.262
B12: 0063ROL00001 | D12: Rollo | E12: 1 | F12: ROLLO ALUMINIO X 1KG. | G12: 1 un x caja | H12: 18866.494
B13: BANDEJAS CON TAPA CARTON ALUMINIZADO
B14: 0061DAR00008 | C14: Q510135RY | D14: Caja | E14: 100 | F14: Bandeja Rectangular Chica 4,5oz (135ml) Con Tapa - DSM | G14: 9,8x7,8x2,8cm | H14: 8250
B15: 0061DAR00003 | C15: Q520220RY | D15: Caja | E15: 200 | F15: Bandeja Rectang. Chica 8oz (220ml) Con Tapa - DA12 | G15: 12,6x9,8x2,6cm | H15: 21726
B16: 0061DAR00012 | C16: Q510500RSTY | D16: Caja | E16: 100 | F16: Band. Rectangular Mediana 16oz SinTapa - DA6-F50 | G16: 16,5x12,4x3,5cm | H16: 14917
B17: 0061DAR00011 | C17: Q510500RY | D17: Caja | E17: 100 | F17: Band. Rectangular Mediana 16oz ConTapa - DA6-F50 | G17: 16,5x12,4x3,5cm | H17: 17997
B18: 0061DAR00002 | C18: Q510650RY | D18: Caja | E18: 100 | F18: Band. Rectang. Budin Ingles 20oz Sin Tapa - DA10 | G18: 21,2x10,2x4,3cm | H18: 16314
B19: 0061DAR00007 | C19: Q510750RSTY | D19: Caja | E19: 100 | F19: Bandeja Rectangular 24oz Sin Tapa - DA7-F75 | G19: 20,6x13,8x3,3cm | H19: 19027
B20: 0061DAR00004 | C20: Q510750RY | D20: Caja | E20: 100 | F20: Bandeja Rectangular 24oz Con Tapa - DA7-F75 | G20: 20,6x13,8x3,3cm | H20: 26629
B21: 0061DAR00010 | C21: Q511000RSTY | D21: Caja | E21: 100 | F21: Band. Rectangular Grande 32oz Sin Tapa - DA2-F100 | G21: 20,0x15,2x4,9cm | H21: 20782
B22: 0061DAR00009 | C22: Q511000RY | D22: Caja | E22: 100 | F22: Band. Rectangular Grande 32oz Con Tapa - DA2-F100 | G22: 20,0x15,2x4,9cm | H22: 28603
B23: 0061DAR00024 | C23: Q511150RSTY | D23: Caja | E23: 100 | F23: Band. Rectang. 40oz 1150ml Sin Tapa - DA5-F1150 | G23: 22,1x17,6x4,0cm | H23: 22518.471
B24: 0061DAR00025 | C24: Q511150RY | D24: Caja | E24: 100 | F24: Band. Rectang. 40oz 1150ml Con Tapa - DA5-F1150 | G24: 22,1x17,6x4,0cm | H24: 32673.064
B25: 0061DAR00026 | C25: Q511500RSTY | D25: Caja | E25: 100 | F25: Fuente Rectang. 48oz 1500ml Sin Tapa - DA8-F1500 | G25: 27,5x18,5x4,2cm | H25: 29759.112
... B28: 0061DAR00027 | C28: Q512000RY | D28: Caja | E28: 100 | F28: Fuente Rectang. Grande 68oz 2000ml con Tapa - DA9 | G28: 28,9x22,8x4,1cm | H28: 57350
B29: LINEA BANDEJAS ALUMINIO TAMAÑO FAMILIAR
B30: 0061DAR00006 | C30: Q504000OY | D30: Caja | E30: 12 | F30: Bandeja Ovalada Grande 136oz 4000ml - DAY40 | G30: 32,5x26,5x6,6cm | H30: 13409
B31: 0061DAR00013 | C31: Q504000RY | D31: Caja | E31: 12 | F31: Bandeja Rectangular Grande 136oz 4000ml - DA40 | G31: 32,5x26,5x6,6cm | H31: 13722
B32: LINEA PACK BANDEJAS EN TERMOCONTRAIBLE
B33: 0061DAR00031 | C33: Q510220RY | D33: Caja | E33: 100 | F33: Pack Bandeja 8oz 220ml 10u x 10p. Base/Tapa - DA12 | G33: 12,6x9,8x2,6cm | H33: 12799
B34: 0061DAR00001 | C34: Q551150RY | D34: Caja | E34: 50 | F34: Pack Bandeja 40oz 1150ml 10u x 5p Base/Tapa - DA5 | G34: 22,1x17,6x4,0cm | H34: 17279
B35: 0061DAR00032 | C35: Q550500RY | D35: Caja | E35: 50 | F35: Pack Bandeja 16oz 500ml 10u x 5p. Base/Tapa - DA6 | G35: 16,5x12,4x3,5cm | H35: 10587
B36: 0061DAR00033 | C36: Q550700RY | D36: Caja | E36: 50 | F36: Pack Bandeja 24oz 700ml 10u x 5p Base/Tapa - DA7 | G36: 20,6x13,8x3,3cm | H36: 14064
B37: PLATOS ALUMINIO
B38: 0061DAR00041 | C38: Q510850CY | D38: Caja | E38: 100 | F38: Plato Redondo Profundo 28oz-850ml Con Tapa - DR8 | G38: 21.1 x 4,5 cm | H38: 17553
B39: FLANERA ALUMINIO
B40: 0061DAR00042 | C40: Q540100CY | D40: Caja | E40: 500 | F40: Flanera Redonda Prof. Chico 9cm (3,5oz)Sin Tapa | G40: 9,1 x 2,8 cm | H40: 24441
B41: BANDEJAS CON TAPA CRISTAL
B42: 0061DAR00015 | C42: Q501600 | D42: Caja | E42: 500 | F42: BANDEJA ALUMINIO DA6-16oz (480CC) simil F50 | G42: 12,7x15,2x5,1cm | H42: =_xlfn.XLOOKUP(B42,lista!A:A,lista!C:C,0,0) -> 72335
B43: 0061DART0002 | C43: D001600T | D43: Caja | E43: 500 | F43: TAPA CRISTAL PARA BANDEJA ALUMINIO DA6-16oz | G43: 14,0 x 11,5 cm | H43: 42224
B44: 0061DAR00016 | C44: Q502400 | D44: Caja | E44: 500 | F44: BANDEJA ALUMINIO DA7-24oz (720CC) simil F75 | G44: 14,0x19,1x5,1cm | H44: =_xlfn.XLOOKUP(B44,lista!A:A,lista!C:C,0,0) -> 94342
B45: 0061DART0004 | C45: D002300T | D45: Caja | E45: 500 | F45: TAPA CRISTAL PARA BANDEJA ALUMINIO DA7-24oz | G45: 17,9 x 12,8 cm | H45: 72898
B46: 0061DAR00017 | C46: Q502800 | D46: Caja | E46: 250 | F46: BANDEJA ALUMINIO DA8-28oz (840CC) simil F100 | G46: 16,2x22,2x5,1cm | H46: =_xlfn.XLOOKUP(B46,lista!A:A,lista!C:C,0,0) -> 58920
B47: 0061DART0007 | C47: D003200T | D47: Caja | E47: 500 | F47: TAPA CRISTAL PARA BANDEJA ALUMINIO DA8-28oz | G47: 21,5 x 15,0 cm | H47: 80150
B48: 0061DAR00018 | C48: Q506400 | D48: Caja | E48: 100 | F48: BANDEJA ALUMINIO DA9-64oz (1900CC) simil F200 | G48: 21,8x31,5x4,7 cm | H48: 58108
B49: 0061DART0006 | C49: D006400T | D49: Caja | E49: 100 | F49: TAPA CRISTAL BANDEJA ALUMINIO DA9-64oz | G49: 30,7 x 20,8 cm | H49: 45116
B50: 0061DAR0005 | C50: Q5010400 | D50: Caja | E50: 100 | F50: BANDEJA ALUMINIO RECTANGULAR 104oz | G50: 26,6x32,5x5,7cm | H50: =_xlfn.XLOOKUP(B50,lista!A:A,lista!C:C,0,0) -> 73505
B51: 0061DART0001 | C51: D0010400T | D51: Caja | E51: 100 | F51: TAPA CRISTAL P/BANDEJA ALUMINIO RECTANG. 104oz | G51: 31,6 x 25,8 cm | H51: 58252
B52: FUENTE DE ALUMINIO Y TAPA CRISTAL
B53: 0062DAR0030 | C53: Q504500 | D53: Caja | E53: 200 | F53: FUENTE REDONDA 23 CM (45oz/1350cc) SIMIL P30 | G53: 23,0 x 4,9 cm | H53: =_xlfn.XLOOKUP(B53,lista!A:A,lista!C:C,0,0) -> 56910
B54: 0061DART0005 | C54: D102200T | D54: Caja | E54: 200 | F54: TAPA CRISTAL FUENTE REDONDA 23CM (45oz) | G54: 22,6 cm diam | H54: 37234
B55: LOS PRECIOS SON MAS IVA

Sheet Línea Vajilla
B2: LISTA DE PRECIOS de 26 DE OCTUBRE 2026 (B18)
C3: COMPAÑÍA LA PILARICA S. A. - DARNEL WWW.DARNELGROUP.COM
B4: CODIGO PILARICA | C4: CODIGO DARNEL | D4: U/M | E4: C/U | F4: DESCRIPCION | G4: COMENTARIO | H4: PRECIO BULTO $
B5: CUBIERTOS DARNEL BISTROT
B6: 0041DAR00001 | C6: D91202000 | D6: Caja | E6: 1000 | F6: DARNEL TENEDOR BISTROT CRISTAL 50PX20u | H6: 49893
B7: 0041DAR00005 | C7: D91202001 | D7: Caja | E7: 1000 | F7: DARNEL TENEDOR BISTROT BLANCO 50PX20U | H7: 51809
B8: 0041DAR00006 | C8: D91202099P | D8: Caja | E8: 240 | F8: DARNEL TENEDOR BISTROT NEGRO 12PX20U | H8: 12837
B9: 0041DAR00002 | C9: D92202000 | D9: Caja | E9: 1000 | F9: DARNEL CUCHILLO BISTROT CRISTAL 50PX20U | H9: 46744
B10: 0041DAR00007 | C10: D92202001 | D10: Caja | E10: 1000 | F10: DARNEL CUCHILLO BISTROT BLANCO 50PX20U | H10: 47588
B11: 0041DAR00008 | C11: D92202099P | D11: Caja | E11: 240 | F11: DARNEL CUCHILLO BISTROT NEGRO 12PX20U | H11: 11960
B12: 0041DAR00003 | C12: D93202000 | D12: Caja | E12: 1000 | F12: DARNEL CUCHARA DULCERA BIS. CRISTAL 50PX20U | H12: 40577
B13: 0041DAR00004 | C13: D94202000 | D13: Caja | E13: 1000 | F13: DARNEL CUCHARA SOPERA BIS.CRISTAL 50PX20U | H13: 56710
B14: 0041DAR00010 | C14: D94202001 | D14: Caja | E14: 1000 | F14: DARNEL CUCHARA SOPERA BIS BLANCA 50PX20U | H14: 58964
B15: CUBIERTOS TAMI
B16: 0041TAM00010 | C16: D81102001 | D16: Caja | E16: 1000 | F16: TAMI TENEDOR BLANCO 50PX20U | H16: 29253
B17: 0041TAM00011 | C17: D81110001 | D17: Caja | E17: 1000 | F17: TAMI TENEDOR BLANCO 10PX100U | H17: 26445
B18: 0041TAM00012 | C18: D82102001 | D18: Caja | E18: 1000 | F18: TAMI CUCHILLO BLANCO 50PX20U | H18: 26314
B19: 0041TAM00013 | C19: D82110001 | D19: Caja | E19: 1000 | F19: TAMI CUCHILLO BLANCO 10PX100U | H19: 24106
B20: 0041TAM00014 | C20: D83102001 | D20: Caja | E20: 1000 | F20: TAMI CUCHARA DULCERA BLANCA 50PX20U | H20: 25862
B21: 0041TAM00015 | C21: D83110001 | D21: Caja | E21: 1000 | F21: TAMI CUCHARA DULCERA BLANCA 10PX100U | H21: 23335
B22: 0041TAM00016 | C22: D84102001 | D22: Caja | E22: 1000 | F22: TAMI CUCHARA SOPERA BLANCA 50PX20U | H22: 38937
B23: 0041TAM00017 | C23: D84110001 | D23: Caja | E23: 1000 | F23: TAMI CUCHARA SOPERA BLANCA 10PX100U | H23: 35502
B24: 0041TAM00018 | C24: D85110001L | D24: Caja | E24: 1000 | F24: TAMI CUCHARITA 11CM BLANCA 10PX100U CMX8 | G24: Multiplo 8 Cajas | H24: 13380
B25: 0041TAM00019 | C25: D87110001L | D25: Caja | E25: 1000 | F25: TAMI TENEDOR 11CM BLANCO 10PX100U CMX8 | G25: Multiplo 8 Cajas | H25: 12351
B26: PLATOS DARNEL CRISTAL Y ROJO
B27: 0042DAR00001 | C27: D550600P | D27: Caja | E27: 180 | F27: DARNEL PLATO 16CM CRISTAL 30PX6U | H27: 60944.163
B28: 0042DAR00002 | C28: D550700AP | D28: Caja | E28: 180 | F28: DARNEL PLATO 18CM CRISTAL 30PX6U | H28: 75307.98
B29: 0042DAR00003 | C29: D550900P | D29: Caja | E29: 180 | F29: DARNEL PLATO 23CM CRISTAL 30PX6U | H29: 114983
B30: 0042DAR00008 | C30: D591532 | D30: Caja | E30: 480 | F30: DARNEL PLATO 15.5CM ROJO 40PX12U | H30: 58199.697
B31: 0042DAR00009 | C31: D592332 | D31: Caja | E31: 480 | F31: DARNEL PLATO 23CM ROJO 40PX12U | H31: 126190
B32: PLATOS TAMI BLANCO
B33: 0042TAM00004 | C33: D571501 | D33: Caja | E33: 1000 | F33: TAMI PLATO 15.5CM BLANCO 50PX20U | H33: 75975
B34: 0042TAM00005 | C34: D571801 | D34: Caja | E34: 1000 | F34: TAMI PLATO 18CM BLANCO 50PX20U | H34: 104557
B35: 0042TAM00006 | C35: D572301 | D35: Caja | E35: 500 | F35: TAMI PLATO 23CM BLANCO 25PX20U | H35: 78960
B36: 0042TAM00007 | C36: D572601 | D36: Caja | E36: 500 | F36: TAMI PLATO 26CM BLANCO 25PX20P | H36: 104779
B37: PLATOS TAMI COLORES EN PACK
B38: 0042DAR50015 | C38: D591588 | D38: Caja | E38: 480 | F38: PLATO TAMI COLOR 15.5CM SURTIDO PQX12 CJX480 | H38: =_xlfn.XLOOKUP(B38,lista!A:A,lista!C:C,0,0) -> 69125
B39: VASOS MURANO
B40: 0043DAR00001 | C40: D6401500P | D40: Caja | E40: 625 | F40: DARNEL VASO MURANO 1.5OZ CR.25Px25U | H40: 36908
B41: 0043DAR00002 | C41: D640300P | D41: Caja | E41: 300 | F41: DARNEL VASO MURANO 3OZ CR.25Px12U | H41: 24509
B42: 0043DAR00003 | C42: D640700P | D42: Caja | E42: 180 | F42: DARNEL VASO MURANO 7OZ CR.15Px12U | H42: 26330
B43: 0043DAR00004 | C43: D640900P | D43: Caja | E43: 180 | F43: DARNEL VASO MURANO 9OZ CR.15PX12U | H43: 34487
B44: 0043DAR00007 | C44: D641200P | D44: Caja | E44: 180 | F44: DARNEL VASO MURANO 12OZ CR.15P12U | H44: 43968
B45: VASOS BICOLOR ROJO Y MIX COLORES (AZUL-ROJO-VERDE-AMARILLO)
B46: 0043DAR00010 | C46: D610788 | D46: Caja | E46: 480 | F46: DARNEL VASO BICOLOR MIX COLOR 7 OZ 40PX12U | H46: 49938
B47: 0043DAR00011 | C47: D611232 | D47: Caja | E47: 480 | F47: DARNEL VASO BICOLOR ROJOS 12 OZ 40PX12U | H47: 77132
B48: 0043DAR00012 | C48: D611288 | D48: Caja | E48: 480 | F48: DARNEL VASO BICOLOR MIX COLOR 12 OZ 40PX12U | H48: 78953
B49: PACK VASOS BICOLOR
B50: 0043DAR70007 | C50: D610712 | D50: Caja | E50: 480 | F50: VASO PLASTICO COLOR 7oz AMARILLO Paq. 12u. | G50: Nuevo | H50: 48148.112
B51: 0043DAR70008 | C51: D610732 | D51: Caja | E51: 480 | F51: VASO PLASTICO COLOR 7oz ROJO Paq. 12u. | G51: Nuevo | H51: 47322.093
B52: 0043DAR70009 | C52: D610752 | D52: Caja | E52: 480 | F52: VASO PLASTICO COLOR 7oz AZUL Paq. 12u. | G52: Nuevo | H52: 51000.326
B53: 0043DAR70010 | C53: D610762 | D53: Caja | E53: 480 | F53: VASO PLASTICO COLOR 7oz VERDE Paq. 12u. | G53: Nuevo | H53: 50388.836
B54: VAJILLA DESCARTABLE BIODEGRADABLE
B55: 0041TAMB0001 | C55: DB81102003 | D55: Caja | E55: 1000 | F55: TAMI TENEDOR NATURAL BIO 50P x 20u. | G55: Nuevo | H55: 35303.435
B56: 0041TAMB0002 | C56: DB82102003 | D56: Caja | E56: 1000 | F56: TAMI CUCHILLO NATURAL BIO 50P x 20u. | G56: Nuevo | H56: 32390.41
B57: 0041TAMB0003 | C57: DB83102003 | D57: Caja | E57: 1000 | F57: TAMI CUCHARA DULCERA NATURAL BIO 50P x 20u. | G57: Nuevo | H57: 31579.594
B58: CUBIERTOS ENSOBRADOS
B59: 0041CUE00012 | D59: Caja | E59: 1000 | F59: CUCHILLO Y TENEDOR CRISTAL (Ensobrado) | G59: 500 Conjuntos | H59: =_xlfn.XLOOKUP(B59,lista!A:A,lista!C:C,0,0) -> 78164
B60: COPAS
B61: 0044DAR00005 | C61: D720500F | D61: Caja | E61: 600 | F61: DARNEL COPA VENECIA FLEX 5oz (Copa y Pie) | G61: 12paq x 50u | H61: 161545
B62: 0044DAR00006 | C62: D720800F | D62: Caja | E62: 600 | F62: DARNEL COPA VENECIA FLEX 8oz (Copa y Pie) | G62: 12paq x 50u | H62: 227004
B63: 0044DAR00007 | C63: D721200F | D63: Caja | E63: 600 | F63: DARNEL COPA VENECIA FLEX 12 OZ (Copia y Pie) | G63: 12paq x 50u | H63: 253939
B64: LOS PRECIOS SON MAS IVA

Sheet Pote Safety - Roaster
B2: LISTA DE PRECIOS de 26 DE OCTUBRE 2026 (B18)
C3: COMPAÑÍA LA PILARICA S. A. - DARNEL WWW.DARNELGROUP.COM
B4: CODIGO PILARICA | C4: CODIGO DARNEL | D4: U/M | E4: C/U | F4: DESCRIPCION | G4: COMENTARIO | H4: PRECIO BULTO $
B5: POTE SAFETYPLUS CUADRADO CON EVIDENCIA
F6: CONSULTAR LISTA DARNEL ARGENTINA (ZAPLAST)
B7: SAFETYPLUS CUADRADO CON EVIDENCIA DE APERTURA
B8: 0052DARSAC08 | C8: DC07150800 | D8: caja | E8: 200 | F8: SAFETYPLUS DELI CUADRADO 8oz C/T EVID. APERT. | H8: 60097
B9: 0052DARSAC12 | C9: DC07151200 | D9: caja | E9: 200 | F9: SAFETYPLUS DELI CUADRADO 12oz C/T EVID. APERT. | H9: 64199
B10: 0052DARSAC16 | C10: DC07151600 | D10: caja | E10: 200 | F10: SAFETYPLUS DELI CUADRADO 16oz C/T EVID. APERT. | H10: 69674
B11: 0052DARSAC24 | C11: DC07152400 | D11: caja | E11: 200 | F11: SAFETYPLUS DELI CUADRADO 24oz C/T EVID. APERT. | H11: 112981
B12: 0052DARSAC32 | C12: DC07153200 | D12: caja | E12: 200 | F12: SAFETYPLUS DELI CUADRADO 32oz C/T EVID. APERT. | H12: 113330
B13: BOWLS SAFETYPLUS CUADRADO CRISTAL CON EVIDENCIA APERTURA
B14: 0052DARSAF12 | C14: DC771200S | D14: caja | E14: 200 | F14: SAFETYPLUS BOWLS Cristal 12oz T/EVID. APERT (355ml) | H14: 62494
B15: 0052DARSAF32 | C15: DC773200S | D15: caja | E15: 200 | F15: SAFETYPLUS BOWLS Cristal 32oz T/EVID. APERT (473ml) | H15: 126104
B16: 0052DARSAF48 | C16: DC774800S | D16: caja | E16: 100 | F16: SAFETYPLUS BOWLS Cristal 48oz T/EVID. APERT. (945ml) | H16: 87286.54
B17: BOWLS SAFETYPLUS REDONDOS CRISTAL CON EVIDENCIA APERTURA
B18: 0052DARST024 | C18: DC0732400 | D18: caja | E18: 100 | F18: CONTEN REDONDO SAFETY TUB 24oz T/EVID APERT (720ml) | G18: Diam 15,5cm | H18: 70664
B19: 0052DARST032 | C19: DC0733200 | D19: caja | E19: 100 | F19: CONTEN REDONDO SAFETY TUB 32oz T/EVID APERT (960ml) | G19: Diam 15,5cm | H19: 76682
B20: 0052DARST048 | C20: DC0734800 | D20: caja | E20: 50 | F20: CONTEN REDONDO SAFETY TUB 48oz T/EVID APERT (1440ml) | G20: Diam 15,5cm | H20: 44692
B21: 0052DARST064 | C21: DC0736400 | D21: caja | E21: 50 | F21: CONTEN REDONDO SAFETY TUB 64oz T/EVID APERT (1920ml) | G21: Diam 15,5cm | H21: 52889
B22: 0052DARST072 | C22: DC0737200 | D22: caja | E22: 50 | F22: CONTEN REDONDO SAFETY TUB 72oz T/EVID APERT (2160ml) | G22: Diam 15,5cm | H22: 56698
B23: 0052DARW00024 | D23: caja | E23: 200 | F23: SAFETY BOWLS RESQ 24oz CRISTAL CON TAPA | G23: paq100 x 200u | H23: 110165
B24: BANDEJAS POLIPROPILENO CON TAPA PARA POLLO
B25: 0052DARPO0015 | D25: caja | E25: 170 | F25: CONTEN ROASTER PROTOGO NEGRO con T/TRANSP. GRANDE | G25: 21 x 16 x 14cm | H25: 114493
B26: 0052DARPO0020 | D26: caja | E26: 170 | F26: CONTEN ROASTER PROTOGO NEGRO con T/TRANSP. CHICO | G26: 21 x 16 x 9cm | H26: 111822
B27: LOS PRECIOS SON MAS IVA

Sheet Potes 
B2: LISTA DE PRECIOS de 26 DE OCTUBRE 2026 (B18)
C3: COMPAÑÍA LA PILARICA S. A. - DARNEL WWW.DARNELGROUP.COM
B4: CODIGO PILARICA | C4: CODIGO DARNEL | D4: U/M | E4: C/U | F4: DESCRIPCION | G4: COMENTARIO | H4: PRECIO BULTO $
B5: POTES SOUFFLE "DEGUSTACION" para SALSAS
B6: 0052DAR00011 | C6: D631599PN | D6: caj | E6: 2500 | F6: DARNEL POTE SOUFFLE 1.5 OZ NEGRA 25PX100U | H6: 82165
B7: 0052DAR00012 | C7: D632099A | D7: caj | E7: 2500 | F7: DARNEL POTE SOUFFLE 2 OZ NEGRA 25PX100U | H7: 87910
B8: 0052DAR00013 | C8: D632599A | D8: caj | E8: 2500 | F8: DARNEL POTE SOUFFLE 2.5 OZ NEGRA 25PX100U | H8: 101516
B9: 0052DAR00010 | C9: D631500TN | D9: caj | E9: 2500 | F9: TAPA CRISTAL P/POTE SOUFFLE 1.5oz-2oz-2.5oz) 25PX100U | H9: 68654
B10: 0052DAR00015 | C10: D631099A | D10: caj | E10: 2500 | F10: DARNEL POTE SOUFFLE 1 OZ NEGRA 25PX100U | H10: 49216
B11: 0052DAR00016 | C11: D630500TN | D11: caj | E11: 2500 | F11: TAPA CRISTAL PARA POTE SOUFFLE DE 1 OZ 25PX100U | H11: 48871
B12: 0052DAR00017 | C12: D634099A | D12: caj | E12: 2500 | F12: DARNEL POTE SOUFFLE 4 oz Negro 25Px100U | H12: 186817
B13: 0052DAR00018 | C13: D635599A | D13: caj | E13: 2500 | F13: DARNEL POTE SOUFFLE 5,5 oz Negro 25Px100U | H13: 212730
B14: 0052DAR00019 | C14: D633000TN | D14: caj | E14: 2500 | F14: TAPA CRISTAL PARA POTE SOUFFLE DE 4,0 y 5,5oz 25Px100U | H14: 107344
B15: LINEA PETITE - DEGUSTACION PARA CATERING
B16: 0041DAR00022 | C16: DC0680300 | D16: caj | E16: 288 | F16: DARNEL CUCHARA DEGUS PETITE CRISTAL 12PX24U | H16: 29599
B17: 0041DAR00023 | C17: DC0680301 | D17: caj | E17: 288 | F17: DARNEL CUCHARA DEGUS PETITE BLANCA 12PX24U | H17: 33102
B18: 0041DAR00024 | C18: DC0680399 | D18: caj | E18: 288 | F18: DARNEL CUCHARA DEGUS PETITE NEGRA 12PX24U | H18: 35002
B19: 0042DAR00019 | C19: DC0680200 | D19: caj | E19: 288 | F19: DARNEL PLATO CUADRADO PETITE CRISTAL 12PX24U | H19: 40252
B20: 0042DAR00020 | C20: DC0680201 | D20: caj | E20: 288 | F20: DARNEL PLATO CUADRADO PETITE BLANCO 12PX24U | H20: 44007
B21: 0042DAR00021 | C21: DC0680299 | D21: caj | E21: 288 | F21: DARNEL PLATO CUADRADO PETITE NEGRO 12PX24U | H21: 42507
B22: 0043DAR00015 | C22: DC0680100 | D22: caj | E22: 288 | F22: DARNEL COPA CUADRADA PETITE CRISTAL 12PX24U | H22: 45987
B23: 0043DAR00016 | C23: DC0680101 | D23: caj | E23: 288 | F23: DARNEL COPA CUADRADA PETITE NEGRA 12PX24U | H23: 47842
B24: 0043DAR00017 | C24: DC0680199 | D24: caj | E24: 288 | F24: DARNEL COPA CUADRADA PETITE BLANCA 12PX24U | H24: 47382
B25: 0043DAR00025 | C25: DC0680799 | D25: caj | E25: 144 | F25: DARNEL COPA TRIANG. PETITE NEGRA 6 OZ 12PX12U | H25: 67640
B26: POTE SAFETYPLUS CUADRADO NEGRO
B27: 0052DARR0012 | C27: DC07151299 | D27: caja | E27: 200 | F27: SAFETYPLUS CUADRADO 12oz Negro C/Tapa PAQX100 Un. | G27: Nuevo | H27: 52824
B28: 0052DARR0024 | C28: DC07152499 | D28: caja | E28: 200 | F28: SAFETYPLUS CUADRADO 24oz Negro C/Tapa PAQX100 Un. | G28: Nuevo | H28: 93797
B29: 0052DARRB0016 | C29: DC07151699B | D29: caja | E29: 200 | F29: SAFETYPLUS BAJO RESQ 16oz NEGRO CON TAPA | G29: Nuevo | H29: 93373
B30: BOWLS SAFETYPLUS CUADRADO CRISTAL
B31: 0052DARW00024 | C31: DC772400S | D31: caja | E31: 200 | F31: SAFETYUPLUS BOWL 24oz CRISTAL C/Tapa PAQX100 Un. | G31: Nuevo | H31: 100150
B32: 0052DARSAB001 | C32: DC770800S | D32: caja | E32: 200 | F32: SAFETYPLUS BOWL CRISTAL 8 OZ CON TAPA | H32: 54453
B33: 0052DARSAB003 | C33: DC771600S | D33: caja | E33: 200 | F33: SAFETYPLUS BOWL CRISTAL 16 OZ CON TAPA | H33: 67230
B34: POTES TAPA BISAGRA DARNEL
B35: 0052DAR00005 | C35: DC07102500V | D35: caj | E35: 200 | F35: DARNEL ROUND MINI PACK HV S (240CC) | H35: 47370
B36: 0052DAR00006 | C36: DC07103500V | D36: caj | E36: 200 | F36: DARNEL ROUND MINI PACK HV M (390CC) | H36: 50512
B37: 0052DAR00007 | C37: DC07105000V | D37: caj | E37: 200 | F37: DARNEL ROUND MINI PACK HV L (500CC) | H37: 51867
B38: LOS PRECIOS SON MAS IVA

Sheet Ensaladeras y Blister
B2: LISTA DE PRECIOS de 26 DE OCTUBRE 2026 (B18)
C3: COMPAÑÍA LA PILARICA S. A. - DARNEL WWW.DARNELGROUP.COM
B4: CODIGO PILARICA | C4: CODIGO DARNEL | D4: U/M | E4: C/U | F4: DESCRIPCION | G4: COMENTARIO | H4: PRECIO BULTO $
B5: BANDEJA CON DIVISIONES
B6: 0054DARB0005 | C6: D152505499N | D6: caja | E6: 50 | F6: BANDEJA BASE NEGRA REDONDA C/Tapa Cristal 5 DIVIS. | G6: 250mm diam. | H6: 66207
B7: 0052DAR80004 | C7: D152505400N | D7: caj | E7: 50 | F7: CONTENEDOR 4 DIV RESQ CRISTAL CON TAPA X50 | G7: Nuevo | H7: 65186
B8: 0053DAR00026 | C8: D7724300SP | D8: caj | E8: 100 | F8: DARNEL CONTENEDOR 3 DIVISIONES 24 oz C/TAPA | H8: 63863
B9: 0052DAR30003 | C9: D7113400D | D9: caj | E9: 300 | F9: CONTENEDOR OVALADO CRISTAL 3 DIVIS. | H9: 95894
B10: 0053DART0001 | C10: D7113400T | D10: caja | E10: 300 | F10: TAPA CONTENEDOR OVALADO CON Y SIN DIVISIONES | H10: 73383
B11: CONTENEDORES
B12: 0052DAR00001 | C12: DC07101200R | D12: caj | E12: 300 | F12: DARNEL MINI PACK REDONDO CH C/T | H12: 23598
B13: 0052DAR00008 | C13: D71181100 | D13: caj | E13: 100 | F13: DARNEL &CONT ROUND PACK PANDO CJx100 | H13: 47028
B14: CONTENEDORES DOBLE USO BASE Y TAPA
B15: 0052DAR00024 | C15: D772400 | D15: caj | E15: 500 | F15: CONTENEDOR DOBLE USO CRISTAL 24oz | H15: 112652
B16: 0052DAR00028 | C16: D770800S | D16: caj | E16: 200 | F16: CONTENEDOR DOBLE USO CRISTAL 8oz | H16: 39621
B17: 0052DAR00048 | C17: D774800 | D17: caj | E17: 500 | F17: CONTENEDOR DOBLE USO CRISTAL 48oz | H17: 165882.72
B18: 0052DAR00124 | C18: D772499SP | D18: caj | E18: 100 | F18: CONTENEDOR DOBLE USO NEGRO 24oz | H18: 36744
B19: 0052DAR00136 | C19: D773699 | D19: caj | E19: 500 | F19: CONTENEDOR DOBLE USO NEGRO 36oz | H19: 133059
B20: 0052DAR00137 | D20: caj | F20: CONTENEDOR DOBLE USO NEGRO 36oz Con TAPA | H20: 60620
B21: CONTENEDOR ENSALADERAS CRISTAL LINEA TOKIO
B22: 0052DARB0001 | C22: D770800Y | D22: caja | E22: 200 | F22: BOWL TOKYO S CRISTAL PAQ X100 CJ X200 | G22: Nuevo | H22: 25761.981
B23: 0052DARBN100 | C23: D770899YPS | D23: caja | E23: 200 | F23: BOWL TOKYO S NEGRO PAQ X100 CJ X200 | G23: Nuevo | H23: 23431.254
B24: 0052DARBT0001 | C24: D771600T | D24: caja | E24: 500 | F24: TAPA CRISTAL 15.5 CM TOKYO/DOBLEUSO PAQ X50 Un. | G24: Nuevo | H24: 65542
B25: CONTENEDOR SELLO PLUS (Tapa Bisagra PLANA) PET
B26: 0053DAR00006 | C26: D750800 | D26: caj | E26: 200 | F26: DARNEL SELLO PLUS 8 OZ TAPA PLANA | H26: 44599
B27: 0053DAR00001 | C27: D751200 | D27: caj | E27: 200 | F27: DARNEL SELLO PLUS 12 OZ TAPA PLANA | H27: 48459
B28: 0053DAR00002 | C28: D751600 | D28: caj | E28: 200 | F28: DARNEL SELLO PLUS 16 OZ TAPA PLANA | H28: 51302
B29: 0053DAR00124 | C29: D752400 | D29: caj | E29: 200 | F29: DARNEL SELLO PLUS 24 OZ TAPA PLANA | H29: 90373
B30: 0053DAR00003 | C30: D753200 | D30: caj | E30: 200 | F30: DARNEL SELLO PLUS 32 OZ TAPA PLANA | H30: 90192
B31: 0053DAR00004 | C31: D754800 | D31: caj | E31: 200 | F31: DARNEL SELLO PLUS 48 OZ TAPA PLANA | H31: 127118
B32: 0053DAR00005 | C32: D756400 | D32: caj | E32: 200 | F32: DARNEL SELLO PLUS 64 OZ TAPA PLANA | H32: 140265
B33: CONTENEDOR SELLO PLUS (Tapa Bisagra MEDIA) PET
B34: 0053DAR10006 | C34: D750800F | D34: caj | E34: 200 | F34: DARNEL SELLO PLUS 8oz TAPA MEDIA | H34: 49235
B35: 0053DAR00051 | C35: D751200F | D35: caj | E35: 200 | F35: DARNEL SELLO PLUS 12 OZ TAPA MEDIA | H35: 50506
B36: CONTENEDOR SELLO PLUS (Tapa Bisagra ALTA) PET
B37: 0053DAR20002 | C37: D751600G | D37: caj | E37: 200 | F37: DARNEL SELLO PLUS 16oz TAPA ALTA | H37: 55882
B38: CONTENEDOR SELLO PLUS (Tapa Bisagra) CON DIVISIONES en PET
B39: 0053DAR00324 | C39: D7524200 | D39: caj | E39: 200 | F39: SELLO PLUS 24oz TRANSP. TAPA PLANA 2 DIV. | H39: 90388
B40: 0053DAR00424 | C40: D7524300 | D40: caj | E40: 200 | F40: SELLO PLUS 24oz TRANSP. TAPA PLANA 3 DIV. | H40: 91232
B41: 0053DAR00524 | C41: D7524400 | D41: caj | E41: 200 | F41: SELLO PLUS 24oz TRANSP.TAPA PLANA 4 DIV | H41: 90388
B42: CONTENEDOR DOBLE USO (CONJUNTO BASE Y TAPA) en PET
B43: 0053DAR00008 | C43: D771200S | D43: caj | E43: 200 | F43: DARNEL CONTENEDOR DOBLE USO 12 OZ C/TAPA CRISTAL | H43: 42030
B44: 0053DAR00009 | C44: D773200SP | D44: caj | E44: 100 | F44: DARNEL CONTENEDOR DOBLE USO 32 OZ C/TAPA CRISTAL | H44: 42219
B45: 0053DAR00010 | C45: D774800SP | D45: caj | E45: 100 | F45: DARNEL CONTENEDOR DOBLE USO 48 OZ C/TAPA CRISTAL | H45: 64683
B46: 0053DART0024 | C46: D772400T | D46: caj | E46: 500 | F46: TAPA CRISTAL P/CONTENEDOR DOBLE 24 Y 32oZ | H46: 86102
B47: 0053DART0036 | C47: D774800T | D47: caj | E47: 500 | F47: TAPA CRISTAL P/CONTENEDOR DOBLE 36 Y 48oz | H47: 162415
B48: CONTENEDOR MULTI ALTA VISIBILIDAD CRISTAL
B49: 0053DAR00011 | C49: BV080D00CS | D49: caj | E49: 50 | F49: DARNEL MULTI ALTA VIS. GDE. | H49: 36584
B50: 0053DAR00012 | C50: BV080S00CS | D50: caj | E50: 50 | F50: DARNEL MULTI ALTA VIS. CH. | H50: 29665
B51: CONTENEDOR TWIST CRISTAL
B52: 0053DAR00015 | C52: D7710800 | D52: caj | E52: 200 | F52: DARNEL TWIST 8 OZ CON TAPA | H52: 53271
B53: 0053DAR00016 | C53: D7712400 | D53: caj | E53: 100 | F53: DARNEL TWIST 24 OZ CON TAPA | H53: 54763
B54: 0053DAR00017 | C54: D7713200 | D54: caj | E54: 100 | F54: DARNEL TWIST 32 OZ CON TAPA | H54: 65961
B55: CONTENEDOR HUEVOS CODORNIZ CRISTAL CON TAPA
B56: 0053DAR00030 | C56: D362400 | D56: caj | E56: 500 | F56: DARNEL PORTAHUEVO CODORNIZ CRISTAL p/24 Und. | H56: 235416
B57: LOS PRECIOS SON MAS IVA

Sheet Panaderia
B2: LISTA DE PRECIOS de 26 DE OCTUBRE 2026 (B18)
C3: COMPAÑÍA LA PILARICA S. A. - DARNEL WWW.DARNELGROUP.COM
B4: CODIGO PILARICA | C4: CODIGO DARNEL | D4: U/M | E4: C/U | F4: DESCRIPCION | G4: COMENTARIO | H4: PRECIO BULTO $
B5: CONTENEDORES PARA CUPCAKE
B6: 0052DAR30006 | C6: D720VN600V | D6: Caja | E6: 200 | F6: CONTENEDOR VISUALPACK P/CUPCAKE 6 UNID. | H6: 110967
B7: CONTENEDORES FORMA CORAZON
B8: 0052DARC0001 | C8: D76080400Q | D8: Caja | E8: 1000 | F8: CONTENEDOR CORAZON 10,7 X 7,8 CM CON TAPA | G8: Nuevo | H8: 126059.87
B9: 0052DARC0002 | C9: D76131100Q | D9: Caja | E9: 750 | F9: CONTENEDOR CORAZON 12,9 X 10,9 CM CON TAPA | G9: Nuevo | H9: 149564.31
B10: CONTENEDORES PARA PORCION DE TORTA
B11: 0053DAR00028 | C11: D76110500 | D11: Caja | E11: 200 | F11: DARNEL TRIANGULO PARA PORCION TORTA 5CM (BAJA) | H11: 34148
B12: 0053DAR00029 | C12: D76110700 | D12: Caja | E12: 200 | F12: DARNEL TRIANGULO PARA PORCION TORTA 7CM (ALTA) | H12: 34164
B13: CONTENEDORES PARA SANDWICH
B14: 0053DARP0001 | C14: DC0780100 | D14: Caja | E14: 200 | F14: PORTA SANDWICH CRISTAL RESQ | H14: 54989
B15: CONTENEDORES VISUAL PACK (Blister)
B16: 0053DAR00024 | C16: D720V050500TB | D16: Caja | E16: 200 | F16: DARNEL VISUAL PACK MIAMI 5x5 C/T BAJA | H16: 50112
B17: 0053DAR00022 | C17: D720V060600 | D17: Caja | E17: 200 | F17: DARNEL VISUAL PACK MIAMI 6x6in | H17: 64247
B18: 0053DAR00023 | C18: D720V120400 | D18: Caja | E18: 200 | F18: DARNEL VISUAL PACK MIAMI 12x4 1/4 | H18: 105372
B19: 0053DAR00021 | C19: D720VX100 | D19: Caja | E19: 100 | F19: DARNEL VISUAL PACK +VX-1 C/TAPA | H19: 88988
B20: 0053DAR00025 | C20: D720VO100TA | D20: Caja | E20: 200 | F20: DARNEL VISUAL PACK VO-1 C/T ALTA | H20: 71948
B21: 0053DAR00018 | C21: DC072VL100TA | D21: Caja | E21: 300 | F21: DARNEL VISUAL PACK VL-1 C/T ALTA | H21: 99368
B22: 0053DAR00019 | C22: D720VI100TB | D22: Caja | E22: 200 | F22: DARNEL VISUAL PACK VI-1 C/T BAJA | H22: 36624
B23: 0053DAR00020 | C23: D720VI100TA | D23: Caja | E23: 200 | F23: DARNEL VISUAL PACK VI-1 C/T ALTA | H23: 40063
B24: TORTERAS
B25: 0054DARB0005 | C25: D152505499N | D25: Caja | E25: 50 | F25: BANDEJA REDONDA NEGRA 4 DIV. CON TAPA CRISTAL | H25: 66207
B26: 0054DARB0008 | C26: D15170899V | D26: caja | E26: 50 | F26: BASE NEGRA 17 cm /DOMO CIRCULAR 8 cm | H26: 31022
B27: 0054DARB0010 | C27: D15171099V | D27: caja | E27: 50 | F27: BASE NEGRA 17 cm /DOMO CIRCULAR 10 cm | H27: 33339
B28: 0054DARB0015 | C28: D15150899D | D28: caja | E28: 50 | F28: TORTERA 15,5cm x 8cm ALTA BASE NEGRA (Conjunto) | G28: Conjuntos | H28: 29121.677
B29: 0054DARB0016 | C29: D15180899VD | D29: caja | E29: 50 | F29: TORTERA 18,5cm x 8cm ALTA BASE NEGRA (Conjunto) | G29: Conjuntos | H29: 32752
B30: 0054DARB0018 | C30: D15180599VD | D30: caja | E30: 50 | F30: BASE NEGRA TORTERA 18,5cm x 5cm Base HONDA | H30: 31553
B31: 0054DARB1008 | C31: D16350899V | D31: caja | E31: 50 | F31: BASE 20.5cm X 12cm ALTURA 8cm Visualdomo RECT Resq NEGRA X50 | G31: Nuevo | H31: 40255
B32: 0054DARB1010 | C32: D16351099V | D32: caja | E32: 50 | F32: BASE 20.5cm x 12cm ALTURA 10cm Visualdomo RECT Resq NEGRO X50 | G32: Nuevo | H32: 40614
B33: 0054DARB2012 | C33: D16491299V | D33: caja | E33: 50 | F33: BASE RECT 21/16cm NEGRA C/DOMO 12 CRISTAL ALTA Visibilidad X50 | G33: Nuevo | H33: 62747
B34: 0054DARB0025 | C34: D16491099V | D34: caja | E34: 50 | F34: TORTERA RECTANG 26x20x10cm Base Negra-Tapa Cristal | G34: Conjuntos | H34: 58887
B35: 0052DAR30003 | C35: D7113400D | D35: caja | E35: 300 | F35: CONTENEDOR OVALADO CRISTAL 3 DIV. | H35: 87176
B36: 0053DART0001 | C36: D7113400T | D36: caja | E36: 300 | F36: TAPA CONTENEDOR OVALADO CON Y SIN DIV | H36: 73382
B37: 0052DAR30006 | C37: D720VN600V | D37: caja | E37: 200 | F37: CONTENEDOR VISUALPACK P/CUPCAKE 6 UNID. | H37: =_xlfn.XLOOKUP(B37,lista!A:A,lista!C:C,0,0) -> 105683
B38: 0053DARV0001 | D38: caja | E38: 200 | F38: CONTENEDOR VISUALPACK P/CUPCAKE-MUFFINS INDIVIDUAL | H38: 24989
B39: LOS PRECIOS SON MAS IVA

Sheet Estuches PP

Sheet Frascos-Vasos-Protogo
B2: LISTA DE PRECIOS de 26 DE OCTUBRE 2026 (B18)
C3: COMPAÑÍA LA PILARICA S. A. - DARNEL WWW.DARNELGROUP.COM
B4: CODIGO PILARICA | C4: CODIGO DARNEL | D4: U/M | E4: C/U | F4: DESCRIPCION | G4: COMENTARIO | H4: PRECIO BULTO $
B5: FRASCOS CRISTAL REDONDOS
B6: 0045DAR00300 | C6: DC5003007000 | D6: Caja | E6: 96 | F6: FRASCO REDONDO 300 ML CRISTAL (10oz) | G6: 7,6cm x 8,6cm | H6: 39715.626
B7: 0045DAR00500 | C7: DC5005007000 | D7: Caja | E7: 96 | F7: FRASCO REDONDO 500 ML CRISTAL (16oz) | G7: 7,8cm x 12,9cm | H7: 52073.813
B8: 0045DAR00750 | C8: DC5007507000 | D8: Caja | E8: 96 | F8: FRASCO REDONDO 750 ML CRISTAL (24oz) | G8: 8,8cm x 14,7cm | H8: 73603.512
B9: 0045DAR01000 | C9: DC5010008900 | D9: Caja | E9: 48 | F9: FRASCO REDONDO 1000 ML CRISTAL (32oz) | G9: 9,9cm x 16,0cm | H9: 51876.177
B10: 0045DAR01500 | C10: DC5015008900 | D10: Caja | E10: 48 | F10: FRASCO REDONDO 1500 ML CRISTAL (48oz) | G10: 11,4cm x 18,2cm | H10: 71187.956
B11: FRASCOS CRISTAL CUADRADOS
B12: 0045DARC0750 | C12: DC5107507000 | D12: Caja | E12: 96 | F12: FRASCO CUADRADO 750 ML CRISTAL (24oz) | G12: 9,1x9,1x12,4cm | H12: 71970.055
B13: 0045DARC1000 | C13: DC5110008900 | D13: Caja | E13: 48 | F13: FRASCO CUADRADO 1000 ML CRISTAL (32oz) | G13: 9,9x9,9x14,0cm | H13: 48768.049
B14: 0045DARC1500 | C14: DC5115011000 | D14: Caja | E14: 48 | F14: FRASCO CUADRADO 1500 ML CRISTAL (48oz) | G14: 11,4x11,4x15,7cm | H14: 75904.202
B15: 0045DARC2000 | C15: DC5120011000 | D15: Caja | E15: 24 | F15: FRASCO CUADRADO 2000 ML CRISTAL (64oz) | G15: 12,4x12,2x18,0cm | H15: 42722.402
B16: 0045DARC3000 | C16: DC5130011000 | D16: Caja | E16: 24 | F16: FRASCO CUADRADO 3000 ML CRISTAL (96oz) | G16: 14,2x14,2x20,3cm | H16: 60041.769
B17: 0045DARC4000 | C17: DC5140011000 | D17: Caja | E17: 24 | F17: FRASCO CUADRADO 4000 ML CRISTAL (128oz) | G17: 15,5x15,5x22,3cm | H17: 84491.25
B18: TAPA NEGRA PARA FRASCOS
B19: 0045DART0750 | C19: DC590701999TC1 | D19: Caja | E19: 96 | F19: TAPA NEGRA FRASCO CUAD 750ml /RED 300-500-750ml | G19: 7,0cm x 1,9cm | H19: 19565
B20: 0045DART1000 | C20: DC59891595TC1 | D20: Caja | E20: 48 | F20: TAPA NEGRA FRASCO CUAD 1000ml /RED 1000-1500ml | G20: 8,9cm x 1,5cm | H20: 17429
B21: 0045DART1501 | C21: DC591101799TC1 | D21: Caja | E21: 24 | F21: TAPA NEGRA Frasco CUAD 1500-2000-3000-4000/RED 2000 | G21: 11,0cm x 1,7cm | H21: 14114
B22: SET FRASCOS
B23: 0045DARSET03 | C23: DC5115011000S | D23: Caja | E23: 6 | F23: SET TRES FRASCOS CUADRADOS 1500 ML C/U | G23: 6 set x 3 unid. | H23: 41648
A24: < | B24: VASOS PET
B25: 0043DAR00029 | C25: D620900N | D25: caja | E25: 300 | F25: VASO PET CRISTAL 9 OZ (266cc) | G25: 25paq x 12un. | H25: 46843
B26: 0043DARRC010 | C26: D621000N | D26: caja | E26: 300 | F26: VASO PET CRISTAL 10 OZ (300cc) | G26: Nuevo | H26: 57460
B27: 0043DAR00030 | C27: D621200N | D27: caja | E27: 300 | F27: VASO PET CRISTAL 12 OZ (360cc) | H27: 60207
B28: 0043DAR00031 | C28: D621600N | D28: caja | E28: 300 | F28: VASO PET CRISTAL 16 OZ (473cc) | G28: 25paq x 12 un. | H28: 71849
B29: 0043DAR00032 | C29: D622000N | D29: caja | E29: 300 | F29: VASO PET CRISTAL 20 OZ (590cc) | G29: 25paq x 12 un. | H29: 73259
B30: 0043DART0006 | C30: D620900NTX | D30: caja | E30: 600 | F30: TAPA PLANA CRISTAL SIN PERF para VASO 9-12-16-20oz | H30: 27478
B31: 0043DART0009 | C31: D620900NT | D31: caja | E31: 600 | F31: TAPA PLANA CRISTAL CON PERF para VASO 9-12-16-20oz | H31: 27478
B32: 0043DART0018 | C32: D620900NTHX | D32: caja | E32: 600 | F32: TAPA DOMO CRISTAL SIN PERF para VASO 9-12-16-20oz | H32: 42304
B33: 0043DART0019 | C33: D620900NTH | D33: caja | E33: 600 | F33: TAPA DOMO CRISTAL CON PERF para VASO 9-12-16-20oz | H33: 42304
B34: CONTENEDORES Y BOWLS ESPUMADOS
B35: 0034DARC0004 | C35: D700401N | D35: caja | E35: 1000 | F35: CONTENEDOR ESPUMADO 4oz BLANCO x 20u | G35: 50p x 20u | H35: 70665
B36: 0034DARC0006 | C36: D700601N | D36: caja | E36: 1000 | F36: CONTENEDOR ESPUMADO 6oz BLANCO x 20u | G36: 50p x 20u | H36: 94230
B37: 0034DARC0008 | C37: D700801N | D37: caja | E37: 1000 | F37: CONTENEDOR ESPUMADO 8oz BLANCO x 20u | G37: 50p x 20u | H37: 115815
B38: 0034DARC0012 | C38: D700121N | D38: caja | E38: 1000 | F38: CONTENEDOR ESPUMADO 12oz BLANCO x 20u | G38: 50p x 20u | H38: 136438
B39: 0034DARC0016 | C39: D701601NL | D39: caja | E39: 500 | F39: CONTENEDOR ESPUMADO 16oz BLANCO x 20u | G39: 25p x 20u | H39: 112503
B40: 0034DARPBE006 | C40: D700601B | D40: caja | E40: 1000 | F40: BOWLS ESPUMADO 6oz BLANCO x 20u. | G40: 50p x 20u | H40: 94666
B41: 0034DARPBE012 | C41: D701201B | D41: caja | E41: 1000 | F41: BOWLS ESPUMADO 12oz BLANCO x 20u. | G41: 50p x 20u | H41: 142960
B42: 0034DARPBE108 | C42: D700801LB | D42: caja | E42: 1000 | F42: BOWLS ESPUMADO BAJO 8oz BLANCO x 20u. | G42: 50p x 20u | H42: 103105
B43: VASO ESPUMADO y TAPAS
B44: 0035DAR00006 | C44: D690601NLA | D44: caja | E44: 2000 | F44: VASO ESPUMADO 6 Oz BLANCO PQX40 CAJ X2000 | G44: Nuevo | H44: =_xlfn.XLOOKUP(B44,lista!A:A,lista!C:C,0,0) -> 143738
B45: 0035DAR00008 | C45: D690801N | D45: caja | E45: 1000 | F45: VASO ESPUMADO 8 Oz BLANCO PQX40 CAJ X2001 | G45: Nuevo | H45: =_xlfn.XLOOKUP(B45,lista!A:A,lista!C:C,0,0) -> 79579
B46: 0035DARBT0006 | C46: D690602TNL | D46: caja | E46: 1000 | F46: TAPA SIN PERF.. p/VASO 6oz y CONTENEDOR 4oz OPAL x 100u | G46: Nuevo | H46: =_xlfn.XLOOKUP(B46,lista!A:A,lista!C:C,0,0) -> 30399
B47: 0035DART0008 | C47: D690802TNL | D47: caja | E47: 1000 | F47: TAPA SIN PERF. p/VASO 8oz y CONTENEDOR 4oz OPAL x 100u | G47: Nuevo | H47: =_xlfn.XLOOKUP(B47,lista!A:A,lista!C:C,0,0) -> 35314
B48: PLATOS ESPUMADOS
B49: 0034DARPWH05 | C49: D5105101NW | D49: caja | E49: 480 | F49: DARNEL PLATO HONDO BLANCO 5oz x 20u. | G49: Nuevo | H49: =_xlfn.XLOOKUP(B49,lista!A:A,lista!C:C,0,0) -> 15646
B50: 0034DARPW0015 | C50: D510601NW | D50: caja | E50: 480 | F50: DARNEL PLATO BLANCO 15,5oz x 20u. | G50: Nuevo | H50: =_xlfn.XLOOKUP(B50,lista!A:A,lista!C:C,0,0) -> 22123
B51: VASOS Y CONTENEDORES TERMICOS BIODEGRADABLE
B52: 0035DARB0006 | C52: D690603N | D52: caja | E52: 1000 | F52: VASO ESPUMADO 6 oz - BIO paq x 20u CAJ x1000 | G52: Nuevo | H52: =_xlfn.XLOOKUP(B52,lista!A:A,lista!C:C,0,0) -> 67392
B53: 0035DARB0008 | C53: D690803N | D53: caja | E53: 1000 | F53: VASO ESPUMADO 8 oz - BIO paq x 20u CAJ x1001 | G53: Nuevo | H53: =_xlfn.XLOOKUP(B53,lista!A:A,lista!C:C,0,0) -> 82298
B54: LINEA PROTOGO (POLIPROPILENO)
B55: 0052DARPR008 | C55: DP4505040899S | D55: caja | E55: 100 | F55: CONTENEDOR Reutiliz. Rectang. Negro (8oz) 12,7 x 10,2cm C/TAPA | G55: Nuevo | H55: 27034
B56: 0052DARPR012 | C56: DP4506051299S | D56: caja | E56: 100 | F56: CONTENEDOR Reutiliz Rectang. Negro (12oz) 15,2 x 12,7cm C/TAPA | G56: Nuevo | H56: 37030
B57: 0052DARPR024 | C57: DP4508062499S | D57: caja | E57: 100 | F57: CONTENEDOR Reutiliz. Rectang. Negro (24oz) 20,3 x 15,2cm C/TAPA | G57: Nuevo | H57: 64691
B58: 0052DARPR200 | C58: DP45100732299S | D58: caja | E58: 100 | F58: CONTENEDOR Reutiliz. Rectang. Negro 25,4 x 17,8cm CON TAPA | G58: Nuevo | H58: 88079
B59: 0052DARPR130 | C59: DP45121013099S | D59: caja | E59: 100 | F59: CONTENEDOR Reutiliz. Rectang. Negro 30,5 x 25,4cm CON TAPA | G59: Nuevo | H59: 108125
B60: 0052DARPC0032 | C60: DP47073299S | D60: caja | E60: 100 | F60: CONTENEDOR Reutiliz. Circular Negro 17,8 diam (32oz) CON TAPA | G60: Nuevo | H60: 58458
B61: 0052DARPC0064 | C61: DP470856499S | D61: caja | E61: 100 | F61: CONTENEDOR Reutiliz. Circular Negro 21,6 diam (64)oz) CON TAPA | G61: Nuevo | H61: 86053
B62: 0052DARPR012 | C62: DP470551299S | D62: caja | E62: 100 | F62: CONTENEDOR REUTILIZABLE CIRCULAR 5.5 12oz NEGRO C/Tapa | G62: Nuevo | H62: 39113
B63: LOS PRECIOS SON MAS IVA

Sheet Linea BIO-Bagazo
B2: LISTA DE PRECIOS de 26 DE OCTUBRE 2026 (B18)
C3: COMPAÑÍA LA PILARICA S. A. - DARNEL WWW.DARNELGROUP.COM
B4: CODIGO PILARICA | C4: CODIGO DARNEL | D4: U/M | E4: C/U | F4: DESCRIPCION | G4: COMENTARIO | H4: PRECIO BULTO $
B5: BAGAZO - BIODEGRADABLE
B6: 0051VAR00020 | D6: caja | E6: 600 | F6: ENVASE REDONDO P180 | G6: diam 180x65mm | H6: =_xlfn.XLOOKUP(B6,lista!A:A,lista!C:C,0,0) -> 191292
B7: 0051VAR00023 | D7: caja | E7: 600 | F7: TAPA PARA ENVASE REDONDO | G7: diam 180x30mm | H7: =_xlfn.XLOOKUP(B7,lista!A:A,lista!C:C,0,0) -> 78657
B8: 0051VAR00021 | D8: caja | E8: 800 | F8: BANDEJA RECTANGULAR | G8: 235x145x20mm | H8: =_xlfn.XLOOKUP(B8,lista!A:A,lista!C:C,0,0) -> 163089
B9: 0051VAR00024 | D9: caja | E9: 800 | F9: TAPA PARA BANDEJA RECTANGULAR | G9: 235x145x25mm | H9: =_xlfn.XLOOKUP(B9,lista!A:A,lista!C:C,0,0) -> 149668
B10: 0051VAR00022 | D10: caja | E10: 500 | F10: BANDEJA OVALADA | G10: 245x165x35mm | H10: =_xlfn.XLOOKUP(B10,lista!A:A,lista!C:C,0,0) -> 112869
B11: 0051VAR00025 | D11: caja | E11: 500 | F11: TAPA BANDEJA OVALADA | G11: 245x165x40mm | H11: =_xlfn.XLOOKUP(B11,lista!A:A,lista!C:C,0,0) -> 148589
B12: FILM PVC BIO
B13: 0027BIO38100 | C13: SA4B35-380-1000 | D13: Rol | E13: 1 | F13: PVC BIO DARNEL WRAP 35X38X1000 MTS | G13: Nuevo | H13: 30219
B14: 0027BIO28100 | C14: SA4B31-280-100DR | D14: Rol | E14: 1 | F14: PVC BIO DARNEL WRAP 31X28X100MTS | G14: Nuevo | H14: 2841
B15: 0027BIO28300 | C15: SA4B31-280-300D | D15: Rol | E15: 1 | F15: PVC BIO DARNEL WRAP 31X28X300 MTS | G15: Nuevo | H15: 8914
B16: VAJILLA DESCARTABLE BIO
B17: 0041TAMB0001 | C17: DB81102003 | D17: CAJ | E17: 1000 | F17: TAMI TENEDOR NATURAL BIO 50P x 20u. | G17: Nuevo | H17: 36363
B18: 0041TAMB0002 | C18: DB82102003 | D18: CAJ | E18: 1000 | F18: TAMI CUCHILLO NATURAL BIO 50P x 20u. | G18: Nuevo | H18: 33363
B19: 0041TAMB0003 | C19: DB83102003 | D19: CAJ | E19: 1000 | F19: TAMI CUCHARA DULCERA NATURAL BIO 50P x 20u. | G19: Nuevo | H19: 32527
B20: PORTA COMIDAS DE EXPANDIDO BIO
B21: 0034DARPB001 | C21: D403103LNW | D21: CAJ | E21: 200 | F21: PORTACOMIDA JL-1 BIO | G21: Nuevo | H21: =_xlfn.XLOOKUP(B21,lista!A:A,lista!C:C,0,0) -> 45748
B22: 0034DARPB002 | C22: D403103NW | D22: CAJ | E22: 200 | F22: PORTACOMIDA J-1 BIO | G22: Nuevo | H22: =_xlfn.XLOOKUP(B22,lista!A:A,lista!C:C,0,0) -> 49737
B23: 0034DARPB003 | C23: D405103NW | D23: CAJ | E23: 200 | F23: PORTACOMIDA P-1 BIO | G23: Nuevo | H23: =_xlfn.XLOOKUP(B23,lista!A:A,lista!C:C,0,0) -> 52087
B24: 0034DARPB004 | C24: D405303NW | D24: CAJ | E24: 200 | F24: PORTACOMIDA P-3 (3 Div.) BIO | G24: Nuevo | H24: =_xlfn.XLOOKUP(B24,lista!A:A,lista!C:C,0,0) -> 50977
B25: VASOS Y CONTENEDORES TERMICOS BIODEGRADABLE
B26: 0034DARB0006 | C26: D690603N | D26: caja | E26: 1000 | F26: VASO ESPUMADO 6 oz - BIO paq x 20u CAJ x1000 | G26: Nuevo | H26: =_xlfn.XLOOKUP(B26,lista!A:A,lista!C:C,0,0) -> 0
B27: 0034DARB0008 | C27: D690803N | D27: caja | E27: 1000 | F27: VASO ESPUMADO 8 oz - BIO paq x 20u CAJ x1001 | G27: Nuevo | H27: =_xlfn.XLOOKUP(B27,lista!A:A,lista!C:C,0,0) -> 0
B28: LINEA NATURALS BAGAZO
B29: 0089DARCHBAG1032 | D29: caja | E29: 480 | F29: PLATO HONDO DARNEL NAT. BAGAZO 32oz 930ml paq20 | H29: 45008.447
B30: 0089DARCHBAG2032 | D30: caja | E30: 480 | F30: TAPA DARNEL NAT PLATO HONDO BAGAZO 32oz paq20 | H30: 37327.712
B31: 0089DARCHBAG5500 | D31: caja | E31: 500 | F31: BAND. BAGAZO DARNEL NATURALS 500ml Paq 125x4 | G31: 174x120x38mm | H31: 36310.215
B32: 0089DARCHBAG5600 | D32: caja | E32: 300 | F32: BAND. BAGAZO CAÑA DARNEL NATURALS paq50x6 | G32: 242x182x28mm | H32: 36173.154
B33: 0089DARCHBAG5700 | D33: caja | E33: 500 | F33: BAND. BAGAZO CAÑA DARNEL NATURALS paq125x4 | G33: 275x205x25mm | H33: 64660.1
B34: 0089DARCHBAG6006 | D34: caja | E34: 1000 | F34: BAND. SUSHI T6 DARNEL NATURALS BAGAZO paq125x8 | G34: 221x92x21mm | H34: 51056.269
B35: 0089DARCHBAM2000 | D35: caja | E35: 2000 | F35: COPA SOUFFLE 0.5 oz DARNEL NAT BAMBOO paq50x40 | H35: 20421
B36: 0089DARCHBAM2001 | D36: caja | E36: 2000 | F36: COPA SOUFFLE 1oz DARNEL NAT BAMBOO paq50x40 | H36: 21526.804
B37: 0089DARCHBAM2002 | D37: caja | E37: 2000 | F37: COPA SOUFFFLE 1.5 oz DARNEL NAT BAMBOO paq50x40 | H37: 23237.406
B38: 0089DARCHBAM2003 | D38: caja | E38: 2000 | F38: COPA SOUFFLE 2oz DARNEL NAT, BAMBOO paq50x40 | H38: 24639
B39: 0089DARCHNAT0240 | D39: caja | E39: 300 | F39: CAJA C/VENT. #2 24oz DARNEL NATURALS MOCA paq50x6 | G39: 168x118x45mm | H39: 39372.136
B40: 0089DARCHNAT0320 | D40: caja | E40: 300 | F40: CAJA C/VENT 32oz DARNEL NATURAL MOCA Paq50/X6 | G40: 198x138x50mm | H40: 57969.982
B41: 0089DARCHNAT1000 | D41: caja | E41: 200 | F41: PORTA COMIDA HOTDOG DARNEL NAT MOCA BLANCO Paq50 | H41: 16335
B42: 0089DARCHNAT2320 | D42: caja | E42: 500 | F42: CONTENEDOR DARNEL NATURAL 32oz MOCA PQX50/X10 | H42: 54580.84
B43: 0089DARCHNAT3320 | D43: caja | E43: 500 | F43: TAPA CONTENEDOR NATURAL 26 Y 32 MOCA PQX25/X20 | H43: 66377.77
B44: 0089DARCHNAT4000 | D44: caja | E44: 1000 | F44: BANDEJA DARNEL NATURALS#1 PQX125/X8 | H44: 65116.036
B45: 0089DARCHNAT4010 | D45: caja | E45: 1000 | F45: BANDEJA DARNEL NATURALS #10 PAQX25/X8 | H45: 115909.79
B46: 0089DARCHNAT5000 | D46: caja | E46: 250 | F46: PORTACO DARNEL NATURALS 950 ml X2DIV PQ125/X2 | H46: 34144.144
B47: 0089DARCHNAT5600 | D47: caja | E47: 400 | F47: PORTA COMIDA DARNEL NATURALS 600 ml PQX50/X8 | H47: 36078.237
B48: 0089DARCHPET1001 | D48: caja | E48: 2000 | F48: TAPA PET p/COPA SOUFFLE 0.5/1oz DARNEL NAT. Paq50 | H48: 27080
B49: 0089DARCHPET1002 | D49: caja | E49: 2000 | F49: TAPA PET p/COPA SOUFFLE 1.5/2 oz DARNEL NAT. Paq50 | H49: 38042
B50: 0089DARCHPETD600 | D50: caja | E50: 1000 | F50: DOMO PET DARNEL NATURALS SUSHI T6 PQX125/X8 | G50: 225x99x32mm | H50: 56889
B51: 0089DARCHBAM4330 | D51: caja | E51: 300 | F51: TAPA CRISTAL Naturals Bowl 1300 cc 50un x 6 PQ. | H51: 46923.267
B52: 0089DARCHBAM4230 | D52: caja | E52: 300 | F52: BOWL DARNEL NATURALS 1300 cc Moca 50un x 6 PQ | H52: 86839.256
B53: 0089DARCHBAM4130 | D53: caja | E53: 300 | F53: BOWL DARNEL NATURALS 1300cc Bambo 50un x 6 PQ | H53: 88028.128
B54: 0089DARCHBAM4375 | D54: caja | E54: 300 | F54: TAPA CRISTAL NATURALS BOWL 750y1000cc 50un x 6 PQ | H54: 34142.342
B55: 0089DARCHBAM4210 | D55: caja | E55: 300 | F55: BOWL DARNEL NATURALS 1000cc MOCA 50un x 6 PQ | H55: 59707.782
B56: 0089DARCHBAM4034 | D56: caja | E56: 300 | F56: BOWL DARNEL NATURALS 34 Oz BAMBOO 50un x 6 PQ | H56: 59707
B57: LOS PRECIOS SON MAS IVA

Sheet Vajilla Madera
B2: LISTA DE PRECIOS de 26 DE OCTUBRE 2026 (B18)
C3: COMPAÑÍA LA PILARICA S. A. - DARNEL WWW.DARNELGROUP.COM
B4: CODIGO PILARICA | C4: CODIGO DARNEL | D4: U/M | E4: C/U | F4: DESCRIPCION | G4: COMENT. | H4: Precio Bulto $
B5: LINEA VAJILLA EN MADERA Y ACCESORIOS
B6: 0041DAR00110 | D6: Caja | E6: 1000 | F6: TENEDOR DE MADERA 16CM DARNEL NAT 10 PAQ x 100un | H6: 49424.68
B7: 0041DAR00111 | D7: Caja | E7: 1000 | F7: CUCHILLO DE MADERA 16CM DARNEL NAT 10 PAQ x 100un | H7: 37691.3
B8: 0041DAR00140 | D8: Caja | E8: 1000 | F8: CUCHARA DE MADERA 14CM DARNEL NAT 10 PAQ x 100un | H8: 37820.86
B9: 0041DAR00160 | D9: Caja | E9: 1000 | F9: CUCHARA DE MADERA 16CM DARNEL NAT 10 PAQ x 100un | H9: 74900
B10: 0041DAR50001 | D10: Caja | E10: 12000 | F10: MEZCLADOR DOBLE 12.7cm (5") DARNEL BIO NAT S/ENVOLT. CAJ 12000 Un | H10: 63113.18
B11: 0041DAR50002 | D11: Caja | E11: 10000 | F11: MEZCLADOR 12.7 cm (5") DARNEL BIO NATURAL S/ENVOLT. CAJ 10000 Un | H11: 37725.98
B12: 0041DAR50007 | D12: Caja | F12: MEZCLADOR BEB. CALIENTE 17.8cm (7") DARNEL BIO NAT. S/ENVOL CAJ 1 | H12: 47530.036
B13: 0041DAR50008 | D13: Caja | E13: 5000 | F13: MEZCLADOR COCKTAIL 20.3 cm (8") DARNEL BIO NAT S/ENVOLT CAJ x 5000un | H13: 42780.78
B14: 0041DAR60001 | D14: Caja | E14: 5000 | F14: PITILLO JUMBO 19.7 cm (7.3/4") DARNEL BIO NATURAL S/ENVOLT CAJ 5000un | H14: 52836.634
B15: 0041DAR60002 | D15: Caja | E15: 5000 | F15: PITILLO JUMBO 19.7cm (7.3/4") DARNEL BIO NATURAL C/ENVOLT CAJ 5000un | H15: 75113.978
B16: 0041DAR60005 | D16: Caja | E16: 2000 | F16: PITILLO JUMBO 26.0cm (10.1/4") DARNEL BIO NATURAL S/ENVOLT CAJ 2000un | H16: 29706.601
B17: 0041DAR60006 | D17: Caja | E17: 2000 | F17: PITILLO JUMBO 26 CM (10.1/4") DARNEL BIO NATURAL C/ENVOLT CAJ 2000un | H17: 40132.818
B18: 0041DAR60008 | D18: Caja | E18: 1200 | F18: PITILLO GIGANTE 26 CM (10.1/4") DARNEL BIO NATURAL C/ENVOLT CAJ 1200un | H18: 36381.159
B19: 0041DAR60009 | D19: Caja | E19: 7500 | F19: PITILLO GIGANTE 19.7 cm (7.3/4") DARNEL BIO NATURAL S/ENVOLT CAJ 7500un | H19: 135250.48
B20: 0041DAR60010 | D20: Caja | E20: 7500 | F20: PITILLO GIGANTE 19.7cm (7.3/4) DARNEL BIO NATURAL C/ENVOLT CAJ 7500un | H20: 177841.82
B21: LOS PRECIOS SON MAS IVA

Sheet Vaso Polipapel
B2: LISTA DE PRECIOS de 26 DE OCTUBRE 2026 (B18)
C3: COMPAÑÍA LA PILARICA S. A. - DARNEL WWW.DARNELGROUP.COM
B4: CODIGO PILARICA | C4: CODIGO DARNEL | D4: U/M | E4: C/U | F4: DESCRIPCION | G4: COMENT. | H4: Precio Bulto $
B5: LINEA VASOS POLIPAPEL
B6: 0089DARCHP0L004 | C6: RPN060204201 | D6: Caja | E6: 1000 | F6: VASO POLIPAPEL DARNEL NATURALS 4 oz BLANCO BEB CALIENTE | G6: 20paq x 50u | H6: 28670
B7: 0089DARCHP0L404 | C7: RPN060204201! | D7: Caja | E7: 1000 | F7: VASO POLIPAPEL DARNEL NATURAL 4 oz DISEÑO BEB CALIENTE | G7: 20paq x 50u | H7: 28670
B8: 0089DARCHPOL006 | C8: RPN060206201 | D8: Caja | E8: 1000 | F8: VASO POLIPAPEL DARNEL NATURALS 6 oz BLANCO BEB CALIENTE | G8: 20paq x 50u | H8: 32739
B9: 0089DARCHPOL406 | C9: RPN060206201! | D9: Caja | E9: 1000 | F9: VASO POLIPAPEL DARNEL NATURALS 6 oz DISEÑO BEB CALIENTE | G9: 20paq x 50u | H9: 33277
B10: 0089DARCHPOLT106 | C10: RPN0602062T | D10: Caja | E10: 1000 | F10: TAPA VASO POLIPAPEL NATURAL 6 oz BEB. CALIENTE | G10: 20paq x 50u | H10: 32439
B11: 0089DARCHPOL108 | C11: RPN060208P110 | D11: Caja | E11: 500 | F11: VASO POLIPAPEL DARNEL NATURAL 8 oz NEGRO Con PROTECTOR | G11: 20paq x 25u | H11: 65256
B12: 0089DARCHPOL408 | C12: RPN060208201! | D12: Caja | E12: 1000 | F12: VASO POLIPAPEL DARNEL NATURAL 8 oz DISEÑO BEB CALIENTE | G12: 20paq x 50u | H12: 52543
B13: 0089DARCHPOL208 | C13: RPN060208P102 | D13: Caja | E13: 500 | F13: VASO POLIPAPEL DARNEL NATURAL 8 oz MOCA con PROTECTOR | G13: 20paq x 25u | H13: 65256
B14: 0089DARCHPOLT108 | C14: RPN0602082T | D14: Caja | E14: 1000 | F14: TAPA VASO POLIPAPEL NATURAL 8 y 12oz BEB. CALIENTE | G14: 20paq x 50u | H14: 38640
B15: 0089DARCHPOL011 | C15: RPN060112201| | D15: Caja | E15: 1000 | F15: VASO POLIPAPEL DARNEL NATURAL 12 oz BLANCO BEB. FRIA | G15: 20paq x 50u | H15: 64664
B16: 0089DARCHPOL012 | C16: RPN060212201 | D16: Caja | E16: 1000 | F16: VASO POLIPAPEL DARNEL NATURAL 12 oz BLANCO BEB. CALIENTE | G16: 20paq x 50u | H16: 62520
B17: 0089DARCHPOL312 | C17: RPN060212201! | D17: Caja | E17: 1000 | F17: VASO POLIPAPEL DARNEL NATURAL 12 oz DISEÑO BEB. CALIENTE | G17: 20paq x 50u | H17: 64634
... B22: 0089DARCHPOLT016 | C22: RPN0601162T | D22: Caja | E22: 1000 | F22: TAPA VASO POLIPAPEL DARNEL NATURAL 16 oz BEBIDA FRIA | G22: 20paq x 50u | H22: 38943
B23: LOS PRECIOS SON MAS IVA

Sheet Band. Envolvibles Aut.

Sheet Hoja2
